Workbook

Sheet 📊 Resumen
C1: IREMI REMESAS RESUMEN GENERAL
A5: Mes | B5: Ops SELL | C5: Ops BUY | D5: Vol. CLP | E5: Gan. Bruta | F5: Gastos | G5: Gan. Neta
A6: Ago 2025 | B6: =COUNTIF('Agosto 2025'!B2:B61,"SELL") | C6: =COUNTIF('Agosto 2025'!B2:B61,"BUY") | D6: =SUMIF('Agosto 2025'!B2:B61,"SELL",'Agosto 2025'!D2:D61) | E6: =SUMIF('Agosto 2025'!B2:B61,"SELL",'Agosto 2025'!R2:R61) | F6: =SUMIF('💰 Gastos'!B3:B59,"Ago-25",'💰 Gastos'!E3:E59) | G6: =E6-F6
A7: Sep 2025 | B7: =COUNTIF('Septiembre 2025'!B2:B104,"SELL") | C7: =COUNTIF('Septiembre 2025'!B2:B104,"BUY") | D7: =SUMIF('Septiembre 2025'!B2:B104,"SELL",'Septiembre 2025'!D2:D104) | E7: =SUMIF('Septiembre 2025'!B2:B104,"SELL",'Septiembre 2025'!R2:R104) | F7: =SUMIF('💰 Gastos'!B3:B59,"Sep-25",'💰 Gastos'!E3:E59) | G7: =E7-F7
A8: Oct 2025 | B8: =COUNTIF('Octubre 2025'!B2:B110,"SELL") | C8: =COUNTIF('Octubre 2025'!B2:B110,"BUY") | D8: =SUMIF('Octubre 2025'!B2:B110,"SELL",'Octubre 2025'!D2:D110) | E8: =SUMIF('Octubre 2025'!B2:B110,"SELL",'Octubre 2025'!R2:R110) | F8: =SUMIF('💰 Gastos'!B3:B59,"Oct-25",'💰 Gastos'!E3:E59) | G8: =E8-F8
A9: Nov 2025 | B9: =COUNTIF('Noviembre 2025'!B2:B126,"SELL") | C9: =COUNTIF('Noviembre 2025'!B2:B126,"BUY") | D9: =SUMIF('Noviembre 2025'!B2:B126,"SELL",'Noviembre 2025'!D2:D126) | E9: =SUMIF('Noviembre 2025'!B2:B126,"SELL",'Noviembre 2025'!R2:R126) | F9: =SUMIF('💰 Gastos'!B3:B59,"Nov-25",'💰 Gastos'!E3:E59) | G9: =E9-F9
A10: Dic 2025 | B10: =COUNTIF('Diciembre 2025'!B2:B161,"SELL") | C10: =COUNTIF('Diciembre 2025'!B2:B161,"BUY") | D10: =SUMIF('Diciembre 2025'!B2:B161,"SELL",'Diciembre 2025'!D2:D161) | E10: =SUMIF('Diciembre 2025'!B2:B161,"SELL",'Diciembre 2025'!R2:R161) | F10: =SUMIF('💰 Gastos'!B3:B59,"Dic-25",'💰 Gastos'!E3:E59) | G10: =E10-F10
A11: Ene 2026 | B11: =COUNTIF('Enero 2026'!B2:B163,"SELL") | C11: =COUNTIF('Enero 2026'!B2:B163,"BUY") | D11: =SUMIF('Enero 2026'!B2:B163,"SELL",'Enero 2026'!D2:D163) | E11: =SUMIF('Enero 2026'!B2:B163,"SELL",'Enero 2026'!R2:R163) | F11: =SUMIF('💰 Gastos'!B3:B59,"Ene-26",'💰 Gastos'!E3:E59) | G11: =E11-F11
A12: Feb 2026 | B12: =COUNTIF('Febrero 2026'!B2:B171,"SELL") | C12: =COUNTIF('Febrero 2026'!B2:B171,"BUY") | D12: =SUMIF('Febrero 2026'!B2:B171,"SELL",'Febrero 2026'!D2:D171) | E12: =SUMIF('Febrero 2026'!B2:B171,"SELL",'Febrero 2026'!R2:R171) | F12: =SUMIF('💰 Gastos'!B3:B59,"Feb-26",'💰 Gastos'!E3:E59) | G12: =E12-F12
A13: Mar 2026 | B13: =COUNTIF('Marzo 2026'!B2:B131,"SELL") | C13: =COUNTIF('Marzo 2026'!B2:B131,"BUY") | D13: =SUMIF('Marzo 2026'!B2:B131,"SELL",'Marzo 2026'!D2:D131) | E13: =SUMIF('Marzo 2026'!B2:B131,"SELL",'Marzo 2026'!R2:R131) | F13: =SUMIF('💰 Gastos'!B3:B59,"Mar-26",'💰 Gastos'!E3:E59) | G13: =E13-F13
A14: Abr 2026 | B14: =COUNTIF('Abril 2026'!B2:B201,"SELL") | C14: =COUNTIF('Abril 2026'!B2:B201,"BUY") | D14: =SUMIF('Abril 2026'!B2:B201,"SELL",'Abril 2026'!D2:D201) | E14: =SUMIF('Abril 2026'!B2:B201,"SELL",'Abril 2026'!R2:R201) | F14: =SUMIF('💰 Gastos'!B3:B59,"Abr-26",'💰 Gastos'!E3:E59) | G14: =E14-F14
A15: TOTAL | B15: =SUM(B6:B14) | C15: =SUM(C6:C14) | D15: =SUM(D6:D14) | E15: =SUM(E6:E14) | F15: =SUM(F6:F14) | G15: =SUM(G6:G14)

Sheet Agosto 2025
A1: N° | B1: Tipo | C1: Fecha | D1: Monto CLP | E1: USDT/CLP Compra | F1: USDT/CLP Venta | G1: USDT Mov | H1: Tax Binance | I1: Capital USDT | J1: Tasa Destino | K1: Tasa Real | L1: Tasa IREMI | M1: Valor Destino | N1: Comentario | O1: % G USDT | P1: % G CLP | Q1: Ganancia USDT | R1: Ganancia CLP | S1: Acumulado SELL
A2: 1 | B2: BUY | C2: 45855 | D2: 20000 | E2: 971.99 | G2: 20.576343 | I2: 72.208434 | K2: =IF(AND(B2="SELL",E2>0,J2<>""),J2/E2,0) | M2: =IF(AND(B2="SELL",L2>0),D2*L2,0) | N2: inyeccion | O2: =IF(AND(B2="SELL",G2<>0),Q2/ABS(G2),0) | P2: =IF(AND(B2="SELL",D2>0),R2/D2,0) | Q2: =IF(AND(B2="SELL",D2>0,E2>0),(D2/E2)+G2,0) | R2: =IF(B2="SELL",Q2*F2,0) | S2: =R2
A3: 2 | B3: BUY | C3: 45865 | D3: 50000 | E3: 968.39 | G3: 51.63209 | I3: 72.208434 | K3: =IF(AND(B3="SELL",E3>0,J3<>""),J3/E3,0) | M3: =IF(AND(B3="SELL",L3>0),D3*L3,0) | N3: Inyeccion Cambio Rosalys Correg | O3: =IF(AND(B3="SELL",G3<>0),Q3/ABS(G3),0) | P3: =IF(AND(B3="SELL",D3>0),R3/D3,0) | Q3: =IF(AND(B3="SELL",D3>0,E3>0),(D3/E3)+G3,0) | R3: =IF(B3="SELL",Q3*F3,0) | S3: =S2+R3
A4: 3 | B4: SELL | C4: 45867 | D4: 10000 | E4: 968.39 | G4: -10 | I4: 62.208434 | J4: 164.5 | K4: =IF(AND(B4="SELL",E4>0,J4<>""),J4/E4,0) | M4: =IF(AND(B4="SELL",L4>0),D4*L4,0) | N4: Cambio Prueba Jesus | O4: =IF(AND(B4="SELL",G4<>0),Q4/ABS(G4),0) | P4: =IF(AND(B4="SELL",D4>0),R4/D4,0) | Q4: =IF(AND(B4="SELL",D4>0,E4>0),(D4/E4)+G4,0) | R4: =IF(B4="SELL",Q4*F4,0) | S4: =S3+R4
A5: 4 | B5: SELL | C5: 45873 | D5: 40000 | E5: 968.39 | G5: -41.65 | I5: -0.01791 | J5: 168.3 | K5: =IF(AND(B5="SELL",E5>0,J5<>""),J5/E5,0) | M5: =IF(AND(B5="SELL",L5>0),D5*L5,0) | N5: Cambio Rosalys | O5: =IF(AND(B5="SELL",G5<>0),Q5/ABS(G5),0) | P5: =IF(AND(B5="SELL",D5>0),R5/D5,0) | Q5: =IF(AND(B5="SELL",D5>0,E5>0),(D5/E5)+G5,0) | R5: =IF(B5="SELL",Q5*F5,0) | S5: =S4+R5
A6: 5 | B6: BUY | C6: 45874 | D6: 100000 | E6: 970.02 | G6: 103.09066 | I6: 123.64909 | K6: =IF(AND(B6="SELL",E6>0,J6<>""),J6/E6,0) | M6: =IF(AND(B6="SELL",L6>0),D6*L6,0) | N6: inyeccion | O6: =IF(AND(B6="SELL",G6<>0),Q6/ABS(G6),0) | P6: =IF(AND(B6="SELL",D6>0),R6/D6,0) | Q6: =IF(AND(B6="SELL",D6>0,E6>0),(D6/E6)+G6,0) | R6: =IF(B6="SELL",Q6*F6,0) | S6: =S5+R6
A7: 6 | B7: SELL | C7: 45874 | D7: 50000 | G7: -51.54 | I7: 72.109092 | J7: 170.8 | K7: =IF(AND(B7="SELL",E7>0,J7<>""),J7/E7,0) | M7: =IF(AND(B7="SELL",L7>0),D7*L7,0) | N7: Cambio Sr Jesus 30 y 20 Rosalys | O7: =IF(AND(B7="SELL",G7<>0),Q7/ABS(G7),0) | P7: =IF(AND(B7="SELL",D7>0),R7/D7,0) | Q7: =IF(AND(B7="SELL",D7>0,E7>0),(D7/E7)+G7,0) | R7: =IF(B7="SELL",Q7*F7,0) | S7: =S6+R7
A8: 7 | B8: BUY | C8: 45874 | D8: 50000 | E8: 973.24 | G8: 51.374789 | I8: 123.48388 | K8: =IF(AND(B8="SELL",E8>0,J8<>""),J8/E8,0) | M8: =IF(AND(B8="SELL",L8>0),D8*L8,0) | N8: inyeccion Jancy | O8: =IF(AND(B8="SELL",G8<>0),Q8/ABS(G8),0) | P8: =IF(AND(B8="SELL",D8>0),R8/D8,0) | Q8: =IF(AND(B8="SELL",D8>0,E8>0),(D8/E8)+G8,0) | R8: =IF(B8="SELL",Q8*F8,0) | S8: =S7+R8
A9: 8 | B9: SELL | C9: 45874 | D9: 50000 | G9: -46.1999 | I9: 77.283981 | J9: 175.515 | K9: =IF(AND(B9="SELL",E9>0,J9<>""),J9/E9,0) | M9: =IF(AND(B9="SELL",L9>0),D9*L9,0) | N9: Cambio Sr Jesus Jancy | O9: =IF(AND(B9="SELL",G9<>0),Q9/ABS(G9),0) | P9: =IF(AND(B9="SELL",D9>0),R9/D9,0) | Q9: =IF(AND(B9="SELL",D9>0,E9>0),(D9/E9)+G9,0) | R9: =IF(B9="SELL",Q9*F9,0) | S9: =S8+R9
A10: 9 | B10: BUY | C10: 45875 | D10: 50000 | E10: 980.99 | G10: 50.968919 | I10: 128.2529 | K10: =IF(AND(B10="SELL",E10>0,J10<>""),J10/E10,0) | M10: =IF(AND(B10="SELL",L10>0),D10*L10,0) | O10: =IF(AND(B10="SELL",G10<>0),Q10/ABS(G10),0) | P10: =IF(AND(B10="SELL",D10>0),R10/D10,0) | Q10: =IF(AND(B10="SELL",D10>0,E10>0),(D10/E10)+G10,0) | R10: =IF(B10="SELL",Q10*F10,0) | S10: =S9+R10
A11: 10 | B11: BUY | C11: 45875 | D11: 50000 | E11: 982.32 | G11: 50.89991 | I11: 179.15281 | K11: =IF(AND(B11="SELL",E11>0,J11<>""),J11/E11,0) | M11: =IF(AND(B11="SELL",L11>0),D11*L11,0) | O11: =IF(AND(B11="SELL",G11<>0),Q11/ABS(G11),0) | P11: =IF(AND(B11="SELL",D11>0),R11/D11,0) | Q11: =IF(AND(B11="SELL",D11>0,E11>0),(D11/E11)+G11,0) | R11: =IF(B11="SELL",Q11*F11,0) | S11: =S10+R11
A12: 11 | B12: SELL | C12: 45877 | D12: 10000 | E12: 982.32 | G12: -9.85 | I12: 169.30281 | J12: 178.8 | K12: =IF(AND(B12="SELL",E12>0,J12<>""),J12/E12,0) | L12: 0.176 | M12: =IF(AND(B12="SELL",L12>0),D12*L12,0) | N12: Inicio IREMI - Cambio Angel | O12: =IF(AND(B12="SELL",G12<>0),Q12/ABS(G12),0) | P12: =IF(AND(B12="SELL",D12>0),R12/D12,0) | Q12: =IF(AND(B12="SELL",D12>0,E12>0),(D12/E12)+G12,0) | R12: =IF(B12="SELL",Q12*F12,0) | S12: =S11+R12
A13: 12 | B13: SELL | C13: 45878 | D13: 10000 | E13: 982.32 | G13: -9.98 | I13: 159.32281 | J13: 180.2 | K13: =IF(AND(B13="SELL",E13>0,J13<>""),J13/E13,0) | L13: 0.18 | M13: =IF(AND(B13="SELL",L13>0),D13*L13,0) | N13: cambio paula | O13: =IF(AND(B13="SELL",G13<>0),Q13/ABS(G13),0) | P13: =IF(AND(B13="SELL",D13>0),R13/D13,0) | Q13: =IF(AND(B13="SELL",D13>0,E13>0),(D13/E13)+G13,0) | R13: =IF(B13="SELL",Q13*F13,0) | S13: =S12+R13
A14: 13 | B14: SELL | C14: 45878 | D14: 60000 | E14: 982.32 | G14: -59.25 | I14: 100.07281 | J14: 182.5 | K14: =IF(AND(B14="SELL",E14>0,J14<>""),J14/E14,0) | L14: 0.18 | M14: =IF(AND(B14="SELL",L14>0),D14*L14,0) | N14: Cambio ucla | O14: =IF(AND(B14="SELL",G14<>0),Q14/ABS(G14),0) | P14: =IF(AND(B14="SELL",D14>0),R14/D14,0) | Q14: =IF(AND(B14="SELL",D14>0,E14>0),(D14/E14)+G14,0) | R14: =IF(B14="SELL",Q14*F14,0) | S14: =S13+R14
A15: 14 | B15: SELL | C15: 45878 | D15: 20000 | E15: 982.32 | G15: -19.53 | I15: 80.542811 | J15: 3.4181 | K15: =IF(AND(B15="SELL",E15>0,J15<>""),J15/E15,0) | L15: 0.0034 | M15: =IF(AND(B15="SELL",L15>0),D15*L15,0) | N15: Cambio armando a PEN | O15: =IF(AND(B15="SELL",G15<>0),Q15/ABS(G15),0) | P15: =IF(AND(B15="SELL",D15>0),R15/D15,0) | Q15: =IF(AND(B15="SELL",D15>0,E15>0),(D15/E15)+G15,0) | R15: =IF(B15="SELL",Q15*F15,0) | S15: =S14+R15
A16: 15 | B16: BUY | C16: 45879 | D16: 100000 | E16: 971.42 | G16: 102.94208 | I16: 183.48489 | K16: =IF(AND(B16="SELL",E16>0,J16<>""),J16/E16,0) | M16: =IF(AND(B16="SELL",L16>0),D16*L16,0) | O16: =IF(AND(B16="SELL",G16<>0),Q16/ABS(G16),0) | P16: =IF(AND(B16="SELL",D16>0),R16/D16,0) | Q16: =IF(AND(B16="SELL",D16>0,E16>0),(D16/E16)+G16,0) | R16: =IF(B16="SELL",Q16*F16,0) | S16: =S15+R16
A17: 16 | B17: SELL | C17: 45879 | D17: 40000 | E17: 971.42 | G17: -39.12 | I17: 144.36489 | J17: 182.511 | K17: =IF(AND(B17="SELL",E17>0,J17<>""),J17/E17,0) | L17: 0.1785 | M17: =IF(AND(B17="SELL",L17>0),D17*L17,0) | N17: Cambio Angel 2 | O17: =IF(AND(B17="SELL",G17<>0),Q17/ABS(G17),0) | P17: =IF(AND(B17="SELL",D17>0),R17/D17,0) | Q17: =IF(AND(B17="SELL",D17>0,E17>0),(D17/E17)+G17,0) | R17: =IF(B17="SELL",Q17*F17,0) | S17: =S16+R17
A18: 17 | B18: SELL | C18: 45879 | D18: 90000 | E18: 971.42 | G18: -89.95 | I18: 54.414895 | J18: 182.41 | K18: =IF(AND(B18="SELL",E18>0,J18<>""),J18/E18,0) | L18: 0.1823 | M18: =IF(AND(B18="SELL",L18>0),D18*L18,0) | N18: Cambio paula y rosalys | O18: =IF(AND(B18="SELL",G18<>0),Q18/ABS(G18),0) | P18: =IF(AND(B18="SELL",D18>0),R18/D18,0) | Q18: =IF(AND(B18="SELL",D18>0,E18>0),(D18/E18)+G18,0) | R18: =IF(B18="SELL",Q18*F18,0) | S18: =S17+R18
A19: 18 | B19: BUY | C19: 45879 | D19: 100000 | E19: 971.52 | G19: 102.93149 | I19: 157.34638 | K19: =IF(AND(B19="SELL",E19>0,J19<>""),J19/E19,0) | M19: =IF(AND(B19="SELL",L19>0),D19*L19,0) | O19: =IF(AND(B19="SELL",G19<>0),Q19/ABS(G19),0) | P19: =IF(AND(B19="SELL",D19>0),R19/D19,0) | Q19: =IF(AND(B19="SELL",D19>0,E19>0),(D19/E19)+G19,0) | R19: =IF(B19="SELL",Q19*F19,0) | S19: =S18+R19
A20: 19 | B20: SELL | C20: 45883 | D20: 40000 | E20: 971.52 | F20: 962.2 | G20: -40.13 | I20: 117.21638 | J20: 189.103 | K20: =IF(AND(B20="SELL",E20>0,J20<>""),J20/E20,0) | L20: 0.1895 | M20: =IF(AND(B20="SELL",L20>0),D20*L20,0) | N20: Cambio Yakari Rosalys | O20: =IF(AND(B20="SELL",G20<>0),Q20/ABS(G20),0) | P20: =IF(AND(B20="SELL",D20>0),R20/D20,0) | Q20: =IF(AND(B20="SELL",D20>0,E20>0),(D20/E20)+G20,0) | R20: =IF(B20="SELL",Q20*F20,0) | S20: =S19+R20
A21: 20 | B21: SELL | C21: 45885 | D21: 30000 | E21: 971.42 | F21: 972.5 | G21: -29.52 | I21: 159.69638 | J21: 190 | K21: =IF(AND(B21="SELL",E21>0,J21<>""),J21/E21,0) | L21: 0.187 | M21: =IF(AND(B21="SELL",L21>0),D21*L21,0) | N21: cambio paula | O21: =IF(AND(B21="SELL",G21<>0),Q21/ABS(G21),0) | P21: =IF(AND(B21="SELL",D21>0),R21/D21,0) | Q21: =IF(AND(B21="SELL",D21>0,E21>0),(D21/E21)+G21,0) | R21: =IF(B21="SELL",Q21*F21,0) | S21: =S20+R21
A22: 21 | B22: SELL | C22: 45885 | D22: 120000 | E22: 971.42 | F22: 972.5 | G22: -116.94 | I22: 22.180041 | J22: 191.3 | K22: =IF(AND(B22="SELL",E22>0,J22<>""),J22/E22,0) | L22: 0.187 | M22: =IF(AND(B22="SELL",L22>0),D22*L22,0) | N22: Cambio Angel 2 | O22: =IF(AND(B22="SELL",G22<>0),Q22/ABS(G22),0) | P22: =IF(AND(B22="SELL",D22>0),R22/D22,0) | Q22: =IF(AND(B22="SELL",D22>0,E22>0),(D22/E22)+G22,0) | R22: =IF(B22="SELL",Q22*F22,0) | S22: =S21+R22
A23: 22 | B23: SELL | C23: 45885 | D23: 10000 | E23: 971.42 | F23: 972.5 | G23: -9.95 | I23: 12.230041 | J23: 187.925 | K23: =IF(AND(B23="SELL",E23>0,J23<>""),J23/E23,0) | L23: 0.187 | M23: =IF(AND(B23="SELL",L23>0),D23*L23,0) | N23: Cambio Mama tia aracelis | O23: =IF(AND(B23="SELL",G23<>0),Q23/ABS(G23),0) | P23: =IF(AND(B23="SELL",D23>0),R23/D23,0) | Q23: =IF(AND(B23="SELL",D23>0,E23>0),(D23/E23)+G23,0) | R23: =IF(B23="SELL",Q23*F23,0) | S23: =S22+R23
A24: 23 | B24: BUY | C24: 45885 | D24: 150000 | E24: 972.28 | F24: 972.5 | G24: 154.52 | I24: 187.32638 | K24: =IF(AND(B24="SELL",E24>0,J24<>""),J24/E24,0) | M24: =IF(AND(B24="SELL",L24>0),D24*L24,0) | O24: =IF(AND(B24="SELL",G24<>0),Q24/ABS(G24),0) | P24: =IF(AND(B24="SELL",D24>0),R24/D24,0) | Q24: =IF(AND(B24="SELL",D24>0,E24>0),(D24/E24)+G24,0) | R24: =IF(B24="SELL",Q24*F24,0) | S24: =S23+R24
A25: 24 | B25: SELL | C25: 45885 | D25: 40000 | E25: 972.28 | F25: 972.5 | G25: -39.13 | I25: 127.62004 | J25: 191.4 | K25: =IF(AND(B25="SELL",E25>0,J25<>""),J25/E25,0) | L25: 0.187 | M25: =IF(AND(B25="SELL",L25>0),D25*L25,0) | N25: Cambio Mama | O25: =IF(AND(B25="SELL",G25<>0),Q25/ABS(G25),0) | P25: =IF(AND(B25="SELL",D25>0),R25/D25,0) | Q25: =IF(AND(B25="SELL",D25>0,E25>0),(D25/E25)+G25,0) | R25: =IF(B25="SELL",Q25*F25,0) | S25: =S24+R25
A26: 25 | B26: SELL | C26: 45887 | D26: 500000 | E26: 970.7 | F26: 972.5 | G26: -450.5 | I26: -302.30362 | J26: 17.89 | K26: =IF(AND(B26="SELL",E26>0,J26<>""),J26/E26,0) | L26: 0.0174 | M26: =IF(AND(B26="SELL",L26>0),D26*L26,0) | N26: cambio johan a mxn | O26: =IF(AND(B26="SELL",G26<>0),Q26/ABS(G26),0) | P26: =IF(AND(B26="SELL",D26>0),R26/D26,0) | Q26: =IF(AND(B26="SELL",D26>0,E26>0),(D26/E26)+G26,0) | R26: =IF(B26="SELL",Q26*F26,0) | S26: =S25+R26
A27: 26 | B27: BUY | C27: 45887 | D27: 500000 | E27: 970.7 | F27: 972.5 | G27: 515.0922 | I27: 212.78859 | K27: =IF(AND(B27="SELL",E27>0,J27<>""),J27/E27,0) | M27: =IF(AND(B27="SELL",L27>0),D27*L27,0) | O27: =IF(AND(B27="SELL",G27<>0),Q27/ABS(G27),0) | P27: =IF(AND(B27="SELL",D27>0),R27/D27,0) | Q27: =IF(AND(B27="SELL",D27>0,E27>0),(D27/E27)+G27,0) | R27: =IF(B27="SELL",Q27*F27,0) | S27: =S26+R27
A28: 27 | B28: SELL | C28: 45889 | D28: 50000 | E28: 970.7 | F28: 969.94 | G28: -47.67 | I28: 165.11859 | J28: 209.106 | K28: =IF(AND(B28="SELL",E28>0,J28<>""),J28/E28,0) | L28: 0.199 | M28: =IF(AND(B28="SELL",L28>0),D28*L28,0) | N28: cambio pinky | O28: =IF(AND(B28="SELL",G28<>0),Q28/ABS(G28),0) | P28: =IF(AND(B28="SELL",D28>0),R28/D28,0) | Q28: =IF(AND(B28="SELL",D28>0,E28>0),(D28/E28)+G28,0) | R28: =IF(B28="SELL",Q28*F28,0) | S28: =S27+R28
A29: 28 | B29: SELL | C29: 45891 | D29: 30000 | E29: 970.7 | F29: 969.94 | G29: -30.46 | I29: 134.65859 | J29: 213.385 | K29: =IF(AND(B29="SELL",E29>0,J29<>""),J29/E29,0) | L29: 0.2175 | M29: =IF(AND(B29="SELL",L29>0),D29*L29,0) | N29: Cambio Turale | O29: =IF(AND(B29="SELL",G29<>0),Q29/ABS(G29),0) | P29: =IF(AND(B29="SELL",D29>0),R29/D29,0) | Q29: =IF(AND(B29="SELL",D29>0,E29>0),(D29/E29)+G29,0) | R29: =IF(B29="SELL",Q29*F29,0) | S29: =S28+R29
A30: 29 | B30: SELL | C30: 45891 | D30: 30000 | E30: 970.7 | F30: 969.94 | G30: -30.5 | I30: 104.15859 | J30: 213.1 | K30: =IF(AND(B30="SELL",E30>0,J30<>""),J30/E30,0) | L30: 0.2175 | M30: =IF(AND(B30="SELL",L30>0),D30*L30,0) | N30: Cambio paula ucla | O30: =IF(AND(B30="SELL",G30<>0),Q30/ABS(G30),0) | P30: =IF(AND(B30="SELL",D30>0),R30/D30,0) | Q30: =IF(AND(B30="SELL",D30>0,E30>0),(D30/E30)+G30,0) | R30: =IF(B30="SELL",Q30*F30,0) | S30: =S29+R30
A31: 30 | B31: SELL | C31: 45892 | D31: 20000 | E31: 970.7 | F31: 969.94 | G31: -19.93 | I31: 84.228586 | J31: 206.65 | K31: =IF(AND(B31="SELL",E31>0,J31<>""),J31/E31,0) | L31: 0.207 | M31: =IF(AND(B31="SELL",L31>0),D31*L31,0) | N31: Cambio Angel 2 | O31: =IF(AND(B31="SELL",G31<>0),Q31/ABS(G31),0) | P31: =IF(AND(B31="SELL",D31>0),R31/D31,0) | Q31: =IF(AND(B31="SELL",D31>0,E31>0),(D31/E31)+G31,0) | R31: =IF(B31="SELL",Q31*F31,0) | S31: =S30+R31
A32: 31 | B32: SELL | C32: 45892 | D32: 25000 | E32: 970.7 | F32: 969.94 | G32: -24.93 | I32: 59.298586 | J32: 206.5 | K32: =IF(AND(B32="SELL",E32>0,J32<>""),J32/E32,0) | L32: 0.207 | M32: =IF(AND(B32="SELL",L32>0),D32*L32,0) | N32: cambio pinky | O32: =IF(AND(B32="SELL",G32<>0),Q32/ABS(G32),0) | P32: =IF(AND(B32="SELL",D32>0),R32/D32,0) | Q32: =IF(AND(B32="SELL",D32>0,E32>0),(D32/E32)+G32,0) | R32: =IF(B32="SELL",Q32*F32,0) | S32: =S31+R32
A33: 32 | B33: SELL | C33: 45892 | D33: 31250 | E33: 970.7 | F33: 969.94 | G33: -30.55 | I33: 28.748586 | J33: 3926.97 | K33: =IF(AND(B33="SELL",E33>0,J33<>""),J33/E33,0) | L33: 3.84 | M33: =IF(AND(B33="SELL",L33>0),D33*L33,0) | N33: cambio angel Col | O33: =IF(AND(B33="SELL",G33<>0),Q33/ABS(G33),0) | P33: =IF(AND(B33="SELL",D33>0),R33/D33,0) | Q33: =IF(AND(B33="SELL",D33>0,E33>0),(D33/E33)+G33,0) | R33: =IF(B33="SELL",Q33*F33,0) | S33: =S32+R33
A34: 33 | B34: BUY | D34: 220000 | E34: 962.96 | F34: 962.96 | G34: 228.46 | I34: 257.20859 | K34: =IF(AND(B34="SELL",E34>0,J34<>""),J34/E34,0) | M34: =IF(AND(B34="SELL",L34>0),D34*L34,0) | O34: =IF(AND(B34="SELL",G34<>0),Q34/ABS(G34),0) | P34: =IF(AND(B34="SELL",D34>0),R34/D34,0) | Q34: =IF(AND(B34="SELL",D34>0,E34>0),(D34/E34)+G34,0) | R34: =IF(B34="SELL",Q34*F34,0) | S34: =S33+R34
A35: 34 | B35: SELL | C35: 45893 | D35: 30000 | E35: 962.96 | F35: 962.96 | G35: -29.466 | I35: 227.74259 | J35: 208.7 | K35: =IF(AND(B35="SELL",E35>0,J35<>""),J35/E35,0) | L35: 0.205 | M35: =IF(AND(B35="SELL",L35>0),D35*L35,0) | N35: cambio angel | O35: =IF(AND(B35="SELL",G35<>0),Q35/ABS(G35),0) | P35: =IF(AND(B35="SELL",D35>0),R35/D35,0) | Q35: =IF(AND(B35="SELL",D35>0,E35>0),(D35/E35)+G35,0) | R35: =IF(B35="SELL",Q35*F35,0) | S35: =S34+R35
A36: 35 | B36: SELL | C36: 45893 | D36: 30000 | E36: 962.96 | F36: 962.96 | G36: -29.466 | I36: 198.27659 | J36: 208.7 | K36: =IF(AND(B36="SELL",E36>0,J36<>""),J36/E36,0) | L36: 0.205 | M36: =IF(AND(B36="SELL",L36>0),D36*L36,0) | N36: cambio paula jesus | O36: =IF(AND(B36="SELL",G36<>0),Q36/ABS(G36),0) | P36: =IF(AND(B36="SELL",D36>0),R36/D36,0) | Q36: =IF(AND(B36="SELL",D36>0,E36>0),(D36/E36)+G36,0) | R36: =IF(B36="SELL",Q36*F36,0) | S36: =S35+R36
A37: 36 | B37: SELL | C37: 45893 | D37: 40000 | E37: 962.96 | F37: 962.96 | G37: -39.88 | I37: 158.39659 | J37: 208.7 | K37: =IF(AND(B37="SELL",E37>0,J37<>""),J37/E37,0) | L37: 0.205 | M37: =IF(AND(B37="SELL",L37>0),D37*L37,0) | N37: cambio mama | O37: =IF(AND(B37="SELL",G37<>0),Q37/ABS(G37),0) | P37: =IF(AND(B37="SELL",D37>0),R37/D37,0) | Q37: =IF(AND(B37="SELL",D37>0,E37>0),(D37/E37)+G37,0) | R37: =IF(B37="SELL",Q37*F37,0) | S37: =S36+R37
A38: 37 | B38: BUY | C38: 45893 | D38: 106500 | E38: 960.79 | F38: 960.79 | G38: 110.78 | I38: 269.17659 | K38: =IF(AND(B38="SELL",E38>0,J38<>""),J38/E38,0) | M38: =IF(AND(B38="SELL",L38>0),D38*L38,0) | O38: =IF(AND(B38="SELL",G38<>0),Q38/ABS(G38),0) | P38: =IF(AND(B38="SELL",D38>0),R38/D38,0) | Q38: =IF(AND(B38="SELL",D38>0,E38>0),(D38/E38)+G38,0) | R38: =IF(B38="SELL",Q38*F38,0) | S38: =S37+R38
A39: 38 | B39: SELL | C39: 45895 | D39: 20000 | E39: 960.79 | F39: 960.79 | G39: -19.88 | I39: 249.29659 | J39: 3.42 | K39: =IF(AND(B39="SELL",E39>0,J39<>""),J39/E39,0) | L39: 0.0034 | M39: =IF(AND(B39="SELL",L39>0),D39*L39,0) | N39: cambio oshetrup | O39: =IF(AND(B39="SELL",G39<>0),Q39/ABS(G39),0) | P39: =IF(AND(B39="SELL",D39>0),R39/D39,0) | Q39: =IF(AND(B39="SELL",D39>0,E39>0),(D39/E39)+G39,0) | R39: =IF(B39="SELL",Q39*F39,0) | S39: =S38+R39
A40: 39 | B40: SELL | C40: 45896 | D40: 30000 | E40: 960.79 | F40: 960.79 | G40: -29.54 | I40: 219.75659 | J40: 215.301 | K40: =IF(AND(B40="SELL",E40>0,J40<>""),J40/E40,0) | L40: 0.212 | M40: =IF(AND(B40="SELL",L40>0),D40*L40,0) | N40: cambio zulehyka | O40: =IF(AND(B40="SELL",G40<>0),Q40/ABS(G40),0) | P40: =IF(AND(B40="SELL",D40>0),R40/D40,0) | Q40: =IF(AND(B40="SELL",D40>0,E40>0),(D40/E40)+G40,0) | R40: =IF(B40="SELL",Q40*F40,0) | S40: =S39+R40
A41: 40 | B41: SELL | C41: 45896 | D41: 20000 | E41: 960.79 | F41: 960.79 | G41: -20.15 | I41: 199.60659 | J41: 210.39 | K41: =IF(AND(B41="SELL",E41>0,J41<>""),J41/E41,0) | L41: 0.212 | M41: =IF(AND(B41="SELL",L41>0),D41*L41,0) | N41: cambio angel | O41: =IF(AND(B41="SELL",G41<>0),Q41/ABS(G41),0) | P41: =IF(AND(B41="SELL",D41>0),R41/D41,0) | Q41: =IF(AND(B41="SELL",D41>0,E41>0),(D41/E41)+G41,0) | R41: =IF(B41="SELL",Q41*F41,0) | S41: =S40+R41
A42: 41 | B42: SELL | C42: 45896 | D42: 20000 | E42: 960.79 | F42: 960.79 | G42: -19.9 | I42: 179.70659 | J42: 213 | K42: =IF(AND(B42="SELL",E42>0,J42<>""),J42/E42,0) | L42: 0.212 | M42: =IF(AND(B42="SELL",L42>0),D42*L42,0) | N42: cambio angel | O42: =IF(AND(B42="SELL",G42<>0),Q42/ABS(G42),0) | P42: =IF(AND(B42="SELL",D42>0),R42/D42,0) | Q42: =IF(AND(B42="SELL",D42>0,E42>0),(D42/E42)+G42,0) | R42: =IF(B42="SELL",Q42*F42,0) | S42: =S41+R42
A43: 42 | B43: SELL | C43: 45896 | D43: 40000 | E43: 960.79 | F43: 960.79 | G43: -39.65 | I43: 140.05659 | J43: 214.1 | K43: =IF(AND(B43="SELL",E43>0,J43<>""),J43/E43,0) | L43: 0.212 | M43: =IF(AND(B43="SELL",L43>0),D43*L43,0) | N43: cambio angel | O43: =IF(AND(B43="SELL",G43<>0),Q43/ABS(G43),0) | P43: =IF(AND(B43="SELL",D43>0),R43/D43,0) | Q43: =IF(AND(B43="SELL",D43>0,E43>0),(D43/E43)+G43,0) | R43: =IF(B43="SELL",Q43*F43,0) | S43: =S42+R43
A44: 43 | B44: SELL | C44: 45896 | D44: 66038 | E44: 960.79 | F44: 960.79 | G44: -65.05 | I44: 75.006586 | J44: 215.2 | K44: =IF(AND(B44="SELL",E44>0,J44<>""),J44/E44,0) | L44: 0.212 | M44: =IF(AND(B44="SELL",L44>0),D44*L44,0) | N44: cambio angel | O44: =IF(AND(B44="SELL",G44<>0),Q44/ABS(G44),0) | P44: =IF(AND(B44="SELL",D44>0),R44/D44,0) | Q44: =IF(AND(B44="SELL",D44>0,E44>0),(D44/E44)+G44,0) | R44: =IF(B44="SELL",Q44*F44,0) | S44: =S43+R44
A45: 44 | B45: SELL | C45: 45896 | D45: 13962 | E45: 960.79 | F45: 960.79 | G45: -13.88 | I45: 61.126586 | J45: 213.21 | K45: =IF(AND(B45="SELL",E45>0,J45<>""),J45/E45,0) | L45: 0.212 | M45: =IF(AND(B45="SELL",L45>0),D45*L45,0) | N45: cambio turale | O45: =IF(AND(B45="SELL",G45<>0),Q45/ABS(G45),0) | P45: =IF(AND(B45="SELL",D45>0),R45/D45,0) | Q45: =IF(AND(B45="SELL",D45>0,E45>0),(D45/E45)+G45,0) | R45: =IF(B45="SELL",Q45*F45,0) | S45: =S44+R45
A46: 45 | B46: BUY | C46: 45897 | D46: 350000 | E46: 970.5 | F46: 970.5 | G46: 360.63 | I46: 421.75659 | K46: =IF(AND(B46="SELL",E46>0,J46<>""),J46/E46,0) | M46: =IF(AND(B46="SELL",L46>0),D46*L46,0) | O46: =IF(AND(B46="SELL",G46<>0),Q46/ABS(G46),0) | P46: =IF(AND(B46="SELL",D46>0),R46/D46,0) | Q46: =IF(AND(B46="SELL",D46>0,E46>0),(D46/E46)+G46,0) | R46: =IF(B46="SELL",Q46*F46,0) | S46: =S45+R46
A47: 46 | B47: SELL | C47: 45897 | D47: 140000 | E47: 970.5 | F47: 970.5 | G47: -138 | I47: 283.75659 | J47: 206.58 | K47: =IF(AND(B47="SELL",E47>0,J47<>""),J47/E47,0) | L47: 0.21 | M47: =IF(AND(B47="SELL",L47>0),D47*L47,0) | N47: cambio angel | O47: =IF(AND(B47="SELL",G47<>0),Q47/ABS(G47),0) | P47: =IF(AND(B47="SELL",D47>0),R47/D47,0) | Q47: =IF(AND(B47="SELL",D47>0,E47>0),(D47/E47)+G47,0) | R47: =IF(B47="SELL",Q47*F47,0) | S47: =S46+R47
A48: 47 | B48: SELL | C48: 45897 | D48: 50000 | E48: 970.5 | F48: 970.5 | G48: -50.82 | I48: 232.93659 | J48: 206.58 | K48: =IF(AND(B48="SELL",E48>0,J48<>""),J48/E48,0) | L48: 0.21 | M48: =IF(AND(B48="SELL",L48>0),D48*L48,0) | N48: cambio pinky | O48: =IF(AND(B48="SELL",G48<>0),Q48/ABS(G48),0) | P48: =IF(AND(B48="SELL",D48>0),R48/D48,0) | Q48: =IF(AND(B48="SELL",D48>0,E48>0),(D48/E48)+G48,0) | R48: =IF(B48="SELL",Q48*F48,0) | S48: =S47+R48
A49: 48 | B49: SELL | C49: 45898 | D49: 50000 | E49: 970.5 | F49: 970.5 | G49: -49.65 | I49: 183.28659 | J49: 205.4 | K49: =IF(AND(B49="SELL",E49>0,J49<>""),J49/E49,0) | L49: 0.204 | M49: =IF(AND(B49="SELL",L49>0),D49*L49,0) | N49: cambio paula | O49: =IF(AND(B49="SELL",G49<>0),Q49/ABS(G49),0) | P49: =IF(AND(B49="SELL",D49>0),R49/D49,0) | Q49: =IF(AND(B49="SELL",D49>0,E49>0),(D49/E49)+G49,0) | R49: =IF(B49="SELL",Q49*F49,0) | S49: =S48+R49
A50: 49 | B50: SELL | C50: 45898 | D50: 30000 | E50: 970.5 | F50: 970.5 | G50: -29.84 | I50: 153.44659 | J50: 205.03 | K50: =IF(AND(B50="SELL",E50>0,J50<>""),J50/E50,0) | L50: 0.204 | M50: =IF(AND(B50="SELL",L50>0),D50*L50,0) | N50: cambio mama | O50: =IF(AND(B50="SELL",G50<>0),Q50/ABS(G50),0) | P50: =IF(AND(B50="SELL",D50>0),R50/D50,0) | Q50: =IF(AND(B50="SELL",D50>0,E50>0),(D50/E50)+G50,0) | R50: =IF(B50="SELL",Q50*F50,0) | S50: =S49+R50
A51: 50 | B51: SELL | C51: 45898 | D51: 40000 | E51: 970.5 | F51: 970.5 | G51: -40.49 | I51: 112.95659 | J51: 201.5 | K51: =IF(AND(B51="SELL",E51>0,J51<>""),J51/E51,0) | L51: 0.204 | M51: =IF(AND(B51="SELL",L51>0),D51*L51,0) | N51: cambio paula | O51: =IF(AND(B51="SELL",G51<>0),Q51/ABS(G51),0) | P51: =IF(AND(B51="SELL",D51>0),R51/D51,0) | Q51: =IF(AND(B51="SELL",D51>0,E51>0),(D51/E51)+G51,0) | R51: =IF(B51="SELL",Q51*F51,0) | S51: =S50+R51
A52: 51 | B52: SELL | C52: 45898 | D52: 44500 | E52: 970.5 | F52: 970.5 | G52: -43.93 | I52: 69.026586 | J52: 200 | K52: =IF(AND(B52="SELL",E52>0,J52<>""),J52/E52,0) | L52: 0.197 | M52: =IF(AND(B52="SELL",L52>0),D52*L52,0) | N52: cambio stefi | O52: =IF(AND(B52="SELL",G52<>0),Q52/ABS(G52),0) | P52: =IF(AND(B52="SELL",D52>0),R52/D52,0) | Q52: =IF(AND(B52="SELL",D52>0,E52>0),(D52/E52)+G52,0) | R52: =IF(B52="SELL",Q52*F52,0) | S52: =S51+R52
A53: 52 | B53: SELL | C53: 45899 | D53: 20000 | E53: 970.5 | F53: 970.5 | G53: -19.44 | I53: 49.586586 | J53: 198.51 | K53: =IF(AND(B53="SELL",E53>0,J53<>""),J53/E53,0) | L53: 0.193 | M53: =IF(AND(B53="SELL",L53>0),D53*L53,0) | N53: cambio paula | O53: =IF(AND(B53="SELL",G53<>0),Q53/ABS(G53),0) | P53: =IF(AND(B53="SELL",D53>0),R53/D53,0) | Q53: =IF(AND(B53="SELL",D53>0,E53>0),(D53/E53)+G53,0) | R53: =IF(B53="SELL",Q53*F53,0) | S53: =S52+R53
A54: 53 | B54: SELL | C54: 45899 | D54: 50000 | E54: 970.5 | F54: 970.5 | G54: -47.19 | I54: 2.396586 | J54: 201.03 | K54: =IF(AND(B54="SELL",E54>0,J54<>""),J54/E54,0) | L54: 0.193 | M54: =IF(AND(B54="SELL",L54>0),D54*L54,0) | N54: cambio francisco | O54: =IF(AND(B54="SELL",G54<>0),Q54/ABS(G54),0) | P54: =IF(AND(B54="SELL",D54>0),R54/D54,0) | Q54: =IF(AND(B54="SELL",D54>0,E54>0),(D54/E54)+G54,0) | R54: =IF(B54="SELL",Q54*F54,0) | S54: =S53+R54
A55: 54 | B55: BUY | C55: 45899 | D55: 300000 | E55: 974.14 | F55: 974.14 | G55: 307.96 | I55: 310.35659 | K55: =IF(AND(B55="SELL",E55>0,J55<>""),J55/E55,0) | M55: =IF(AND(B55="SELL",L55>0),D55*L55,0) | O55: =IF(AND(B55="SELL",G55<>0),Q55/ABS(G55),0) | P55: =IF(AND(B55="SELL",D55>0),R55/D55,0) | Q55: =IF(AND(B55="SELL",D55>0,E55>0),(D55/E55)+G55,0) | R55: =IF(B55="SELL",Q55*F55,0) | S55: =S54+R55
A56: 55 | B56: SELL | C56: 45899 | D56: 60000 | E56: 974.14 | F56: 974.14 | G56: -58.06 | I56: 252.29659 | J56: 202.2 | K56: =IF(AND(B56="SELL",E56>0,J56<>""),J56/E56,0) | L56: 0.193 | M56: =IF(AND(B56="SELL",L56>0),D56*L56,0) | N56: cambio enyimar | O56: =IF(AND(B56="SELL",G56<>0),Q56/ABS(G56),0) | P56: =IF(AND(B56="SELL",D56>0),R56/D56,0) | Q56: =IF(AND(B56="SELL",D56>0,E56>0),(D56/E56)+G56,0) | R56: =IF(B56="SELL",Q56*F56,0) | S56: =S55+R56
A57: 56 | B57: SELL | C57: 45899 | D57: 50000 | E57: 974.14 | F57: 974.14 | G57: -48.05 | I57: 204.24659 | J57: 201.02 | K57: =IF(AND(B57="SELL",E57>0,J57<>""),J57/E57,0) | L57: 0.193 | M57: =IF(AND(B57="SELL",L57>0),D57*L57,0) | N57: cambio pinky | O57: =IF(AND(B57="SELL",G57<>0),Q57/ABS(G57),0) | P57: =IF(AND(B57="SELL",D57>0),R57/D57,0) | Q57: =IF(AND(B57="SELL",D57>0,E57>0),(D57/E57)+G57,0) | R57: =IF(B57="SELL",Q57*F57,0) | S57: =S56+R57
A58: 57 | B58: SELL | C58: 45899 | D58: 50000 | E58: 974.14 | F58: 974.14 | G58: -49.53 | I58: 154.71659 | J58: 195 | K58: =IF(AND(B58="SELL",E58>0,J58<>""),J58/E58,0) | L58: 0.193 | M58: =IF(AND(B58="SELL",L58>0),D58*L58,0) | N58: cambio turale | O58: =IF(AND(B58="SELL",G58<>0),Q58/ABS(G58),0) | P58: =IF(AND(B58="SELL",D58>0),R58/D58,0) | Q58: =IF(AND(B58="SELL",D58>0,E58>0),(D58/E58)+G58,0) | R58: =IF(B58="SELL",Q58*F58,0) | S58: =S57+R58
A59: 58 | B59: SELL | C59: 45899 | D59: 27250 | E59: 974.14 | F59: 974.14 | G59: -27.06 | I59: 127.65659 | J59: 194.3 | K59: =IF(AND(B59="SELL",E59>0,J59<>""),J59/E59,0) | L59: 0.193 | M59: =IF(AND(B59="SELL",L59>0),D59*L59,0) | N59: cambio jasniel | O59: =IF(AND(B59="SELL",G59<>0),Q59/ABS(G59),0) | P59: =IF(AND(B59="SELL",D59>0),R59/D59,0) | Q59: =IF(AND(B59="SELL",D59>0,E59>0),(D59/E59)+G59,0) | R59: =IF(B59="SELL",Q59*F59,0) | S59: =S58+R59
A60: 59 | B60: SELL | C60: 45900 | D60: 50000 | E60: 974.14 | F60: 974.14 | G60: -48.07 | I60: 79.586586 | J60: 203.255 | K60: =IF(AND(B60="SELL",E60>0,J60<>""),J60/E60,0) | L60: 0.198 | M60: =IF(AND(B60="SELL",L60>0),D60*L60,0) | N60: cambio zuleheyka | O60: =IF(AND(B60="SELL",G60<>0),Q60/ABS(G60),0) | P60: =IF(AND(B60="SELL",D60>0),R60/D60,0) | Q60: =IF(AND(B60="SELL",D60>0,E60>0),(D60/E60)+G60,0) | R60: =IF(B60="SELL",Q60*F60,0) | S60: =S59+R60
A61: 60 | B61: SELL | C61: 45900 | D61: 60000 | E61: 974.14 | F61: 974.14 | G61: -59.24 | I61: 20.346586 | J61: 200.521 | K61: =IF(AND(B61="SELL",E61>0,J61<>""),J61/E61,0) | L61: 0.198 | M61: =IF(AND(B61="SELL",L61>0),D61*L61,0) | N61: cmbio turale | O61: =IF(AND(B61="SELL",G61<>0),Q61/ABS(G61),0) | P61: =IF(AND(B61="SELL",D61>0),R61/D61,0) | Q61: =IF(AND(B61="SELL",D61>0,E61>0),(D61/E61)+G61,0) | R61: =IF(B61="SELL",Q61*F61,0) | S61: =S60+R61
A63: TOTALES — Agosto 2025 | D63: =SUMIF(B2:B61,"SELL",D2:D61) | G63: =COUNTIF(B2:B61,"SELL") | I63: =I61 | Q63: =SUM(Q2:Q61) | R63: =SUMIF(B2:B61,"SELL",R2:R61) | S63: =S61

Sheet Septiembre 2025
A1: N° | B1: Tipo | C1: Fecha | D1: Monto CLP | E1: USDT/CLP Compra | F1: USDT/CLP Venta | G1: USDT Mov | H1: Tax Binance | I1: Capital USDT | J1: Tasa Destino | K1: Tasa Real | L1: Tasa IREMI | M1: Valor Destino | N1: Comentario | O1: % G USDT | P1: % G CLP | Q1: Ganancia USDT | R1: Ganancia CLP | S1: Acumulado SELL
A2: 1 | B2: BUY | C2: 45901 | D2: 300000 | E2: 970 | F2: 970 | G2: 309.27 | I2: 329.61659 | K2: =IF(AND(B2="SELL",E2>0,J2<>""),J2/E2,0) | M2: =IF(AND(B2="SELL",L2>0),D2*L2,0) | O2: =IF(AND(B2="SELL",G2<>0),Q2/ABS(G2),0) | P2: =IF(AND(B2="SELL",D2>0),R2/D2,0) | Q2: =IF(AND(B2="SELL",D2>0,E2>0),(D2/E2)+G2,0) | R2: =IF(B2="SELL",Q2*F2,0) | S2: ='Agosto 2025'!S61+R2
A3: 2 | B3: SELL | C3: 45901 | D3: 15000 | E3: 970 | F3: 970 | G3: -15.01 | I3: 314.60659 | J3: 200.45 | K3: =IF(AND(B3="SELL",E3>0,J3<>""),J3/E3,0) | L3: 0.2 | M3: =IF(AND(B3="SELL",L3>0),D3*L3,0) | N3: cambio paula | O3: =IF(AND(B3="SELL",G3<>0),Q3/ABS(G3),0) | P3: =IF(AND(B3="SELL",D3>0),R3/D3,0) | Q3: =IF(AND(B3="SELL",D3>0,E3>0),(D3/E3)+G3,0) | R3: =IF(B3="SELL",Q3*F3,0) | S3: =S2+R3
A4: 3 | B4: SELL | C4: 45901 | D4: 200000 | E4: 970 | F4: 970 | G4: -191.9 | I4: 122.70659 | J4: 0.86 | K4: =IF(AND(B4="SELL",E4>0,J4<>""),J4/E4,0) | L4: 0.000825 | M4: =IF(AND(B4="SELL",L4>0),D4*L4,0) | N4: cambio okunkule | O4: =IF(AND(B4="SELL",G4<>0),Q4/ABS(G4),0) | P4: =IF(AND(B4="SELL",D4>0),R4/D4,0) | Q4: =IF(AND(B4="SELL",D4>0,E4>0),(D4/E4)+G4,0) | R4: =IF(B4="SELL",Q4*F4,0) | S4: =S3+R4
A5: 4 | B5: SELL | C5: 45902 | D5: 60000 | E5: 970 | F5: 970 | G5: -58.81 | I5: 63.896586 | J5: 209.3 | K5: =IF(AND(B5="SELL",E5>0,J5<>""),J5/E5,0) | L5: 0.205 | M5: =IF(AND(B5="SELL",L5>0),D5*L5,0) | N5: cambio zuleyka | O5: =IF(AND(B5="SELL",G5<>0),Q5/ABS(G5),0) | P5: =IF(AND(B5="SELL",D5>0),R5/D5,0) | Q5: =IF(AND(B5="SELL",D5>0,E5>0),(D5/E5)+G5,0) | R5: =IF(B5="SELL",Q5*F5,0) | S5: =S4+R5
A6: 5 | B6: SELL | C6: 45902 | D6: 65000 | E6: 970 | F6: 970 | G6: -63.81 | I6: 0.0865857 | J6: 208.8 | K6: =IF(AND(B6="SELL",E6>0,J6<>""),J6/E6,0) | L6: 0.205 | M6: =IF(AND(B6="SELL",L6>0),D6*L6,0) | N6: cmabio yaka | O6: =IF(AND(B6="SELL",G6<>0),Q6/ABS(G6),0) | P6: =IF(AND(B6="SELL",D6>0),R6/D6,0) | Q6: =IF(AND(B6="SELL",D6>0,E6>0),(D6/E6)+G6,0) | R6: =IF(B6="SELL",Q6*F6,0) | S6: =S5+R6
A7: 6 | B7: BUY | C7: 45902 | D7: 340000 | E7: 978.3 | F7: 978.3 | G7: 347.54 | I7: 347.62659 | K7: =IF(AND(B7="SELL",E7>0,J7<>""),J7/E7,0) | M7: =IF(AND(B7="SELL",L7>0),D7*L7,0) | O7: =IF(AND(B7="SELL",G7<>0),Q7/ABS(G7),0) | P7: =IF(AND(B7="SELL",D7>0),R7/D7,0) | Q7: =IF(AND(B7="SELL",D7>0,E7>0),(D7/E7)+G7,0) | R7: =IF(B7="SELL",Q7*F7,0) | S7: =S6+R7
A8: 7 | B8: SELL | C8: 45902 | D8: 59000 | E8: 978.3 | F8: 978.3 | G8: -57.58 | I8: 290.04659 | J8: 209.0225 | K8: =IF(AND(B8="SELL",E8>0,J8<>""),J8/E8,0) | L8: 0.204 | M8: =IF(AND(B8="SELL",L8>0),D8*L8,0) | N8: cambio pinky | O8: =IF(AND(B8="SELL",G8<>0),Q8/ABS(G8),0) | P8: =IF(AND(B8="SELL",D8>0),R8/D8,0) | Q8: =IF(AND(B8="SELL",D8>0,E8>0),(D8/E8)+G8,0) | R8: =IF(B8="SELL",Q8*F8,0) | S8: =S7+R8
A9: 8 | B9: SELL | C9: 45902 | D9: 120000 | E9: 978.3 | F9: 978.3 | G9: -116.25 | I9: 173.79659 | J9: 211.7 | K9: =IF(AND(B9="SELL",E9>0,J9<>""),J9/E9,0) | L9: 0.205 | M9: =IF(AND(B9="SELL",L9>0),D9*L9,0) | N9: cambio francisco y jasniel | O9: =IF(AND(B9="SELL",G9<>0),Q9/ABS(G9),0) | P9: =IF(AND(B9="SELL",D9>0),R9/D9,0) | Q9: =IF(AND(B9="SELL",D9>0,E9>0),(D9/E9)+G9,0) | R9: =IF(B9="SELL",Q9*F9,0) | S9: =S8+R9
A10: 9 | B10: SELL | C10: 45902 | D10: 40000 | E10: 978.3 | F10: 978.3 | G10: -39.06 | I10: 134.73659 | J10: 210.2 | K10: =IF(AND(B10="SELL",E10>0,J10<>""),J10/E10,0) | L10: 0.205 | M10: =IF(AND(B10="SELL",L10>0),D10*L10,0) | N10: cambio para mi tia yari | O10: =IF(AND(B10="SELL",G10<>0),Q10/ABS(G10),0) | P10: =IF(AND(B10="SELL",D10>0),R10/D10,0) | Q10: =IF(AND(B10="SELL",D10>0,E10>0),(D10/E10)+G10,0) | R10: =IF(B10="SELL",Q10*F10,0) | S10: =S9+R10
A11: 10 | B11: BUY | C11: 45902 | D11: 400000 | E11: 979.3 | F11: 979.3 | G11: 408.45 | I11: 543.18659 | K11: =IF(AND(B11="SELL",E11>0,J11<>""),J11/E11,0) | M11: =IF(AND(B11="SELL",L11>0),D11*L11,0) | O11: =IF(AND(B11="SELL",G11<>0),Q11/ABS(G11),0) | P11: =IF(AND(B11="SELL",D11>0),R11/D11,0) | Q11: =IF(AND(B11="SELL",D11>0,E11>0),(D11/E11)+G11,0) | R11: =IF(B11="SELL",Q11*F11,0) | S11: =S10+R11
A12: 11 | B12: SELL | C12: 45902 | D12: 175707 | E12: 979.3 | F12: 979.3 | G12: -171.2 | I12: 371.98659 | J12: 212.61 | K12: =IF(AND(B12="SELL",E12>0,J12<>""),J12/E12,0) | L12: 0.205 | M12: =IF(AND(B12="SELL",L12>0),D12*L12,0) | N12: cambio zule y mi mama | O12: =IF(AND(B12="SELL",G12<>0),Q12/ABS(G12),0) | P12: =IF(AND(B12="SELL",D12>0),R12/D12,0) | Q12: =IF(AND(B12="SELL",D12>0,E12>0),(D12/E12)+G12,0) | R12: =IF(B12="SELL",Q12*F12,0) | S12: =S11+R12
A13: 12 | B13: SELL | C13: 45903 | D13: 29140 | E13: 979.3 | F13: 979.3 | G13: -28.72 | I13: 343.26659 | J13: 210 | K13: =IF(AND(B13="SELL",E13>0,J13<>""),J13/E13,0) | L13: 0.206 | M13: =IF(AND(B13="SELL",L13>0),D13*L13,0) | N13: cambio zule | O13: =IF(AND(B13="SELL",G13<>0),Q13/ABS(G13),0) | P13: =IF(AND(B13="SELL",D13>0),R13/D13,0) | Q13: =IF(AND(B13="SELL",D13>0,E13>0),(D13/E13)+G13,0) | R13: =IF(B13="SELL",Q13*F13,0) | S13: =S12+R13
A14: 13 | B14: SELL | C14: 45903 | D14: 20000 | E14: 979.3 | F14: 979.3 | G14: -19.61 | I14: 323.65659 | J14: 210 | K14: =IF(AND(B14="SELL",E14>0,J14<>""),J14/E14,0) | L14: 0.206 | M14: =IF(AND(B14="SELL",L14>0),D14*L14,0) | O14: =IF(AND(B14="SELL",G14<>0),Q14/ABS(G14),0) | P14: =IF(AND(B14="SELL",D14>0),R14/D14,0) | Q14: =IF(AND(B14="SELL",D14>0,E14>0),(D14/E14)+G14,0) | R14: =IF(B14="SELL",Q14*F14,0) | S14: =S13+R14
A15: 14 | B15: SELL | C15: 45903 | D15: 40000 | E15: 979.3 | F15: 979.3 | G15: -38.46 | I15: 285.19659 | J15: 214.22 | K15: =IF(AND(B15="SELL",E15>0,J15<>""),J15/E15,0) | L15: 0.206 | M15: =IF(AND(B15="SELL",L15>0),D15*L15,0) | O15: =IF(AND(B15="SELL",G15<>0),Q15/ABS(G15),0) | P15: =IF(AND(B15="SELL",D15>0),R15/D15,0) | Q15: =IF(AND(B15="SELL",D15>0,E15>0),(D15/E15)+G15,0) | R15: =IF(B15="SELL",Q15*F15,0) | S15: =S14+R15
A16: 15 | B16: SELL | C16: 45903 | D16: 17504 | E16: 979.3 | F16: 979.3 | G16: -17.07 | I16: 268.12659 | J16: 211.15 | K16: =IF(AND(B16="SELL",E16>0,J16<>""),J16/E16,0) | L16: 0.206 | M16: =IF(AND(B16="SELL",L16>0),D16*L16,0) | O16: =IF(AND(B16="SELL",G16<>0),Q16/ABS(G16),0) | P16: =IF(AND(B16="SELL",D16>0),R16/D16,0) | Q16: =IF(AND(B16="SELL",D16>0,E16>0),(D16/E16)+G16,0) | R16: =IF(B16="SELL",Q16*F16,0) | S16: =S15+R16
A17: 16 | B17: SELL | C17: 45903 | D17: 20000 | E17: 979.3 | F17: 979.3 | G17: -19.13 | I17: 248.99659 | J17: 215.34 | K17: =IF(AND(B17="SELL",E17>0,J17<>""),J17/E17,0) | L17: 0.206 | M17: =IF(AND(B17="SELL",L17>0),D17*L17,0) | O17: =IF(AND(B17="SELL",G17<>0),Q17/ABS(G17),0) | P17: =IF(AND(B17="SELL",D17>0),R17/D17,0) | Q17: =IF(AND(B17="SELL",D17>0,E17>0),(D17/E17)+G17,0) | R17: =IF(B17="SELL",Q17*F17,0) | S17: =S16+R17
A18: 17 | B18: SELL | C18: 45904 | D18: 15000 | E18: 979.3 | F18: 979.3 | G18: -14.64 | I18: 234.35659 | J18: 215.05 | K18: =IF(AND(B18="SELL",E18>0,J18<>""),J18/E18,0) | L18: 0.207 | M18: =IF(AND(B18="SELL",L18>0),D18*L18,0) | N18: cambio paula sra | O18: =IF(AND(B18="SELL",G18<>0),Q18/ABS(G18),0) | P18: =IF(AND(B18="SELL",D18>0),R18/D18,0) | Q18: =IF(AND(B18="SELL",D18>0,E18>0),(D18/E18)+G18,0) | R18: =IF(B18="SELL",Q18*F18,0) | S18: =S17+R18
A19: 18 | B19: SELL | C19: 45904 | D19: 30000 | E19: 979.3 | F19: 979.3 | G19: -29.13 | I19: 205.22659 | J19: 3912.17 | K19: =IF(AND(B19="SELL",E19>0,J19<>""),J19/E19,0) | L19: 3.8 | M19: =IF(AND(B19="SELL",L19>0),D19*L19,0) | N19: cambio turale | O19: =IF(AND(B19="SELL",G19<>0),Q19/ABS(G19),0) | P19: =IF(AND(B19="SELL",D19>0),R19/D19,0) | Q19: =IF(AND(B19="SELL",D19>0,E19>0),(D19/E19)+G19,0) | R19: =IF(B19="SELL",Q19*F19,0) | S19: =S18+R19
A20: 19 | B20: SELL | C20: 45905 | D20: 22000 | E20: 979.3 | F20: 979.3 | G20: -21.42 | I20: 183.80659 | J20: 214.701 | K20: =IF(AND(B20="SELL",E20>0,J20<>""),J20/E20,0) | L20: 0.209 | M20: =IF(AND(B20="SELL",L20>0),D20*L20,0) | O20: =IF(AND(B20="SELL",G20<>0),Q20/ABS(G20),0) | P20: =IF(AND(B20="SELL",D20>0),R20/D20,0) | Q20: =IF(AND(B20="SELL",D20>0,E20>0),(D20/E20)+G20,0) | R20: =IF(B20="SELL",Q20*F20,0) | S20: =S19+R20
A21: 20 | B21: SELL | C21: 45905 | D21: 10000 | E21: 979.3 | F21: 979.3 | G21: -9.86 | I21: 173.94659 | J21: 3853.5 | K21: =IF(AND(B21="SELL",E21>0,J21<>""),J21/E21,0) | L21: 3.8 | M21: =IF(AND(B21="SELL",L21>0),D21*L21,0) | N21: cambio turale | O21: =IF(AND(B21="SELL",G21<>0),Q21/ABS(G21),0) | P21: =IF(AND(B21="SELL",D21>0),R21/D21,0) | Q21: =IF(AND(B21="SELL",D21>0,E21>0),(D21/E21)+G21,0) | R21: =IF(B21="SELL",Q21*F21,0) | S21: =S20+R21
A22: 21 | B22: SELL | C22: 45906 | D22: 7000 | E22: 979.3 | F22: 979.3 | G22: -6.96 | I22: 166.98659 | J22: 210.057 | K22: =IF(AND(B22="SELL",E22>0,J22<>""),J22/E22,0) | L22: 0.209 | M22: =IF(AND(B22="SELL",L22>0),D22*L22,0) | N22: cambio wale | O22: =IF(AND(B22="SELL",G22<>0),Q22/ABS(G22),0) | P22: =IF(AND(B22="SELL",D22>0),R22/D22,0) | Q22: =IF(AND(B22="SELL",D22>0,E22>0),(D22/E22)+G22,0) | R22: =IF(B22="SELL",Q22*F22,0) | S22: =S21+R22
A23: 22 | B23: SELL | C23: 45906 | D23: 25667 | E23: 979.3 | F23: 979.3 | G23: -24.82 | I23: 142.16659 | J23: 217.105 | K23: =IF(AND(B23="SELL",E23>0,J23<>""),J23/E23,0) | L23: 0.2105 | M23: =IF(AND(B23="SELL",L23>0),D23*L23,0) | N23: pago de internet jesus | O23: =IF(AND(B23="SELL",G23<>0),Q23/ABS(G23),0) | P23: =IF(AND(B23="SELL",D23>0),R23/D23,0) | Q23: =IF(AND(B23="SELL",D23>0,E23>0),(D23/E23)+G23,0) | R23: =IF(B23="SELL",Q23*F23,0) | S23: =S22+R23
A24: 23 | B24: SELL | C24: 45906 | D24: 30000 | E24: 979.3 | F24: 979.3 | G24: -29.23 | I24: 112.93659 | J24: 216.019 | K24: =IF(AND(B24="SELL",E24>0,J24<>""),J24/E24,0) | L24: 0.2105 | M24: =IF(AND(B24="SELL",L24>0),D24*L24,0) | N24: cambio rosalys | O24: =IF(AND(B24="SELL",G24<>0),Q24/ABS(G24),0) | P24: =IF(AND(B24="SELL",D24>0),R24/D24,0) | Q24: =IF(AND(B24="SELL",D24>0,E24>0),(D24/E24)+G24,0) | R24: =IF(B24="SELL",Q24*F24,0) | S24: =S23+R24
A25: 24 | B25: SELL | C25: 45906 | D25: 50000 | E25: 979.3 | F25: 979.3 | G25: -48.56 | I25: 64.376586 | J25: 216.7 | K25: =IF(AND(B25="SELL",E25>0,J25<>""),J25/E25,0) | L25: 0.2105 | M25: =IF(AND(B25="SELL",L25>0),D25*L25,0) | N25: cambio pinky | O25: =IF(AND(B25="SELL",G25<>0),Q25/ABS(G25),0) | P25: =IF(AND(B25="SELL",D25>0),R25/D25,0) | Q25: =IF(AND(B25="SELL",D25>0,E25>0),(D25/E25)+G25,0) | R25: =IF(B25="SELL",Q25*F25,0) | S25: =S24+R25
A26: 25 | B26: SELL | C26: 45906 | D26: 50000 | E26: 979.3 | F26: 979.3 | G26: -48.54 | I26: 15.836586 | J26: 216.8 | K26: =IF(AND(B26="SELL",E26>0,J26<>""),J26/E26,0) | L26: 0.2105 | M26: =IF(AND(B26="SELL",L26>0),D26*L26,0) | N26: cambio rosalys | O26: =IF(AND(B26="SELL",G26<>0),Q26/ABS(G26),0) | P26: =IF(AND(B26="SELL",D26>0),R26/D26,0) | Q26: =IF(AND(B26="SELL",D26>0,E26>0),(D26/E26)+G26,0) | R26: =IF(B26="SELL",Q26*F26,0) | S26: =S25+R26
A27: 26 | B27: BUY | C27: 45906 | D27: 366000 | E27: 974.45 | F27: 974.45 | G27: 375.59 | I27: 391.42659 | K27: =IF(AND(B27="SELL",E27>0,J27<>""),J27/E27,0) | L27: 0.2105 | M27: =IF(AND(B27="SELL",L27>0),D27*L27,0) | O27: =IF(AND(B27="SELL",G27<>0),Q27/ABS(G27),0) | P27: =IF(AND(B27="SELL",D27>0),R27/D27,0) | Q27: =IF(AND(B27="SELL",D27>0,E27>0),(D27/E27)+G27,0) | R27: =IF(B27="SELL",Q27*F27,0) | S27: =S26+R27
A28: 27 | B28: SELL | C28: 45907 | D28: 50000 | E28: 979.3 | F28: 979.3 | G28: -49.04 | I28: 342.38659 | J28: 215.61 | K28: =IF(AND(B28="SELL",E28>0,J28<>""),J28/E28,0) | L28: 0.2115 | M28: =IF(AND(B28="SELL",L28>0),D28*L28,0) | N28: cambio mimi | O28: =IF(AND(B28="SELL",G28<>0),Q28/ABS(G28),0) | P28: =IF(AND(B28="SELL",D28>0),R28/D28,0) | Q28: =IF(AND(B28="SELL",D28>0,E28>0),(D28/E28)+G28,0) | R28: =IF(B28="SELL",Q28*F28,0) | S28: =S27+R28
A29: 28 | B29: SELL | C29: 45907 | D29: 30950 | E29: 979.3 | F29: 979.3 | G29: -30.6 | I29: 311.78659 | J29: 213 | K29: =IF(AND(B29="SELL",E29>0,J29<>""),J29/E29,0) | L29: 3.8 | M29: =IF(AND(B29="SELL",L29>0),D29*L29,0) | N29: cambio yumery | O29: =IF(AND(B29="SELL",G29<>0),Q29/ABS(G29),0) | P29: =IF(AND(B29="SELL",D29>0),R29/D29,0) | Q29: =IF(AND(B29="SELL",D29>0,E29>0),(D29/E29)+G29,0) | R29: =IF(B29="SELL",Q29*F29,0) | S29: =S28+R29
A30: 29 | B30: SELL | C30: 45908 | D30: 20000 | E30: 979.3 | F30: 979.3 | G30: -19.71 | I30: 292.07659 | J30: 213 | K30: =IF(AND(B30="SELL",E30>0,J30<>""),J30/E30,0) | L30: 0.2115 | M30: =IF(AND(B30="SELL",L30>0),D30*L30,0) | N30: cambio turale | O30: =IF(AND(B30="SELL",G30<>0),Q30/ABS(G30),0) | P30: =IF(AND(B30="SELL",D30>0),R30/D30,0) | Q30: =IF(AND(B30="SELL",D30>0,E30>0),(D30/E30)+G30,0) | R30: =IF(B30="SELL",Q30*F30,0) | S30: =S29+R30
A31: 30 | B31: SELL | C31: 45908 | D31: 43810 | E31: 979.3 | F31: 979.3 | G31: -41.75 | I31: 250.32659 | J31: 220.32 | K31: =IF(AND(B31="SELL",E31>0,J31<>""),J31/E31,0) | L31: 0.21 | M31: =IF(AND(B31="SELL",L31>0),D31*L31,0) | N31: cmabio paula | O31: =IF(AND(B31="SELL",G31<>0),Q31/ABS(G31),0) | P31: =IF(AND(B31="SELL",D31>0),R31/D31,0) | Q31: =IF(AND(B31="SELL",D31>0,E31>0),(D31/E31)+G31,0) | R31: =IF(B31="SELL",Q31*F31,0) | S31: =S30+R31
A32: 31 | B32: SELL | C32: 45908 | D32: 50000 | E32: 979.3 | F32: 979.3 | G32: -49.13 | I32: 201.19659 | J32: 3867 | K32: =IF(AND(B32="SELL",E32>0,J32<>""),J32/E32,0) | L32: 3.8 | M32: =IF(AND(B32="SELL",L32>0),D32*L32,0) | N32: cambio ramses | O32: =IF(AND(B32="SELL",G32<>0),Q32/ABS(G32),0) | P32: =IF(AND(B32="SELL",D32>0),R32/D32,0) | Q32: =IF(AND(B32="SELL",D32>0,E32>0),(D32/E32)+G32,0) | R32: =IF(B32="SELL",Q32*F32,0) | S32: =S31+R32
A33: 32 | B33: SELL | C33: 45908 | D33: 30000 | E33: 979.3 | F33: 979.3 | G33: -28.59 | I33: 172.60659 | J33: 220.3 | K33: =IF(AND(B33="SELL",E33>0,J33<>""),J33/E33,0) | L33: 0.21 | M33: =IF(AND(B33="SELL",L33>0),D33*L33,0) | N33: cambio rosalys | O33: =IF(AND(B33="SELL",G33<>0),Q33/ABS(G33),0) | P33: =IF(AND(B33="SELL",D33>0),R33/D33,0) | Q33: =IF(AND(B33="SELL",D33>0,E33>0),(D33/E33)+G33,0) | R33: =IF(B33="SELL",Q33*F33,0) | S33: =S32+R33
A34: 33 | B34: SELL | C34: 45909 | D34: 40000 | E34: 979.3 | F34: 979.3 | G34: -37.66 | I34: 177.94659 | J34: 232.6 | K34: =IF(AND(B34="SELL",E34>0,J34<>""),J34/E34,0) | L34: 0.219 | M34: =IF(AND(B34="SELL",L34>0),D34*L34,0) | N34: cambio | O34: =IF(AND(B34="SELL",G34<>0),Q34/ABS(G34),0) | P34: =IF(AND(B34="SELL",D34>0),R34/D34,0) | Q34: =IF(AND(B34="SELL",D34>0,E34>0),(D34/E34)+G34,0) | R34: =IF(B34="SELL",Q34*F34,0) | S34: =S33+R34
A35: 34 | B35: SELL | C35: 45910 | D35: 150000 | E35: 979.3 | F35: 979.3 | G35: -139.59 | I35: 38.356586 | J35: 238.006 | K35: =IF(AND(B35="SELL",E35>0,J35<>""),J35/E35,0) | L35: 0.2245 | M35: =IF(AND(B35="SELL",L35>0),D35*L35,0) | N35: cambio paula y pinky | O35: =IF(AND(B35="SELL",G35<>0),Q35/ABS(G35),0) | P35: =IF(AND(B35="SELL",D35>0),R35/D35,0) | Q35: =IF(AND(B35="SELL",D35>0,E35>0),(D35/E35)+G35,0) | R35: =IF(B35="SELL",Q35*F35,0) | S35: =S34+R35
A36: 35 | B36: SELL | C36: 45910 | D36: 5000 | E36: 979.3 | F36: 979.3 | G36: -5.27 | I36: 33.086586 | J36: 231.866 | K36: =IF(AND(B36="SELL",E36>0,J36<>""),J36/E36,0) | L36: 0.2245 | M36: =IF(AND(B36="SELL",L36>0),D36*L36,0) | N36: cambio pinky | O36: =IF(AND(B36="SELL",G36<>0),Q36/ABS(G36),0) | P36: =IF(AND(B36="SELL",D36>0),R36/D36,0) | Q36: =IF(AND(B36="SELL",D36>0,E36>0),(D36/E36)+G36,0) | R36: =IF(B36="SELL",Q36*F36,0) | S36: =S35+R36
A37: 36 | B37: BUY | C37: 45911 | D37: 507887 | E37: 964.77 | F37: 964.77 | G37: 526.43 | I37: 559.51659 | K37: =IF(AND(B37="SELL",E37>0,J37<>""),J37/E37,0) | M37: =IF(AND(B37="SELL",L37>0),D37*L37,0) | O37: =IF(AND(B37="SELL",G37<>0),Q37/ABS(G37),0) | P37: =IF(AND(B37="SELL",D37>0),R37/D37,0) | Q37: =IF(AND(B37="SELL",D37>0,E37>0),(D37/E37)+G37,0) | R37: =IF(B37="SELL",Q37*F37,0) | S37: =S36+R37
A38: 37 | B38: SELL | C38: 45911 | D38: 50000 | E38: 964.77 | F38: 964.77 | G38: -49.91 | I38: 509.60659 | J38: 238.4 | K38: =IF(AND(B38="SELL",E38>0,J38<>""),J38/E38,0) | L38: 0.238 | M38: =IF(AND(B38="SELL",L38>0),D38*L38,0) | N38: cambio paula | O38: =IF(AND(B38="SELL",G38<>0),Q38/ABS(G38),0) | P38: =IF(AND(B38="SELL",D38>0),R38/D38,0) | Q38: =IF(AND(B38="SELL",D38>0,E38>0),(D38/E38)+G38,0) | R38: =IF(B38="SELL",Q38*F38,0) | S38: =S37+R38
A39: 38 | B39: SELL | C39: 45911 | D39: 50000 | E39: 964.77 | F39: 964.77 | G39: -49.64 | I39: 459.96659 | J39: 18.53 | K39: =IF(AND(B39="SELL",E39>0,J39<>""),J39/E39,0) | L39: 0.184 | M39: =IF(AND(B39="SELL",L39>0),D39*L39,0) | N39: cambio paula | O39: =IF(AND(B39="SELL",G39<>0),Q39/ABS(G39),0) | P39: =IF(AND(B39="SELL",D39>0),R39/D39,0) | Q39: =IF(AND(B39="SELL",D39>0,E39>0),(D39/E39)+G39,0) | R39: =IF(B39="SELL",Q39*F39,0) | S39: =S38+R39
A40: 39 | B40: SELL | C40: 45911 | D40: 20000 | E40: 964.77 | F40: 964.77 | G40: -20.2 | I40: 439.76659 | J40: 235.601 | K40: =IF(AND(B40="SELL",E40>0,J40<>""),J40/E40,0) | L40: 0.238 | M40: =IF(AND(B40="SELL",L40>0),D40*L40,0) | N40: cambio wale | O40: =IF(AND(B40="SELL",G40<>0),Q40/ABS(G40),0) | P40: =IF(AND(B40="SELL",D40>0),R40/D40,0) | Q40: =IF(AND(B40="SELL",D40>0,E40>0),(D40/E40)+G40,0) | R40: =IF(B40="SELL",Q40*F40,0) | S40: =S39+R40
A41: 40 | B41: SELL | C41: 45912 | D41: 40000 | E41: 964.77 | F41: 964.77 | G41: -39.69 | I41: 400.07659 | J41: 237.311 | K41: =IF(AND(B41="SELL",E41>0,J41<>""),J41/E41,0) | L41: 0.2355 | M41: =IF(AND(B41="SELL",L41>0),D41*L41,0) | N41: cmabio zule | O41: =IF(AND(B41="SELL",G41<>0),Q41/ABS(G41),0) | P41: =IF(AND(B41="SELL",D41>0),R41/D41,0) | Q41: =IF(AND(B41="SELL",D41>0,E41>0),(D41/E41)+G41,0) | R41: =IF(B41="SELL",Q41*F41,0) | S41: =S40+R41
A42: 41 | B42: SELL | C42: 45912 | D42: 40000 | E42: 964.77 | F42: 964.77 | G42: -39.69 | I42: 360.38659 | J42: 237.311 | K42: =IF(AND(B42="SELL",E42>0,J42<>""),J42/E42,0) | L42: 0.2355 | M42: =IF(AND(B42="SELL",L42>0),D42*L42,0) | N42: cambio | O42: =IF(AND(B42="SELL",G42<>0),Q42/ABS(G42),0) | P42: =IF(AND(B42="SELL",D42>0),R42/D42,0) | Q42: =IF(AND(B42="SELL",D42>0,E42>0),(D42/E42)+G42,0) | R42: =IF(B42="SELL",Q42*F42,0) | S42: =S41+R42
A43: 42 | B43: SELL | C43: 45912 | D43: 15000 | E43: 964.77 | F43: 964.77 | G43: -15.08 | I43: 345.30659 | J43: 234.2 | K43: =IF(AND(B43="SELL",E43>0,J43<>""),J43/E43,0) | L43: 0.2245 | M43: =IF(AND(B43="SELL",L43>0),D43*L43,0) | N43: cambio angel | O43: =IF(AND(B43="SELL",G43<>0),Q43/ABS(G43),0) | P43: =IF(AND(B43="SELL",D43>0),R43/D43,0) | Q43: =IF(AND(B43="SELL",D43>0,E43>0),(D43/E43)+G43,0) | R43: =IF(B43="SELL",Q43*F43,0) | S43: =S42+R43
A44: 43 | B44: SELL | C44: 45912 | D44: 70000 | E44: 964.77 | F44: 964.77 | G44: -69.43 | I44: 275.87659 | J44: 237.635 | K44: =IF(AND(B44="SELL",E44>0,J44<>""),J44/E44,0) | L44: 0.2245 | M44: =IF(AND(B44="SELL",L44>0),D44*L44,0) | O44: =IF(AND(B44="SELL",G44<>0),Q44/ABS(G44),0) | P44: =IF(AND(B44="SELL",D44>0),R44/D44,0) | Q44: =IF(AND(B44="SELL",D44>0,E44>0),(D44/E44)+G44,0) | R44: =IF(B44="SELL",Q44*F44,0) | S44: =S43+R44
A45: 44 | B45: SELL | C45: 45913 | D45: 50000 | E45: 964.77 | F45: 964.77 | G45: -49.12 | I45: 226.75659 | J45: 240.2 | K45: =IF(AND(B45="SELL",E45>0,J45<>""),J45/E45,0) | L45: 0.236 | M45: =IF(AND(B45="SELL",L45>0),D45*L45,0) | O45: =IF(AND(B45="SELL",G45<>0),Q45/ABS(G45),0) | P45: =IF(AND(B45="SELL",D45>0),R45/D45,0) | Q45: =IF(AND(B45="SELL",D45>0,E45>0),(D45/E45)+G45,0) | R45: =IF(B45="SELL",Q45*F45,0) | S45: =S44+R45
A46: 45 | B46: SELL | C46: 45914 | D46: 15800 | E46: 964.77 | F46: 964.77 | G46: -15.62 | I46: 211.13659 | J46: 240 | K46: =IF(AND(B46="SELL",E46>0,J46<>""),J46/E46,0) | L46: 0.2375 | M46: =IF(AND(B46="SELL",L46>0),D46*L46,0) | O46: =IF(AND(B46="SELL",G46<>0),Q46/ABS(G46),0) | P46: =IF(AND(B46="SELL",D46>0),R46/D46,0) | Q46: =IF(AND(B46="SELL",D46>0,E46>0),(D46/E46)+G46,0) | R46: =IF(B46="SELL",Q46*F46,0) | S46: =S45+R46
A47: 46 | B47: SELL | C47: 45914 | D47: 60000 | E47: 964.77 | F47: 964.77 | G47: -58.52 | I47: 152.61659 | J47: 243.5 | K47: =IF(AND(B47="SELL",E47>0,J47<>""),J47/E47,0) | L47: 0.2375 | M47: =IF(AND(B47="SELL",L47>0),D47*L47,0) | O47: =IF(AND(B47="SELL",G47<>0),Q47/ABS(G47),0) | P47: =IF(AND(B47="SELL",D47>0),R47/D47,0) | Q47: =IF(AND(B47="SELL",D47>0,E47>0),(D47/E47)+G47,0) | R47: =IF(B47="SELL",Q47*F47,0) | S47: =S46+R47
A48: 47 | B48: BUY | C48: 45915 | D48: 910000 | E48: 955.5 | F48: 955.5 | G48: 952.48 | I48: 1105.0966 | K48: =IF(AND(B48="SELL",E48>0,J48<>""),J48/E48,0) | M48: =IF(AND(B48="SELL",L48>0),D48*L48,0) | O48: =IF(AND(B48="SELL",G48<>0),Q48/ABS(G48),0) | P48: =IF(AND(B48="SELL",D48>0),R48/D48,0) | Q48: =IF(AND(B48="SELL",D48>0,E48>0),(D48/E48)+G48,0) | R48: =IF(B48="SELL",Q48*F48,0) | S48: =S47+R48
A49: 48 | B49: SELL | C49: 45915 | D49: 540000 | E49: 955.5 | F49: 955.5 | G49: -534.1 | I49: 570.99659 | J49: 1.01 | K49: =IF(AND(B49="SELL",E49>0,J49<>""),J49/E49,0) | L49: 0.000999 | M49: =IF(AND(B49="SELL",L49>0),D49*L49,0) | N49: cambio daryeli | O49: =IF(AND(B49="SELL",G49<>0),Q49/ABS(G49),0) | P49: =IF(AND(B49="SELL",D49>0),R49/D49,0) | Q49: =IF(AND(B49="SELL",D49>0,E49>0),(D49/E49)+G49,0) | R49: =IF(B49="SELL",Q49*F49,0) | S49: =S48+R49
A50: 49 | B50: SELL | C50: 45915 | D50: 50000 | E50: 955.5 | F50: 955.5 | G50: -48.97 | I50: 522.02659 | J50: 243.5 | K50: =IF(AND(B50="SELL",E50>0,J50<>""),J50/E50,0) | L50: 0.2385 | M50: =IF(AND(B50="SELL",L50>0),D50*L50,0) | N50: cambio angel | O50: =IF(AND(B50="SELL",G50<>0),Q50/ABS(G50),0) | P50: =IF(AND(B50="SELL",D50>0),R50/D50,0) | Q50: =IF(AND(B50="SELL",D50>0,E50>0),(D50/E50)+G50,0) | R50: =IF(B50="SELL",Q50*F50,0) | S50: =S49+R50
A51: 50 | B51: SELL | C51: 45915 | D51: 40000 | E51: 955.5 | F51: 955.5 | G51: -39.5 | I51: 482.52659 | J51: 241.5 | K51: =IF(AND(B51="SELL",E51>0,J51<>""),J51/E51,0) | L51: 0.2385 | M51: =IF(AND(B51="SELL",L51>0),D51*L51,0) | N51: cambio paula | O51: =IF(AND(B51="SELL",G51<>0),Q51/ABS(G51),0) | P51: =IF(AND(B51="SELL",D51>0),R51/D51,0) | Q51: =IF(AND(B51="SELL",D51>0,E51>0),(D51/E51)+G51,0) | R51: =IF(B51="SELL",Q51*F51,0) | S51: =S50+R51
A52: 51 | B52: SELL | C52: 45915 | D52: 22000 | E52: 955.5 | F52: 955.5 | G52: -21.99 | I52: 460.53659 | J52: 239.7722 | K52: =IF(AND(B52="SELL",E52>0,J52<>""),J52/E52,0) | L52: 0.2385 | M52: =IF(AND(B52="SELL",L52>0),D52*L52,0) | N52: cambio paula | O52: =IF(AND(B52="SELL",G52<>0),Q52/ABS(G52),0) | P52: =IF(AND(B52="SELL",D52>0),R52/D52,0) | Q52: =IF(AND(B52="SELL",D52>0,E52>0),(D52/E52)+G52,0) | R52: =IF(B52="SELL",Q52*F52,0) | S52: =S51+R52
A53: 52 | B53: SELL | C53: 45915 | D53: 30000 | E53: 955.5 | F53: 955.5 | G53: -29.74 | I53: 430.79659 | J53: 240.3824 | K53: =IF(AND(B53="SELL",E53>0,J53<>""),J53/E53,0) | L53: 0.2385 | M53: =IF(AND(B53="SELL",L53>0),D53*L53,0) | N53: cambio wale | O53: =IF(AND(B53="SELL",G53<>0),Q53/ABS(G53),0) | P53: =IF(AND(B53="SELL",D53>0),R53/D53,0) | Q53: =IF(AND(B53="SELL",D53>0,E53>0),(D53/E53)+G53,0) | R53: =IF(B53="SELL",Q53*F53,0) | S53: =S52+R53
A54: 53 | B54: SELL | C54: 45916 | D54: 80000 | E54: 955.5 | F54: 955.5 | G54: -78.4 | I54: 352.39659 | J54: 240.801 | K54: =IF(AND(B54="SELL",E54>0,J54<>""),J54/E54,0) | L54: 0.236 | M54: =IF(AND(B54="SELL",L54>0),D54*L54,0) | O54: =IF(AND(B54="SELL",G54<>0),Q54/ABS(G54),0) | P54: =IF(AND(B54="SELL",D54>0),R54/D54,0) | Q54: =IF(AND(B54="SELL",D54>0,E54>0),(D54/E54)+G54,0) | R54: =IF(B54="SELL",Q54*F54,0) | S54: =S53+R54
A55: 54 | B55: SELL | C55: 45916 | D55: 60500 | E55: 955.5 | F55: 955.5 | G55: -57.67 | I55: 294.72659 | J55: 247.61 | K55: =IF(AND(B55="SELL",E55>0,J55<>""),J55/E55,0) | L55: 0.236 | M55: =IF(AND(B55="SELL",L55>0),D55*L55,0) | O55: =IF(AND(B55="SELL",G55<>0),Q55/ABS(G55),0) | P55: =IF(AND(B55="SELL",D55>0),R55/D55,0) | Q55: =IF(AND(B55="SELL",D55>0,E55>0),(D55/E55)+G55,0) | R55: =IF(B55="SELL",Q55*F55,0) | S55: =S54+R55
A56: 55 | B56: SELL | C56: 45916 | D56: 40000 | E56: 955.5 | F56: 955.5 | G56: -38.06 | I56: 256.66659 | J56: 248.001 | K56: =IF(AND(B56="SELL",E56>0,J56<>""),J56/E56,0) | L56: 0.236 | M56: =IF(AND(B56="SELL",L56>0),D56*L56,0) | O56: =IF(AND(B56="SELL",G56<>0),Q56/ABS(G56),0) | P56: =IF(AND(B56="SELL",D56>0),R56/D56,0) | Q56: =IF(AND(B56="SELL",D56>0,E56>0),(D56/E56)+G56,0) | R56: =IF(B56="SELL",Q56*F56,0) | S56: =S55+R56
A57: 56 | B57: SELL | C57: 45917 | D57: 30000 | E57: 955.5 | F57: 955.5 | G57: -29.58 | I57: 227.08659 | J57: 0.85 | K57: =IF(AND(B57="SELL",E57>0,J57<>""),J57/E57,0) | L57: 0.000834 | M57: =IF(AND(B57="SELL",L57>0),D57*L57,0) | O57: =IF(AND(B57="SELL",G57<>0),Q57/ABS(G57),0) | P57: =IF(AND(B57="SELL",D57>0),R57/D57,0) | Q57: =IF(AND(B57="SELL",D57>0,E57>0),(D57/E57)+G57,0) | R57: =IF(B57="SELL",Q57*F57,0) | S57: =S56+R57
A58: 57 | B58: SELL | C58: 45917 | D58: 100000 | E58: 955.5 | F58: 955.5 | G58: -94.84 | I58: 132.24659 | J58: 263.6 | K58: =IF(AND(B58="SELL",E58>0,J58<>""),J58/E58,0) | L58: 0.25 | M58: =IF(AND(B58="SELL",L58>0),D58*L58,0) | O58: =IF(AND(B58="SELL",G58<>0),Q58/ABS(G58),0) | P58: =IF(AND(B58="SELL",D58>0),R58/D58,0) | Q58: =IF(AND(B58="SELL",D58>0,E58>0),(D58/E58)+G58,0) | R58: =IF(B58="SELL",Q58*F58,0) | S58: =S57+R58
A59: 58 | B59: SELL | C59: 45917 | D59: 20000 | E59: 955.5 | F59: 955.5 | G59: -19.59 | I59: 112.65659 | J59: 3806.5 | K59: =IF(AND(B59="SELL",E59>0,J59<>""),J59/E59,0) | L59: 3.73 | M59: =IF(AND(B59="SELL",L59>0),D59*L59,0) | O59: =IF(AND(B59="SELL",G59<>0),Q59/ABS(G59),0) | P59: =IF(AND(B59="SELL",D59>0),R59/D59,0) | Q59: =IF(AND(B59="SELL",D59>0,E59>0),(D59/E59)+G59,0) | R59: =IF(B59="SELL",Q59*F59,0) | S59: =S58+R59
A60: 59 | B60: SELL | C60: 45917 | D60: 10000 | E60: 955.5 | F60: 955.5 | G60: -9.76 | I60: 102.89659 | J60: 256.005 | K60: =IF(AND(B60="SELL",E60>0,J60<>""),J60/E60,0) | L60: 0.25 | M60: =IF(AND(B60="SELL",L60>0),D60*L60,0) | O60: =IF(AND(B60="SELL",G60<>0),Q60/ABS(G60),0) | P60: =IF(AND(B60="SELL",D60>0),R60/D60,0) | Q60: =IF(AND(B60="SELL",D60>0,E60>0),(D60/E60)+G60,0) | R60: =IF(B60="SELL",Q60*F60,0) | S60: =S59+R60
A61: 60 | B61: SELL | C61: 45918 | D61: 50000 | E61: 955.5 | F61: 955.5 | G61: -49.69 | I61: 53.206586 | J61: 261.61 | K61: =IF(AND(B61="SELL",E61>0,J61<>""),J61/E61,0) | L61: 0.26 | M61: =IF(AND(B61="SELL",L61>0),D61*L61,0) | O61: =IF(AND(B61="SELL",G61<>0),Q61/ABS(G61),0) | P61: =IF(AND(B61="SELL",D61>0),R61/D61,0) | Q61: =IF(AND(B61="SELL",D61>0,E61>0),(D61/E61)+G61,0) | R61: =IF(B61="SELL",Q61*F61,0) | S61: =S60+R61
A62: 61 | B62: SELL | C62: 45918 | D62: 10000 | E62: 955.5 | F62: 955.5 | G62: -9.99 | I62: 43.216586 | J62: 260.101 | K62: =IF(AND(B62="SELL",E62>0,J62<>""),J62/E62,0) | L62: 0.26 | M62: =IF(AND(B62="SELL",L62>0),D62*L62,0) | O62: =IF(AND(B62="SELL",G62<>0),Q62/ABS(G62),0) | P62: =IF(AND(B62="SELL",D62>0),R62/D62,0) | Q62: =IF(AND(B62="SELL",D62>0,E62>0),(D62/E62)+G62,0) | R62: =IF(B62="SELL",Q62*F62,0) | S62: =S61+R62
A63: 62 | B63: SELL | C63: 45918 | D63: 20000 | E63: 955.5 | F63: 955.5 | G63: -19.75 | I63: 23.466586 | J63: 263.2 | K63: =IF(AND(B63="SELL",E63>0,J63<>""),J63/E63,0) | L63: 0.26 | M63: =IF(AND(B63="SELL",L63>0),D63*L63,0) | O63: =IF(AND(B63="SELL",G63<>0),Q63/ABS(G63),0) | P63: =IF(AND(B63="SELL",D63>0),R63/D63,0) | Q63: =IF(AND(B63="SELL",D63>0,E63>0),(D63/E63)+G63,0) | R63: =IF(B63="SELL",Q63*F63,0) | S63: =S62+R63
A64: 63 | B64: BUY | C64: 45919 | D64: 592000 | E64: 963.5 | F64: 963.5 | G64: 614.42 | I64: 637.88659 | K64: =IF(AND(B64="SELL",E64>0,J64<>""),J64/E64,0) | M64: =IF(AND(B64="SELL",L64>0),D64*L64,0) | O64: =IF(AND(B64="SELL",G64<>0),Q64/ABS(G64),0) | P64: =IF(AND(B64="SELL",D64>0),R64/D64,0) | Q64: =IF(AND(B64="SELL",D64>0,E64>0),(D64/E64)+G64,0) | R64: =IF(B64="SELL",Q64*F64,0) | S64: =S63+R64
A65: 64 | B65: SELL | C65: 45919 | D65: 70000 | E65: 963.5 | F65: 963.5 | G65: -69.97 | I65: 567.91659 | J65: 261.1 | K65: =IF(AND(B65="SELL",E65>0,J65<>""),J65/E65,0) | L65: 0.261 | M65: =IF(AND(B65="SELL",L65>0),D65*L65,0) | O65: =IF(AND(B65="SELL",G65<>0),Q65/ABS(G65),0) | P65: =IF(AND(B65="SELL",D65>0),R65/D65,0) | Q65: =IF(AND(B65="SELL",D65>0,E65>0),(D65/E65)+G65,0) | R65: =IF(B65="SELL",Q65*F65,0) | S65: =S64+R65
A66: 65 | B66: SELL | C66: 45919 | D66: 80000 | E66: 963.5 | F66: 963.5 | G66: -78.76 | I66: 489.15659 | J66: 165.081 | K66: =IF(AND(B66="SELL",E66>0,J66<>""),J66/E66,0) | L66: 0.261 | M66: =IF(AND(B66="SELL",L66>0),D66*L66,0) | O66: =IF(AND(B66="SELL",G66<>0),Q66/ABS(G66),0) | P66: =IF(AND(B66="SELL",D66>0),R66/D66,0) | Q66: =IF(AND(B66="SELL",D66>0,E66>0),(D66/E66)+G66,0) | R66: =IF(B66="SELL",Q66*F66,0) | S66: =S65+R66
A67: 66 | B67: SELL | C67: 45919 | D67: 20000 | E67: 963.5 | F67: 963.5 | G67: -19.77 | I67: 469.38659 | J67: 3791.99 | K67: =IF(AND(B67="SELL",E67>0,J67<>""),J67/E67,0) | L67: 3.75 | M67: =IF(AND(B67="SELL",L67>0),D67*L67,0) | O67: =IF(AND(B67="SELL",G67<>0),Q67/ABS(G67),0) | P67: =IF(AND(B67="SELL",D67>0),R67/D67,0) | Q67: =IF(AND(B67="SELL",D67>0,E67>0),(D67/E67)+G67,0) | R67: =IF(B67="SELL",Q67*F67,0) | S67: =S66+R67
A68: 67 | B68: SELL | C68: 45920 | D68: 25000 | E68: 963.5 | F68: 963.5 | G68: -25.37 | I68: 444.01659 | J68: 262.05 | K68: =IF(AND(B68="SELL",E68>0,J68<>""),J68/E68,0) | L68: 0.266 | M68: =IF(AND(B68="SELL",L68>0),D68*L68,0) | O68: =IF(AND(B68="SELL",G68<>0),Q68/ABS(G68),0) | P68: =IF(AND(B68="SELL",D68>0),R68/D68,0) | Q68: =IF(AND(B68="SELL",D68>0,E68>0),(D68/E68)+G68,0) | R68: =IF(B68="SELL",Q68*F68,0) | S68: =S67+R68
A69: 68 | B69: SELL | C69: 45920 | D69: 40000 | E69: 963.5 | F69: 963.5 | G69: -40.45 | I69: 403.56659 | J69: 263.025 | K69: =IF(AND(B69="SELL",E69>0,J69<>""),J69/E69,0) | L69: 0.266 | M69: =IF(AND(B69="SELL",L69>0),D69*L69,0) | O69: =IF(AND(B69="SELL",G69<>0),Q69/ABS(G69),0) | P69: =IF(AND(B69="SELL",D69>0),R69/D69,0) | Q69: =IF(AND(B69="SELL",D69>0,E69>0),(D69/E69)+G69,0) | R69: =IF(B69="SELL",Q69*F69,0) | S69: =S68+R69
A70: 69 | B70: BUY | C70: 45922 | D70: 765000 | E70: 959.6 | F70: 959.6 | G70: 797.2 | I70: 1200.7666 | K70: =IF(AND(B70="SELL",E70>0,J70<>""),J70/E70,0) | M70: =IF(AND(B70="SELL",L70>0),D70*L70,0) | O70: =IF(AND(B70="SELL",G70<>0),Q70/ABS(G70),0) | P70: =IF(AND(B70="SELL",D70>0),R70/D70,0) | Q70: =IF(AND(B70="SELL",D70>0,E70>0),(D70/E70)+G70,0) | R70: =IF(B70="SELL",Q70*F70,0) | S70: =S69+R70
A71: 70 | B71: SELL | C71: 45922 | D71: 540000 | E71: 959.6 | F71: 959.6 | G71: -525 | I71: 675.76659 | J71: 1.003 | K71: =IF(AND(B71="SELL",E71>0,J71<>""),J71/E71,0) | L71: 0.000999 | M71: =IF(AND(B71="SELL",L71>0),D71*L71,0) | O71: =IF(AND(B71="SELL",G71<>0),Q71/ABS(G71),0) | P71: =IF(AND(B71="SELL",D71>0),R71/D71,0) | Q71: =IF(AND(B71="SELL",D71>0,E71>0),(D71/E71)+G71,0) | R71: =IF(B71="SELL",Q71*F71,0) | S71: =S70+R71
A72: 71 | B72: SELL | C72: 45922 | D72: 60000 | E72: 959.6 | F72: 959.6 | G72: -58.27 | I72: 617.49659 | J72: 265.65 | K72: =IF(AND(B72="SELL",E72>0,J72<>""),J72/E72,0) | L72: 0.258 | M72: =IF(AND(B72="SELL",L72>0),D72*L72,0) | O72: =IF(AND(B72="SELL",G72<>0),Q72/ABS(G72),0) | P72: =IF(AND(B72="SELL",D72>0),R72/D72,0) | Q72: =IF(AND(B72="SELL",D72>0,E72>0),(D72/E72)+G72,0) | R72: =IF(B72="SELL",Q72*F72,0) | S72: =S71+R72
A73: 72 | B73: SELL | C73: 45923 | D73: 15000 | E73: 959.6 | F73: 959.6 | G73: -14.92 | I73: 602.57659 | J73: 261.35 | K73: =IF(AND(B73="SELL",E73>0,J73<>""),J73/E73,0) | L73: 0.26 | M73: =IF(AND(B73="SELL",L73>0),D73*L73,0) | O73: =IF(AND(B73="SELL",G73<>0),Q73/ABS(G73),0) | P73: =IF(AND(B73="SELL",D73>0),R73/D73,0) | Q73: =IF(AND(B73="SELL",D73>0,E73>0),(D73/E73)+G73,0) | R73: =IF(B73="SELL",Q73*F73,0) | S73: =S72+R73
A74: 73 | B74: SELL | C74: 45923 | D74: 30000 | E74: 959.6 | F74: 959.6 | G74: -29.69 | I74: 572.88659 | J74: 266 | K74: =IF(AND(B74="SELL",E74>0,J74<>""),J74/E74,0) | L74: 0.26 | M74: =IF(AND(B74="SELL",L74>0),D74*L74,0) | O74: =IF(AND(B74="SELL",G74<>0),Q74/ABS(G74),0) | P74: =IF(AND(B74="SELL",D74>0),R74/D74,0) | Q74: =IF(AND(B74="SELL",D74>0,E74>0),(D74/E74)+G74,0) | R74: =IF(B74="SELL",Q74*F74,0) | S74: =S73+R74
A75: 74 | B75: SELL | C75: 45924 | D75: 28000 | E75: 959.6 | F75: 959.6 | G75: -27.3 | I75: 545.58659 | J75: 282 | K75: =IF(AND(B75="SELL",E75>0,J75<>""),J75/E75,0) | L75: 0.275 | M75: =IF(AND(B75="SELL",L75>0),D75*L75,0) | O75: =IF(AND(B75="SELL",G75<>0),Q75/ABS(G75),0) | P75: =IF(AND(B75="SELL",D75>0),R75/D75,0) | Q75: =IF(AND(B75="SELL",D75>0,E75>0),(D75/E75)+G75,0) | R75: =IF(B75="SELL",Q75*F75,0) | S75: =S74+R75
A76: 75 | B76: SELL | C76: 45924 | D76: 10000 | E76: 959.6 | F76: 959.6 | G76: -9.84 | I76: 535.74659 | J76: 279.2 | K76: =IF(AND(B76="SELL",E76>0,J76<>""),J76/E76,0) | L76: 0.275 | M76: =IF(AND(B76="SELL",L76>0),D76*L76,0) | O76: =IF(AND(B76="SELL",G76<>0),Q76/ABS(G76),0) | P76: =IF(AND(B76="SELL",D76>0),R76/D76,0) | Q76: =IF(AND(B76="SELL",D76>0,E76>0),(D76/E76)+G76,0) | R76: =IF(B76="SELL",Q76*F76,0) | S76: =S75+R76
A77: 76 | B77: SELL | C77: 45924 | D77: 10000 | E77: 959.6 | F77: 959.6 | G77: -9.8 | I77: 525.94659 | J77: 280.35 | K77: =IF(AND(B77="SELL",E77>0,J77<>""),J77/E77,0) | L77: 0.275 | M77: =IF(AND(B77="SELL",L77>0),D77*L77,0) | N77: cambio jasniel | O77: =IF(AND(B77="SELL",G77<>0),Q77/ABS(G77),0) | P77: =IF(AND(B77="SELL",D77>0),R77/D77,0) | Q77: =IF(AND(B77="SELL",D77>0,E77>0),(D77/E77)+G77,0) | R77: =IF(B77="SELL",Q77*F77,0) | S77: =S76+R77
A78: 77 | B78: SELL | C78: 45924 | D78: 4500 | E78: 959.6 | F78: 959.6 | G78: -4.43 | I78: 521.51659 | J78: 279.101 | K78: =IF(AND(B78="SELL",E78>0,J78<>""),J78/E78,0) | L78: 0.275 | M78: =IF(AND(B78="SELL",L78>0),D78*L78,0) | N78: cambio jasniel | O78: =IF(AND(B78="SELL",G78<>0),Q78/ABS(G78),0) | P78: =IF(AND(B78="SELL",D78>0),R78/D78,0) | Q78: =IF(AND(B78="SELL",D78>0,E78>0),(D78/E78)+G78,0) | R78: =IF(B78="SELL",Q78*F78,0) | S78: =S77+R78
A79: 78 | B79: SELL | C79: 45924 | D79: 50000 | E79: 959.6 | F79: 959.6 | G79: -47.74 | I79: 473.77659 | J79: 288 | K79: =IF(AND(B79="SELL",E79>0,J79<>""),J79/E79,0) | L79: 0.275 | M79: =IF(AND(B79="SELL",L79>0),D79*L79,0) | O79: =IF(AND(B79="SELL",G79<>0),Q79/ABS(G79),0) | P79: =IF(AND(B79="SELL",D79>0),R79/D79,0) | Q79: =IF(AND(B79="SELL",D79>0,E79>0),(D79/E79)+G79,0) | R79: =IF(B79="SELL",Q79*F79,0) | S79: =S78+R79
A80: 79 | B80: SELL | C80: 45924 | D80: 50000 | E80: 959.6 | F80: 959.6 | G80: -47.82 | I80: 425.95659 | J80: 287.5 | K80: =IF(AND(B80="SELL",E80>0,J80<>""),J80/E80,0) | L80: 0.275 | M80: =IF(AND(B80="SELL",L80>0),D80*L80,0) | O80: =IF(AND(B80="SELL",G80<>0),Q80/ABS(G80),0) | P80: =IF(AND(B80="SELL",D80>0),R80/D80,0) | Q80: =IF(AND(B80="SELL",D80>0,E80>0),(D80/E80)+G80,0) | R80: =IF(B80="SELL",Q80*F80,0) | S80: =S79+R80
A81: 80 | B81: SELL | C81: 45925 | D81: 39000 | E81: 959.6 | F81: 959.6 | G81: -38.07 | I81: 387.88659 | J81: 3835.22 | K81: =IF(AND(B81="SELL",E81>0,J81<>""),J81/E81,0) | L81: 3.75 | M81: =IF(AND(B81="SELL",L81>0),D81*L81,0) | N81: cambio danger | O81: =IF(AND(B81="SELL",G81<>0),Q81/ABS(G81),0) | P81: =IF(AND(B81="SELL",D81>0),R81/D81,0) | Q81: =IF(AND(B81="SELL",D81>0,E81>0),(D81/E81)+G81,0) | R81: =IF(B81="SELL",Q81*F81,0) | S81: =S80+R81
A82: 81 | B82: SELL | C82: 45926 | D82: 15000 | E82: 959.6 | F82: 959.6 | G82: -14.97 | I82: 372.91659 | J82: 288.511 | K82: =IF(AND(B82="SELL",E82>0,J82<>""),J82/E82,0) | L82: 0.288 | M82: =IF(AND(B82="SELL",L82>0),D82*L82,0) | O82: =IF(AND(B82="SELL",G82<>0),Q82/ABS(G82),0) | P82: =IF(AND(B82="SELL",D82>0),R82/D82,0) | Q82: =IF(AND(B82="SELL",D82>0,E82>0),(D82/E82)+G82,0) | R82: =IF(B82="SELL",Q82*F82,0) | S82: =S81+R82
A83: 82 | B83: SELL | C83: 45926 | D83: 100000 | E83: 959.6 | F83: 959.6 | G83: -99.18 | I83: 273.73659 | J83: 290.353 | K83: =IF(AND(B83="SELL",E83>0,J83<>""),J83/E83,0) | L83: 0.288 | M83: =IF(AND(B83="SELL",L83>0),D83*L83,0) | N83: cambio angel | O83: =IF(AND(B83="SELL",G83<>0),Q83/ABS(G83),0) | P83: =IF(AND(B83="SELL",D83>0),R83/D83,0) | Q83: =IF(AND(B83="SELL",D83>0,E83>0),(D83/E83)+G83,0) | R83: =IF(B83="SELL",Q83*F83,0) | S83: =S82+R83
A84: 83 | B84: SELL | C84: 45926 | D84: 100000 | E84: 959.6 | F84: 959.6 | G84: -100 | I84: 173.73659 | J84: 288 | K84: =IF(AND(B84="SELL",E84>0,J84<>""),J84/E84,0) | L84: 0.288 | M84: =IF(AND(B84="SELL",L84>0),D84*L84,0) | N84: cambio angel | O84: =IF(AND(B84="SELL",G84<>0),Q84/ABS(G84),0) | P84: =IF(AND(B84="SELL",D84>0),R84/D84,0) | Q84: =IF(AND(B84="SELL",D84>0,E84>0),(D84/E84)+G84,0) | R84: =IF(B84="SELL",Q84*F84,0) | S84: =S83+R84
A85: 84 | B85: SELL | C85: 45927 | D85: 50000 | E85: 959.6 | F85: 959.6 | G85: -49.65 | I85: 124.08659 | J85: 287 | K85: =IF(AND(B85="SELL",E85>0,J85<>""),J85/E85,0) | L85: 0.285 | M85: =IF(AND(B85="SELL",L85>0),D85*L85,0) | N85: delci | O85: =IF(AND(B85="SELL",G85<>0),Q85/ABS(G85),0) | P85: =IF(AND(B85="SELL",D85>0),R85/D85,0) | Q85: =IF(AND(B85="SELL",D85>0,E85>0),(D85/E85)+G85,0) | R85: =IF(B85="SELL",Q85*F85,0) | S85: =S84+R85
A86: 85 | B86: SELL | C86: 45927 | D86: 20000 | E86: 959.6 | F86: 959.6 | G86: -20.3 | I86: 103.78659 | J86: 280.7 | K86: =IF(AND(B86="SELL",E86>0,J86<>""),J86/E86,0) | L86: 0.285 | M86: =IF(AND(B86="SELL",L86>0),D86*L86,0) | N86: cambio angel | O86: =IF(AND(B86="SELL",G86<>0),Q86/ABS(G86),0) | P86: =IF(AND(B86="SELL",D86>0),R86/D86,0) | Q86: =IF(AND(B86="SELL",D86>0,E86>0),(D86/E86)+G86,0) | R86: =IF(B86="SELL",Q86*F86,0) | S86: =S85+R86
A87: 86 | B87: SELL | C87: 45927 | D87: 70000 | E87: 959.6 | F87: 959.6 | G87: -69.46 | I87: 34.326586 | J87: 282.153 | K87: =IF(AND(B87="SELL",E87>0,J87<>""),J87/E87,0) | L87: 0.28 | M87: =IF(AND(B87="SELL",L87>0),D87*L87,0) | N87: cambio pinky | O87: =IF(AND(B87="SELL",G87<>0),Q87/ABS(G87),0) | P87: =IF(AND(B87="SELL",D87>0),R87/D87,0) | Q87: =IF(AND(B87="SELL",D87>0,E87>0),(D87/E87)+G87,0) | R87: =IF(B87="SELL",Q87*F87,0) | S87: =S86+R87
A88: 87 | B88: BUY | C88: 45927 | D88: 677500 | E88: 964.25 | F88: 964.25 | G88: 702.56 | I88: 736.88659 | K88: =IF(AND(B88="SELL",E88>0,J88<>""),J88/E88,0) | M88: =IF(AND(B88="SELL",L88>0),D88*L88,0) | O88: =IF(AND(B88="SELL",G88<>0),Q88/ABS(G88),0) | P88: =IF(AND(B88="SELL",D88>0),R88/D88,0) | Q88: =IF(AND(B88="SELL",D88>0,E88>0),(D88/E88)+G88,0) | R88: =IF(B88="SELL",Q88*F88,0) | S88: =S87+R88
A89: 88 | B89: SELL | C89: 45927 | D89: 40000 | E89: 964.25 | F89: 964.25 | G89: -39.68 | I89: 697.20659 | J89: 282.215 | K89: =IF(AND(B89="SELL",E89>0,J89<>""),J89/E89,0) | L89: 0.28 | M89: =IF(AND(B89="SELL",L89>0),D89*L89,0) | N89: cambio | O89: =IF(AND(B89="SELL",G89<>0),Q89/ABS(G89),0) | P89: =IF(AND(B89="SELL",D89>0),R89/D89,0) | Q89: =IF(AND(B89="SELL",D89>0,E89>0),(D89/E89)+G89,0) | R89: =IF(B89="SELL",Q89*F89,0) | S89: =S88+R89
A90: 89 | B90: SELL | C90: 45928 | D90: 10000 | E90: 964.25 | F90: 964.25 | G90: -9.97 | I90: 687.23659 | J90: 275.781 | K90: =IF(AND(B90="SELL",E90>0,J90<>""),J90/E90,0) | L90: 0.274 | M90: =IF(AND(B90="SELL",L90>0),D90*L90,0) | N90: cambio mama | O90: =IF(AND(B90="SELL",G90<>0),Q90/ABS(G90),0) | P90: =IF(AND(B90="SELL",D90>0),R90/D90,0) | Q90: =IF(AND(B90="SELL",D90>0,E90>0),(D90/E90)+G90,0) | R90: =IF(B90="SELL",Q90*F90,0) | S90: =S89+R90
A91: 90 | B91: SELL | C91: 45928 | D91: 146671 | E91: 964.25 | F91: 964.25 | G91: -141.35 | I91: 545.88659 | J91: 284.31 | K91: =IF(AND(B91="SELL",E91>0,J91<>""),J91/E91,0) | L91: 0.274 | M91: =IF(AND(B91="SELL",L91>0),D91*L91,0) | N91: cambio turale | O91: =IF(AND(B91="SELL",G91<>0),Q91/ABS(G91),0) | P91: =IF(AND(B91="SELL",D91>0),R91/D91,0) | Q91: =IF(AND(B91="SELL",D91>0,E91>0),(D91/E91)+G91,0) | R91: =IF(B91="SELL",Q91*F91,0) | S91: =S90+R91
A92: 91 | B92: SELL | C92: 45928 | D92: 30000 | E92: 964.25 | F92: 964.25 | G92: -29.36 | I92: 516.52659 | J92: 279.905 | K92: =IF(AND(B92="SELL",E92>0,J92<>""),J92/E92,0) | L92: 0.274 | M92: =IF(AND(B92="SELL",L92>0),D92*L92,0) | O92: =IF(AND(B92="SELL",G92<>0),Q92/ABS(G92),0) | P92: =IF(AND(B92="SELL",D92>0),R92/D92,0) | Q92: =IF(AND(B92="SELL",D92>0,E92>0),(D92/E92)+G92,0) | R92: =IF(B92="SELL",Q92*F92,0) | S92: =S91+R92
A93: 92 | B93: SELL | C93: 45928 | D93: 30000 | E93: 964.25 | F93: 964.25 | G93: -30.41 | I93: 486.11659 | J93: 270.3 | K93: =IF(AND(B93="SELL",E93>0,J93<>""),J93/E93,0) | L93: 0.274 | M93: =IF(AND(B93="SELL",L93>0),D93*L93,0) | O93: =IF(AND(B93="SELL",G93<>0),Q93/ABS(G93),0) | P93: =IF(AND(B93="SELL",D93>0),R93/D93,0) | Q93: =IF(AND(B93="SELL",D93>0,E93>0),(D93/E93)+G93,0) | R93: =IF(B93="SELL",Q93*F93,0) | S93: =S92+R93
A94: 93 | B94: SELL | C94: 45929 | D94: 45000 | E94: 964.25 | F94: 964.25 | G94: -44.05 | I94: 442.06659 | J94: 284 | K94: =IF(AND(B94="SELL",E94>0,J94<>""),J94/E94,0) | L94: 0.275 | M94: =IF(AND(B94="SELL",L94>0),D94*L94,0) | O94: =IF(AND(B94="SELL",G94<>0),Q94/ABS(G94),0) | P94: =IF(AND(B94="SELL",D94>0),R94/D94,0) | Q94: =IF(AND(B94="SELL",D94>0,E94>0),(D94/E94)+G94,0) | R94: =IF(B94="SELL",Q94*F94,0) | S94: =S93+R94
A95: 94 | B95: SELL | C95: 45929 | D95: 15000 | E95: 964.25 | F95: 964.25 | G95: -14.6 | I95: 427.46659 | J95: 282.414 | K95: =IF(AND(B95="SELL",E95>0,J95<>""),J95/E95,0) | L95: 0.275 | M95: =IF(AND(B95="SELL",L95>0),D95*L95,0) | O95: =IF(AND(B95="SELL",G95<>0),Q95/ABS(G95),0) | P95: =IF(AND(B95="SELL",D95>0),R95/D95,0) | Q95: =IF(AND(B95="SELL",D95>0,E95>0),(D95/E95)+G95,0) | R95: =IF(B95="SELL",Q95*F95,0) | S95: =S94+R95
A96: 95 | B96: SELL | C96: 45929 | D96: 10000 | E96: 964.25 | F96: 964.25 | G96: -9.89 | I96: 417.57659 | J96: 278.05 | K96: =IF(AND(B96="SELL",E96>0,J96<>""),J96/E96,0) | L96: 0.275 | M96: =IF(AND(B96="SELL",L96>0),D96*L96,0) | O96: =IF(AND(B96="SELL",G96<>0),Q96/ABS(G96),0) | P96: =IF(AND(B96="SELL",D96>0),R96/D96,0) | Q96: =IF(AND(B96="SELL",D96>0,E96>0),(D96/E96)+G96,0) | R96: =IF(B96="SELL",Q96*F96,0) | S96: =S95+R96
A97: 96 | B97: BUY | C97: 45929 | D97: 877000 | E97: 967 | F97: 967 | G97: 907.65 | I97: 1318.8366 | K97: =IF(AND(B97="SELL",E97>0,J97<>""),J97/E97,0) | M97: =IF(AND(B97="SELL",L97>0),D97*L97,0) | N97: cambio capital | O97: =IF(AND(B97="SELL",G97<>0),Q97/ABS(G97),0) | P97: =IF(AND(B97="SELL",D97>0),R97/D97,0) | Q97: =IF(AND(B97="SELL",D97>0,E97>0),(D97/E97)+G97,0) | R97: =IF(B97="SELL",Q97*F97,0) | S97: =S96+R97
A98: 97 | B98: SELL | C98: 45929 | D98: 550000 | E98: 967 | F98: 967 | G98: -541.42 | I98: 777.41659 | J98: 1.014 | K98: =IF(AND(B98="SELL",E98>0,J98<>""),J98/E98,0) | L98: 0.000999 | M98: =IF(AND(B98="SELL",L98>0),D98*L98,0) | O98: =IF(AND(B98="SELL",G98<>0),Q98/ABS(G98),0) | P98: =IF(AND(B98="SELL",D98>0),R98/D98,0) | Q98: =IF(AND(B98="SELL",D98>0,E98>0),(D98/E98)+G98,0) | R98: =IF(B98="SELL",Q98*F98,0) | S98: =S97+R98
A99: 98 | B99: SELL | C99: 45929 | D99: 55000 | E99: 967 | F99: 967 | G99: -52.72 | I99: 724.69659 | J99: 285.851 | K99: =IF(AND(B99="SELL",E99>0,J99<>""),J99/E99,0) | L99: 0.275 | M99: =IF(AND(B99="SELL",L99>0),D99*L99,0) | N99: cambio uvida | O99: =IF(AND(B99="SELL",G99<>0),Q99/ABS(G99),0) | P99: =IF(AND(B99="SELL",D99>0),R99/D99,0) | Q99: =IF(AND(B99="SELL",D99>0,E99>0),(D99/E99)+G99,0) | R99: =IF(B99="SELL",Q99*F99,0) | S99: =S98+R99
A100: 99 | B100: SELL | C100: 45930 | D100: 20000 | E100: 967 | F100: 967 | G100: -20.28 | I100: 704.41659 | J100: 276 | K100: =IF(AND(B100="SELL",E100>0,J100<>""),J100/E100,0) | L100: 0.28 | M100: =IF(AND(B100="SELL",L100>0),D100*L100,0) | N100: cambiopaula uvida | O100: =IF(AND(B100="SELL",G100<>0),Q100/ABS(G100),0) | P100: =IF(AND(B100="SELL",D100>0),R100/D100,0) | Q100: =IF(AND(B100="SELL",D100>0,E100>0),(D100/E100)+G100,0) | R100: =IF(B100="SELL",Q100*F100,0) | S100: =S99+R100
...

Sheet Octubre 2025
A1: N° | B1: Tipo | C1: Fecha | D1: Monto CLP | E1: USDT/CLP Compra | F1: USDT/CLP Venta | G1: USDT Mov | H1: Tax Binance | I1: Capital USDT | J1: Tasa Destino | K1: Tasa Real | L1: Tasa IREMI | M1: Valor Destino | N1: Comentario | O1: % G USDT | P1: % G CLP | Q1: Ganancia USDT | R1: Ganancia CLP | S1: Acumulado SELL
A2: 1 | B2: SELL | C2: 45930 | D2: 20000 | E2: 967 | F2: 967 | G2: -19.95 | I2: 375.03 | J2: 280.6 | K2: =IF(AND(B2="SELL",E2>0,J2<>""),J2/E2,0) | L2: 0.28 | M2: =IF(AND(B2="SELL",L2>0),D2*L2,0) | O2: =IF(AND(B2="SELL",G2<>0),Q2/ABS(G2),0) | P2: =IF(AND(B2="SELL",D2>0),R2/D2,0) | Q2: =IF(AND(B2="SELL",D2>0,E2>0),(D2/E2)+G2,0) | R2: =IF(B2="SELL",Q2*F2,0) | S2: ='Septiembre 2025'!S104+R2
A3: 2 | B3: SELL | C3: 45931 | D3: 165000 | E3: 967 | F3: 967 | G3: -162.92 | I3: 212.11 | J3: 285.2 | K3: =IF(AND(B3="SELL",E3>0,J3<>""),J3/E3,0) | L3: 0.278 | M3: =IF(AND(B3="SELL",L3>0),D3*L3,0) | N3: Cambio uvida y francisco | O3: =IF(AND(B3="SELL",G3<>0),Q3/ABS(G3),0) | P3: =IF(AND(B3="SELL",D3>0),R3/D3,0) | Q3: =IF(AND(B3="SELL",D3>0,E3>0),(D3/E3)+G3,0) | R3: =IF(B3="SELL",Q3*F3,0) | S3: =S2+R3
A4: 3 | B4: SELL | C4: 45931 | D4: 110000 | E4: 967 | F4: 967 | G4: -106.87 | I4: 105.24 | J4: 289.21 | K4: =IF(AND(B4="SELL",E4>0,J4<>""),J4/E4,0) | L4: 0.281 | M4: =IF(AND(B4="SELL",L4>0),D4*L4,0) | N4: cambio angel | O4: =IF(AND(B4="SELL",G4<>0),Q4/ABS(G4),0) | P4: =IF(AND(B4="SELL",D4>0),R4/D4,0) | Q4: =IF(AND(B4="SELL",D4>0,E4>0),(D4/E4)+G4,0) | R4: =IF(B4="SELL",Q4*F4,0) | S4: =S3+R4
A5: 4 | B5: SELL | C5: 45931 | D5: 100000 | E5: 967 | F5: 967 | G5: -97.48 | I5: 7.76 | J5: 288.25 | K5: =IF(AND(B5="SELL",E5>0,J5<>""),J5/E5,0) | L5: 0.281 | M5: =IF(AND(B5="SELL",L5>0),D5*L5,0) | O5: =IF(AND(B5="SELL",G5<>0),Q5/ABS(G5),0) | P5: =IF(AND(B5="SELL",D5>0),R5/D5,0) | Q5: =IF(AND(B5="SELL",D5>0,E5>0),(D5/E5)+G5,0) | R5: =IF(B5="SELL",Q5*F5,0) | S5: =S4+R5
A6: 5 | B6: BUY | C6: 45931 | D6: 1020000 | E6: 964.8 | F6: 964.8 | G6: 1057.21 | I6: 1064.97 | K6: =IF(AND(B6="SELL",E6>0,J6<>""),J6/E6,0) | M6: =IF(AND(B6="SELL",L6>0),D6*L6,0) | O6: =IF(AND(B6="SELL",G6<>0),Q6/ABS(G6),0) | P6: =IF(AND(B6="SELL",D6>0),R6/D6,0) | Q6: =IF(AND(B6="SELL",D6>0,E6>0),(D6/E6)+G6,0) | R6: =IF(B6="SELL",Q6*F6,0) | S6: =S5+R6
A7: 6 | B7: SELL | C7: 45931 | D7: 105000 | E7: 964.8 | F7: 964.8 | G7: -102.21 | I7: 962.76 | J7: 288.65 | K7: =IF(AND(B7="SELL",E7>0,J7<>""),J7/E7,0) | L7: 0.281 | M7: =IF(AND(B7="SELL",L7>0),D7*L7,0) | O7: =IF(AND(B7="SELL",G7<>0),Q7/ABS(G7),0) | P7: =IF(AND(B7="SELL",D7>0),R7/D7,0) | Q7: =IF(AND(B7="SELL",D7>0,E7>0),(D7/E7)+G7,0) | R7: =IF(B7="SELL",Q7*F7,0) | S7: =S6+R7
A8: 7 | B8: SELL | C8: 45931 | D8: 18000 | E8: 964.8 | F8: 964.8 | G8: -17.8 | I8: 944.96 | J8: 284.005 | K8: =IF(AND(B8="SELL",E8>0,J8<>""),J8/E8,0) | L8: 0.281 | M8: =IF(AND(B8="SELL",L8>0),D8*L8,0) | O8: =IF(AND(B8="SELL",G8<>0),Q8/ABS(G8),0) | P8: =IF(AND(B8="SELL",D8>0),R8/D8,0) | Q8: =IF(AND(B8="SELL",D8>0,E8>0),(D8/E8)+G8,0) | R8: =IF(B8="SELL",Q8*F8,0) | S8: =S7+R8
A9: 8 | B9: SELL | C9: 45932 | D9: 130000 | E9: 964.8 | F9: 964.8 | G9: -127.09 | I9: 817.87 | J9: 291.51 | K9: =IF(AND(B9="SELL",E9>0,J9<>""),J9/E9,0) | L9: 0.285 | M9: =IF(AND(B9="SELL",L9>0),D9*L9,0) | O9: =IF(AND(B9="SELL",G9<>0),Q9/ABS(G9),0) | P9: =IF(AND(B9="SELL",D9>0),R9/D9,0) | Q9: =IF(AND(B9="SELL",D9>0,E9>0),(D9/E9)+G9,0) | R9: =IF(B9="SELL",Q9*F9,0) | S9: =S8+R9
A10: 9 | B10: SELL | C10: 45932 | D10: 50000 | E10: 964.8 | F10: 964.8 | G10: -49.82 | I10: 768.05 | J10: 286 | K10: =IF(AND(B10="SELL",E10>0,J10<>""),J10/E10,0) | L10: 0.285 | M10: =IF(AND(B10="SELL",L10>0),D10*L10,0) | O10: =IF(AND(B10="SELL",G10<>0),Q10/ABS(G10),0) | P10: =IF(AND(B10="SELL",D10>0),R10/D10,0) | Q10: =IF(AND(B10="SELL",D10>0,E10>0),(D10/E10)+G10,0) | R10: =IF(B10="SELL",Q10*F10,0) | S10: =S9+R10
A11: 10 | B11: SELL | C11: 45932 | D11: 40000 | E11: 964.8 | F11: 964.8 | G11: -39.37 | I11: 728.68 | J11: 289.519 | K11: =IF(AND(B11="SELL",E11>0,J11<>""),J11/E11,0) | L11: 0.285 | M11: =IF(AND(B11="SELL",L11>0),D11*L11,0) | O11: =IF(AND(B11="SELL",G11<>0),Q11/ABS(G11),0) | P11: =IF(AND(B11="SELL",D11>0),R11/D11,0) | Q11: =IF(AND(B11="SELL",D11>0,E11>0),(D11/E11)+G11,0) | R11: =IF(B11="SELL",Q11*F11,0) | S11: =S10+R11
A12: 11 | B12: SELL | C12: 45932 | D12: 20000 | E12: 964.8 | F12: 964.8 | G12: -19.9 | I12: 708.78 | J12: 3421 | K12: =IF(AND(B12="SELL",E12>0,J12<>""),J12/E12,0) | L12: 0.0034 | M12: =IF(AND(B12="SELL",L12>0),D12*L12,0) | O12: =IF(AND(B12="SELL",G12<>0),Q12/ABS(G12),0) | P12: =IF(AND(B12="SELL",D12>0),R12/D12,0) | Q12: =IF(AND(B12="SELL",D12>0,E12>0),(D12/E12)+G12,0) | R12: =IF(B12="SELL",Q12*F12,0) | S12: =S11+R12
A13: 12 | B13: SELL | C13: 45933 | D13: 22000 | E13: 964.8 | F13: 964.8 | G13: -22.19 | I13: 686.59 | J13: 286.5 | K13: =IF(AND(B13="SELL",E13>0,J13<>""),J13/E13,0) | L13: 0.289 | M13: =IF(AND(B13="SELL",L13>0),D13*L13,0) | O13: =IF(AND(B13="SELL",G13<>0),Q13/ABS(G13),0) | P13: =IF(AND(B13="SELL",D13>0),R13/D13,0) | Q13: =IF(AND(B13="SELL",D13>0,E13>0),(D13/E13)+G13,0) | R13: =IF(B13="SELL",Q13*F13,0) | S13: =S12+R13
A14: 13 | B14: SELL | C14: 45933 | D14: 80000 | E14: 964.8 | F14: 964.8 | G14: -79.92 | I14: 606.67 | J14: 289.26 | K14: =IF(AND(B14="SELL",E14>0,J14<>""),J14/E14,0) | L14: 0.289 | M14: =IF(AND(B14="SELL",L14>0),D14*L14,0) | O14: =IF(AND(B14="SELL",G14<>0),Q14/ABS(G14),0) | P14: =IF(AND(B14="SELL",D14>0),R14/D14,0) | Q14: =IF(AND(B14="SELL",D14>0,E14>0),(D14/E14)+G14,0) | R14: =IF(B14="SELL",Q14*F14,0) | S14: =S13+R14
A15: 14 | B15: SELL | C15: 45933 | D15: 80000 | E15: 964.8 | F15: 964.8 | G15: -79.28 | I15: 527.39 | J15: 291.61 | K15: =IF(AND(B15="SELL",E15>0,J15<>""),J15/E15,0) | L15: 0.289 | M15: =IF(AND(B15="SELL",L15>0),D15*L15,0) | O15: =IF(AND(B15="SELL",G15<>0),Q15/ABS(G15),0) | P15: =IF(AND(B15="SELL",D15>0),R15/D15,0) | Q15: =IF(AND(B15="SELL",D15>0,E15>0),(D15/E15)+G15,0) | R15: =IF(B15="SELL",Q15*F15,0) | S15: =S14+R15
A16: 15 | B16: SELL | C16: 45933 | D16: 25000 | E16: 964.8 | F16: 964.8 | G16: -25.21 | I16: 502.18 | J16: 286 | K16: =IF(AND(B16="SELL",E16>0,J16<>""),J16/E16,0) | L16: 0.289 | M16: =IF(AND(B16="SELL",L16>0),D16*L16,0) | O16: =IF(AND(B16="SELL",G16<>0),Q16/ABS(G16),0) | P16: =IF(AND(B16="SELL",D16>0),R16/D16,0) | Q16: =IF(AND(B16="SELL",D16>0,E16>0),(D16/E16)+G16,0) | R16: =IF(B16="SELL",Q16*F16,0) | S16: =S15+R16
A17: 16 | B17: SELL | C17: 45934 | D17: 20000 | E17: 964.8 | F17: 964.8 | G17: -19.39 | I17: 482.79 | J17: 291.858 | K17: =IF(AND(B17="SELL",E17>0,J17<>""),J17/E17,0) | L17: 0.283 | M17: =IF(AND(B17="SELL",L17>0),D17*L17,0) | O17: =IF(AND(B17="SELL",G17<>0),Q17/ABS(G17),0) | P17: =IF(AND(B17="SELL",D17>0),R17/D17,0) | Q17: =IF(AND(B17="SELL",D17>0,E17>0),(D17/E17)+G17,0) | R17: =IF(B17="SELL",Q17*F17,0) | S17: =S16+R17
A18: 17 | B18: SELL | C18: 45934 | D18: 53200 | E18: 964.8 | F18: 964.8 | G18: -51.58 | I18: 431.21 | J18: 291.858 | K18: =IF(AND(B18="SELL",E18>0,J18<>""),J18/E18,0) | L18: 0.283 | M18: =IF(AND(B18="SELL",L18>0),D18*L18,0) | O18: =IF(AND(B18="SELL",G18<>0),Q18/ABS(G18),0) | P18: =IF(AND(B18="SELL",D18>0),R18/D18,0) | Q18: =IF(AND(B18="SELL",D18>0,E18>0),(D18/E18)+G18,0) | R18: =IF(B18="SELL",Q18*F18,0) | S18: =S17+R18
... A28: 27 | B28: SELL | C28: 45938 | D28: 20000 | E28: 964.8 | F28: 964.8 | G28: -19.68 | I28: -177.8 | J28: 297.612 | K28: =IF(AND(B28="SELL",E28>0,J28<>""),J28/E28,0) | L28: 0.293 | M28: =IF(AND(B28="SELL",L28>0),D28*L28,0) | O28: =IF(AND(B28="SELL",G28<>0),Q28/ABS(G28),0) | P28: =IF(AND(B28="SELL",D28>0),R28/D28,0) | Q28: =IF(AND(B28="SELL",D28>0,E28>0),(D28/E28)+G28,0) | R28: =IF(B28="SELL",Q28*F28,0) | S28: =S27+R28
A29: 28 | B29: BUY | C29: 45938 | D29: 998700 | E29: 963 | F29: 963 | G29: 1038.42 | I29: 860.62 | K29: =IF(AND(B29="SELL",E29>0,J29<>""),J29/E29,0) | L29: 0 | M29: =IF(AND(B29="SELL",L29>0),D29*L29,0) | N29: Compra de USDT | O29: =IF(AND(B29="SELL",G29<>0),Q29/ABS(G29),0) | P29: =IF(AND(B29="SELL",D29>0),R29/D29,0) | Q29: =IF(AND(B29="SELL",D29>0,E29>0),(D29/E29)+G29,0) | R29: =IF(B29="SELL",Q29*F29,0) | S29: =S28+R29
A30: 29 | B30: SELL | C30: 45938 | D30: 30000 | E30: 963 | F30: 963 | G30: -29.17 | I30: 831.45 | K30: =IF(AND(B30="SELL",E30>0,J30<>""),J30/E30,0) | L30: 0.000845 | M30: =IF(AND(B30="SELL",L30>0),D30*L30,0) | O30: =IF(AND(B30="SELL",G30<>0),Q30/ABS(G30),0) | P30: =IF(AND(B30="SELL",D30>0),R30/D30,0) | Q30: =IF(AND(B30="SELL",D30>0,E30>0),(D30/E30)+G30,0) | R30: =IF(B30="SELL",Q30*F30,0) | S30: =S29+R30
A31: 30 | B31: SELL | C31: 45938 | D31: 100000 | E31: 963 | F31: 963 | G31: -94.24 | I31: 737.21 | K31: =IF(AND(B31="SELL",E31>0,J31<>""),J31/E31,0) | L31: 0.0172 | M31: =IF(AND(B31="SELL",L31>0),D31*L31,0) | N31: cambio mex | O31: =IF(AND(B31="SELL",G31<>0),Q31/ABS(G31),0) | P31: =IF(AND(B31="SELL",D31>0),R31/D31,0) | Q31: =IF(AND(B31="SELL",D31>0,E31>0),(D31/E31)+G31,0) | R31: =IF(B31="SELL",Q31*F31,0) | S31: =S30+R31
A32: 31 | B32: SELL | C32: 45939 | D32: 25000 | E32: 963 | F32: 963 | G32: -24.51 | I32: 712.7 | J32: 298.8 | K32: =IF(AND(B32="SELL",E32>0,J32<>""),J32/E32,0) | L32: 0.293 | M32: =IF(AND(B32="SELL",L32>0),D32*L32,0) | O32: =IF(AND(B32="SELL",G32<>0),Q32/ABS(G32),0) | P32: =IF(AND(B32="SELL",D32>0),R32/D32,0) | Q32: =IF(AND(B32="SELL",D32>0,E32>0),(D32/E32)+G32,0) | R32: =IF(B32="SELL",Q32*F32,0) | S32: =S31+R32
A33: 32 | B33: SELL | C33: 45939 | D33: 25000 | E33: 963 | F33: 963 | G33: -24.51 | I33: 688.19 | J33: 298.8 | K33: =IF(AND(B33="SELL",E33>0,J33<>""),J33/E33,0) | L33: 0.293 | M33: =IF(AND(B33="SELL",L33>0),D33*L33,0) | O33: =IF(AND(B33="SELL",G33<>0),Q33/ABS(G33),0) | P33: =IF(AND(B33="SELL",D33>0),R33/D33,0) | Q33: =IF(AND(B33="SELL",D33>0,E33>0),(D33/E33)+G33,0) | R33: =IF(B33="SELL",Q33*F33,0) | S33: =S32+R33
A34: 33 | B34: SELL | C34: 45939 | D34: 32700 | E34: 963 | F34: 963 | G34: -32.06 | I34: 656.13 | J34: 298.8 | K34: =IF(AND(B34="SELL",E34>0,J34<>""),J34/E34,0) | L34: 0.293 | M34: =IF(AND(B34="SELL",L34>0),D34*L34,0) | O34: =IF(AND(B34="SELL",G34<>0),Q34/ABS(G34),0) | P34: =IF(AND(B34="SELL",D34>0),R34/D34,0) | Q34: =IF(AND(B34="SELL",D34>0,E34>0),(D34/E34)+G34,0) | R34: =IF(B34="SELL",Q34*F34,0) | S34: =S33+R34
A35: 34 | B35: SELL | C35: 45939 | D35: 100000 | E35: 963 | F35: 963 | G35: -98.05 | I35: 558.08 | J35: 298.8 | K35: =IF(AND(B35="SELL",E35>0,J35<>""),J35/E35,0) | L35: 0.293 | M35: =IF(AND(B35="SELL",L35>0),D35*L35,0) | O35: =IF(AND(B35="SELL",G35<>0),Q35/ABS(G35),0) | P35: =IF(AND(B35="SELL",D35>0),R35/D35,0) | Q35: =IF(AND(B35="SELL",D35>0,E35>0),(D35/E35)+G35,0) | R35: =IF(B35="SELL",Q35*F35,0) | S35: =S34+R35
A36: 35 | B36: SELL | C36: 45939 | D36: 17000 | E36: 963 | F36: 963 | G36: -16.69 | I36: 541.39 | J36: 298.401 | K36: =IF(AND(B36="SELL",E36>0,J36<>""),J36/E36,0) | L36: 0.293 | M36: =IF(AND(B36="SELL",L36>0),D36*L36,0) | O36: =IF(AND(B36="SELL",G36<>0),Q36/ABS(G36),0) | P36: =IF(AND(B36="SELL",D36>0),R36/D36,0) | Q36: =IF(AND(B36="SELL",D36>0,E36>0),(D36/E36)+G36,0) | R36: =IF(B36="SELL",Q36*F36,0) | S36: =S35+R36
A37: 36 | B37: SELL | C37: 45940 | D37: 20000 | E37: 963 | F37: 963 | G37: -19.43 | I37: 521.96 | J37: 298.401 | K37: =IF(AND(B37="SELL",E37>0,J37<>""),J37/E37,0) | L37: 0.29 | M37: =IF(AND(B37="SELL",L37>0),D37*L37,0) | O37: =IF(AND(B37="SELL",G37<>0),Q37/ABS(G37),0) | P37: =IF(AND(B37="SELL",D37>0),R37/D37,0) | Q37: =IF(AND(B37="SELL",D37>0,E37>0),(D37/E37)+G37,0) | R37: =IF(B37="SELL",Q37*F37,0) | S37: =S36+R37
A38: 37 | B38: SELL | C38: 45940 | D38: 30000 | E38: 963 | F38: 963 | G38: -29.15 | I38: 492.81 | J38: 298.401 | K38: =IF(AND(B38="SELL",E38>0,J38<>""),J38/E38,0) | L38: 0.29 | M38: =IF(AND(B38="SELL",L38>0),D38*L38,0) | O38: =IF(AND(B38="SELL",G38<>0),Q38/ABS(G38),0) | P38: =IF(AND(B38="SELL",D38>0),R38/D38,0) | Q38: =IF(AND(B38="SELL",D38>0,E38>0),(D38/E38)+G38,0) | R38: =IF(B38="SELL",Q38*F38,0) | S38: =S37+R38
A39: 38 | B39: SELL | C39: 45940 | D39: 20000 | E39: 963 | F39: 963 | G39: -19.43 | I39: 473.38 | J39: 298.401 | K39: =IF(AND(B39="SELL",E39>0,J39<>""),J39/E39,0) | L39: 0.29 | M39: =IF(AND(B39="SELL",L39>0),D39*L39,0) | O39: =IF(AND(B39="SELL",G39<>0),Q39/ABS(G39),0) | P39: =IF(AND(B39="SELL",D39>0),R39/D39,0) | Q39: =IF(AND(B39="SELL",D39>0,E39>0),(D39/E39)+G39,0) | R39: =IF(B39="SELL",Q39*F39,0) | S39: =S38+R39
A40: 39 | B40: SELL | C40: 45940 | D40: 50000 | E40: 963 | F40: 963 | G40: -48.59 | I40: 424.79 | J40: 298.401 | K40: =IF(AND(B40="SELL",E40>0,J40<>""),J40/E40,0) | L40: 0.29 | M40: =IF(AND(B40="SELL",L40>0),D40*L40,0) | O40: =IF(AND(B40="SELL",G40<>0),Q40/ABS(G40),0) | P40: =IF(AND(B40="SELL",D40>0),R40/D40,0) | Q40: =IF(AND(B40="SELL",D40>0,E40>0),(D40/E40)+G40,0) | R40: =IF(B40="SELL",Q40*F40,0) | S40: =S39+R40
A41: 40 | B41: SELL | C41: 45941 | D41: 30000 | E41: 963 | F41: 963 | G41: -28.71 | I41: 396.08 | J41: 284.5 | K41: =IF(AND(B41="SELL",E41>0,J41<>""),J41/E41,0) | L41: 0.288 | M41: =IF(AND(B41="SELL",L41>0),D41*L41,0) | N41: cambio zuleika | O41: =IF(AND(B41="SELL",G41<>0),Q41/ABS(G41),0) | P41: =IF(AND(B41="SELL",D41>0),R41/D41,0) | Q41: =IF(AND(B41="SELL",D41>0,E41>0),(D41/E41)+G41,0) | R41: =IF(B41="SELL",Q41*F41,0) | S41: =S40+R41
A42: 41 | B42: SELL | C42: 45941 | D42: 50000 | E42: 963 | F42: 963 | G42: -49.93 | I42: 346.15 | J42: 290.35 | K42: =IF(AND(B42="SELL",E42>0,J42<>""),J42/E42,0) | L42: 0.288 | M42: =IF(AND(B42="SELL",L42>0),D42*L42,0) | N42: cambio paula papa | O42: =IF(AND(B42="SELL",G42<>0),Q42/ABS(G42),0) | P42: =IF(AND(B42="SELL",D42>0),R42/D42,0) | Q42: =IF(AND(B42="SELL",D42>0,E42>0),(D42/E42)+G42,0) | R42: =IF(B42="SELL",Q42*F42,0) | S42: =S41+R42
A43: 42 | B43: SELL | C43: 45941 | D43: 90000 | E43: 963 | F43: 963 | G43: -89.25 | I43: 256.9 | J43: 290.401 | K43: =IF(AND(B43="SELL",E43>0,J43<>""),J43/E43,0) | L43: 0.288 | M43: =IF(AND(B43="SELL",L43>0),D43*L43,0) | N43: cambio pinky | O43: =IF(AND(B43="SELL",G43<>0),Q43/ABS(G43),0) | P43: =IF(AND(B43="SELL",D43>0),R43/D43,0) | Q43: =IF(AND(B43="SELL",D43>0,E43>0),(D43/E43)+G43,0) | R43: =IF(B43="SELL",Q43*F43,0) | S43: =S42+R43
A44: 43 | B44: SELL | C44: 45942 | D44: 40000 | E44: 963 | F44: 963 | G44: -39.83 | I44: 442.07 | J44: 288.703 | K44: =IF(AND(B44="SELL",E44>0,J44<>""),J44/E44,0) | L44: 0.2875 | M44: =IF(AND(B44="SELL",L44>0),D44*L44,0) | O44: =IF(AND(B44="SELL",G44<>0),Q44/ABS(G44),0) | P44: =IF(AND(B44="SELL",D44>0),R44/D44,0) | Q44: =IF(AND(B44="SELL",D44>0,E44>0),(D44/E44)+G44,0) | R44: =IF(B44="SELL",Q44*F44,0) | S44: =S43+R44
A45: 44 | B45: SELL | C45: 45942 | D45: 40000 | E45: 963 | F45: 963 | G45: -39.87 | I45: 402.2 | J45: 288.4 | K45: =IF(AND(B45="SELL",E45>0,J45<>""),J45/E45,0) | L45: 0.2875 | M45: =IF(AND(B45="SELL",L45>0),D45*L45,0) | O45: =IF(AND(B45="SELL",G45<>0),Q45/ABS(G45),0) | P45: =IF(AND(B45="SELL",D45>0),R45/D45,0) | Q45: =IF(AND(B45="SELL",D45>0,E45>0),(D45/E45)+G45,0) | R45: =IF(B45="SELL",Q45*F45,0) | S45: =S44+R45
A46: 45 | B46: SELL | C46: 45943 | D46: 40000 | E46: 963 | F46: 963 | G46: -39.63 | I46: 362.57 | J46: 289.662 | K46: =IF(AND(B46="SELL",E46>0,J46<>""),J46/E46,0) | L46: 0.287 | M46: =IF(AND(B46="SELL",L46>0),D46*L46,0) | O46: =IF(AND(B46="SELL",G46<>0),Q46/ABS(G46),0) | P46: =IF(AND(B46="SELL",D46>0),R46/D46,0) | Q46: =IF(AND(B46="SELL",D46>0,E46>0),(D46/E46)+G46,0) | R46: =IF(B46="SELL",Q46*F46,0) | S46: =S45+R46
A47: 46 | B47: SELL | C47: 45943 | D47: 25000 | E47: 963 | F47: 963 | G47: -24.69 | I47: 337.88 | J47: 290.57 | K47: =IF(AND(B47="SELL",E47>0,J47<>""),J47/E47,0) | L47: 0.287 | M47: =IF(AND(B47="SELL",L47>0),D47*L47,0) | O47: =IF(AND(B47="SELL",G47<>0),Q47/ABS(G47),0) | P47: =IF(AND(B47="SELL",D47>0),R47/D47,0) | Q47: =IF(AND(B47="SELL",D47>0,E47>0),(D47/E47)+G47,0) | R47: =IF(B47="SELL",Q47*F47,0) | S47: =S46+R47
A48: 47 | B48: SELL | C48: 45943 | D48: 25000 | E48: 963 | F48: 963 | G48: -24.41 | I48: 313.47 | J48: 293.8565 | K48: =IF(AND(B48="SELL",E48>0,J48<>""),J48/E48,0) | L48: 0.287 | M48: =IF(AND(B48="SELL",L48>0),D48*L48,0) | O48: =IF(AND(B48="SELL",G48<>0),Q48/ABS(G48),0) | P48: =IF(AND(B48="SELL",D48>0),R48/D48,0) | Q48: =IF(AND(B48="SELL",D48>0,E48>0),(D48/E48)+G48,0) | R48: =IF(B48="SELL",Q48*F48,0) | S48: =S47+R48
A49: 48 | B49: SELL | C49: 45944 | D49: 35100 | E49: 963 | F49: 963 | G49: -34.31 | I49: 279.16 | J49: 294.5 | K49: =IF(AND(B49="SELL",E49>0,J49<>""),J49/E49,0) | L49: 0.288 | M49: =IF(AND(B49="SELL",L49>0),D49*L49,0) | O49: =IF(AND(B49="SELL",G49<>0),Q49/ABS(G49),0) | P49: =IF(AND(B49="SELL",D49>0),R49/D49,0) | Q49: =IF(AND(B49="SELL",D49>0,E49>0),(D49/E49)+G49,0) | R49: =IF(B49="SELL",Q49*F49,0) | S49: =S48+R49
A50: 49 | B50: SELL | C50: 45944 | D50: 383500 | E50: 963 | F50: 963 | G50: -379 | I50: -99.84 | J50: 3.43 | K50: =IF(AND(B50="SELL",E50>0,J50<>""),J50/E50,0) | L50: 0.00339 | M50: =IF(AND(B50="SELL",L50>0),D50*L50,0) | N50: cambio a soles | O50: =IF(AND(B50="SELL",G50<>0),Q50/ABS(G50),0) | P50: =IF(AND(B50="SELL",D50>0),R50/D50,0) | Q50: =IF(AND(B50="SELL",D50>0,E50>0),(D50/E50)+G50,0) | R50: =IF(B50="SELL",Q50*F50,0) | S50: =S49+R50
A51: 50 | B51: SELL | C51: 45944 | D51: 20000 | E51: 963 | F51: 963 | G51: -19.72 | I51: -119.56 | J51: 292 | K51: =IF(AND(B51="SELL",E51>0,J51<>""),J51/E51,0) | L51: 0.288 | M51: =IF(AND(B51="SELL",L51>0),D51*L51,0) | O51: =IF(AND(B51="SELL",G51<>0),Q51/ABS(G51),0) | P51: =IF(AND(B51="SELL",D51>0),R51/D51,0) | Q51: =IF(AND(B51="SELL",D51>0,E51>0),(D51/E51)+G51,0) | R51: =IF(B51="SELL",Q51*F51,0) | S51: =S50+R51
A52: 51 | B52: BUY | C52: 45944 | D52: 1200000 | E52: 965 | F52: 965 | G52: 1243.36 | I52: 1123.8 | K52: =IF(AND(B52="SELL",E52>0,J52<>""),J52/E52,0) | M52: =IF(AND(B52="SELL",L52>0),D52*L52,0) | O52: =IF(AND(B52="SELL",G52<>0),Q52/ABS(G52),0) | P52: =IF(AND(B52="SELL",D52>0),R52/D52,0) | Q52: =IF(AND(B52="SELL",D52>0,E52>0),(D52/E52)+G52,0) | R52: =IF(B52="SELL",Q52*F52,0) | S52: =S51+R52
A53: 52 | B53: SELL | C53: 45944 | D53: 20000 | E53: 965 | F53: 965 | G53: -19.65 | I53: 1104.15 | J53: 293 | K53: =IF(AND(B53="SELL",E53>0,J53<>""),J53/E53,0) | L53: 0.288 | M53: =IF(AND(B53="SELL",L53>0),D53*L53,0) | O53: =IF(AND(B53="SELL",G53<>0),Q53/ABS(G53),0) | P53: =IF(AND(B53="SELL",D53>0),R53/D53,0) | Q53: =IF(AND(B53="SELL",D53>0,E53>0),(D53/E53)+G53,0) | R53: =IF(B53="SELL",Q53*F53,0) | S53: =S52+R53
A54: 53 | B54: SELL | C54: 45945 | D54: 80000 | E54: 965 | F54: 965 | G54: -78.45 | I54: 1025.7 | J54: 289.6 | K54: =IF(AND(B54="SELL",E54>0,J54<>""),J54/E54,0) | L54: 0.284 | M54: =IF(AND(B54="SELL",L54>0),D54*L54,0) | O54: =IF(AND(B54="SELL",G54<>0),Q54/ABS(G54),0) | P54: =IF(AND(B54="SELL",D54>0),R54/D54,0) | Q54: =IF(AND(B54="SELL",D54>0,E54>0),(D54/E54)+G54,0) | R54: =IF(B54="SELL",Q54*F54,0) | S54: =S53+R54
A55: 54 | B55: SELL | C55: 45945 | D55: 40000 | E55: 965 | F55: 965 | G55: -39.3 | I55: 986.4 | J55: 289.04 | K55: =IF(AND(B55="SELL",E55>0,J55<>""),J55/E55,0) | L55: 0.284 | M55: =IF(AND(B55="SELL",L55>0),D55*L55,0) | O55: =IF(AND(B55="SELL",G55<>0),Q55/ABS(G55),0) | P55: =IF(AND(B55="SELL",D55>0),R55/D55,0) | Q55: =IF(AND(B55="SELL",D55>0,E55>0),(D55/E55)+G55,0) | R55: =IF(B55="SELL",Q55*F55,0) | S55: =S54+R55
A56: 55 | B56: SELL | C56: 45945 | D56: 50000 | E56: 965 | F56: 965 | G56: -49.04 | I56: 937.36 | J56: 289.535 | K56: =IF(AND(B56="SELL",E56>0,J56<>""),J56/E56,0) | L56: 0.284 | M56: =IF(AND(B56="SELL",L56>0),D56*L56,0) | O56: =IF(AND(B56="SELL",G56<>0),Q56/ABS(G56),0) | P56: =IF(AND(B56="SELL",D56>0),R56/D56,0) | Q56: =IF(AND(B56="SELL",D56>0,E56>0),(D56/E56)+G56,0) | R56: =IF(B56="SELL",Q56*F56,0) | S56: =S55+R56
A57: 56 | B57: SELL | C57: 45946 | D57: 70000 | E57: 965 | F57: 965 | G57: -68.19 | I57: 869.17 | J57: 292.529 | K57: =IF(AND(B57="SELL",E57>0,J57<>""),J57/E57,0) | L57: 0.285 | M57: =IF(AND(B57="SELL",L57>0),D57*L57,0) | O57: =IF(AND(B57="SELL",G57<>0),Q57/ABS(G57),0) | P57: =IF(AND(B57="SELL",D57>0),R57/D57,0) | Q57: =IF(AND(B57="SELL",D57>0,E57>0),(D57/E57)+G57,0) | R57: =IF(B57="SELL",Q57*F57,0) | S57: =S56+R57
A58: 57 | B58: SELL | C58: 45946 | D58: 5000 | E58: 965 | F58: 965 | G58: -4.96 | I58: 864.21 | J58: 287 | K58: =IF(AND(B58="SELL",E58>0,J58<>""),J58/E58,0) | L58: 0.285 | M58: =IF(AND(B58="SELL",L58>0),D58*L58,0) | O58: =IF(AND(B58="SELL",G58<>0),Q58/ABS(G58),0) | P58: =IF(AND(B58="SELL",D58>0),R58/D58,0) | Q58: =IF(AND(B58="SELL",D58>0,E58>0),(D58/E58)+G58,0) | R58: =IF(B58="SELL",Q58*F58,0) | S58: =S57+R58
A59: 58 | B59: SELL | C59: 45946 | D59: 100000 | E59: 965 | F59: 965 | G59: -96.16 | I59: 768.05 | J59: 296.364 | K59: =IF(AND(B59="SELL",E59>0,J59<>""),J59/E59,0) | L59: 0.285 | M59: =IF(AND(B59="SELL",L59>0),D59*L59,0) | O59: =IF(AND(B59="SELL",G59<>0),Q59/ABS(G59),0) | P59: =IF(AND(B59="SELL",D59>0),R59/D59,0) | Q59: =IF(AND(B59="SELL",D59>0,E59>0),(D59/E59)+G59,0) | R59: =IF(B59="SELL",Q59*F59,0) | S59: =S58+R59
A60: 59 | B60: SELL | C60: 45946 | D60: 40000 | E60: 965 | F60: 965 | G60: -39.27 | I60: 728.78 | J60: 290.252 | K60: =IF(AND(B60="SELL",E60>0,J60<>""),J60/E60,0) | L60: 0.285 | M60: =IF(AND(B60="SELL",L60>0),D60*L60,0) | O60: =IF(AND(B60="SELL",G60<>0),Q60/ABS(G60),0) | P60: =IF(AND(B60="SELL",D60>0),R60/D60,0) | Q60: =IF(AND(B60="SELL",D60>0,E60>0),(D60/E60)+G60,0) | R60: =IF(B60="SELL",Q60*F60,0) | S60: =S59+R60
A61: 60 | B61: SELL | C61: 45946 | D61: 90000 | E61: 965 | F61: 965 | G61: -89.16 | I61: 639.62 | J61: 287.67 | K61: =IF(AND(B61="SELL",E61>0,J61<>""),J61/E61,0) | L61: 0.285 | M61: =IF(AND(B61="SELL",L61>0),D61*L61,0) | O61: =IF(AND(B61="SELL",G61<>0),Q61/ABS(G61),0) | P61: =IF(AND(B61="SELL",D61>0),R61/D61,0) | Q61: =IF(AND(B61="SELL",D61>0,E61>0),(D61/E61)+G61,0) | R61: =IF(B61="SELL",Q61*F61,0) | S61: =S60+R61
A62: 61 | B62: SELL | C62: 45947 | D62: 107000 | E62: 965 | F62: 965 | G62: -105.38 | I62: 534.24 | J62: 294.45 | K62: =IF(AND(B62="SELL",E62>0,J62<>""),J62/E62,0) | L62: 0.29 | M62: =IF(AND(B62="SELL",L62>0),D62*L62,0) | O62: =IF(AND(B62="SELL",G62<>0),Q62/ABS(G62),0) | P62: =IF(AND(B62="SELL",D62>0),R62/D62,0) | Q62: =IF(AND(B62="SELL",D62>0,E62>0),(D62/E62)+G62,0) | R62: =IF(B62="SELL",Q62*F62,0) | S62: =S61+R62
A63: 62 | B63: SELL | C63: 45947 | D63: 65000 | E63: 965 | F63: 965 | G63: -65.75 | I63: 468.49 | J63: 292 | K63: =IF(AND(B63="SELL",E63>0,J63<>""),J63/E63,0) | L63: 0.29 | M63: =IF(AND(B63="SELL",L63>0),D63*L63,0) | O63: =IF(AND(B63="SELL",G63<>0),Q63/ABS(G63),0) | P63: =IF(AND(B63="SELL",D63>0),R63/D63,0) | Q63: =IF(AND(B63="SELL",D63>0,E63>0),(D63/E63)+G63,0) | R63: =IF(B63="SELL",Q63*F63,0) | S63: =S62+R63
A64: 63 | B64: SELL | C64: 45947 | D64: 10000 | E64: 965 | F64: 965 | G64: -10.5 | I64: 457.99 | J64: 276.11 | K64: =IF(AND(B64="SELL",E64>0,J64<>""),J64/E64,0) | L64: 0.29 | M64: =IF(AND(B64="SELL",L64>0),D64*L64,0) | O64: =IF(AND(B64="SELL",G64<>0),Q64/ABS(G64),0) | P64: =IF(AND(B64="SELL",D64>0),R64/D64,0) | Q64: =IF(AND(B64="SELL",D64>0,E64>0),(D64/E64)+G64,0) | R64: =IF(B64="SELL",Q64*F64,0) | S64: =S63+R64
... A68: 67 | B68: SELL | C68: 45952 | D68: 52400 | E68: 965 | F68: 965 | G68: -51.48 | I68: 231.17 | J68: 303.002 | K68: =IF(AND(B68="SELL",E68>0,J68<>""),J68/E68,0) | L68: 0.2975 | M68: =IF(AND(B68="SELL",L68>0),D68*L68,0) | O68: =IF(AND(B68="SELL",G68<>0),Q68/ABS(G68),0) | P68: =IF(AND(B68="SELL",D68>0),R68/D68,0) | Q68: =IF(AND(B68="SELL",D68>0,E68>0),(D68/E68)+G68,0) | R68: =IF(B68="SELL",Q68*F68,0) | S68: =S67+R68
A69: 68 | B69: BUY | C69: 45952 | D69: 1000000 | E69: 953.8 | F69: 953.8 | G69: 1048.3 | I69: 1279.47 | K69: =IF(AND(B69="SELL",E69>0,J69<>""),J69/E69,0) | M69: =IF(AND(B69="SELL",L69>0),D69*L69,0) | O69: =IF(AND(B69="SELL",G69<>0),Q69/ABS(G69),0) | P69: =IF(AND(B69="SELL",D69>0),R69/D69,0) | Q69: =IF(AND(B69="SELL",D69>0,E69>0),(D69/E69)+G69,0) | R69: =IF(B69="SELL",Q69*F69,0) | S69: =S68+R69
A70: 69 | B70: SELL | C70: 45952 | D70: 25000 | E70: 953.8 | F70: 953.8 | G70: -24.91 | I70: 1254.56 | J70: 301.24 | K70: =IF(AND(B70="SELL",E70>0,J70<>""),J70/E70,0) | L70: 0.3 | M70: =IF(AND(B70="SELL",L70>0),D70*L70,0) | O70: =IF(AND(B70="SELL",G70<>0),Q70/ABS(G70),0) | P70: =IF(AND(B70="SELL",D70>0),R70/D70,0) | Q70: =IF(AND(B70="SELL",D70>0,E70>0),(D70/E70)+G70,0) | R70: =IF(B70="SELL",Q70*F70,0) | S70: =S69+R70
A71: 70 | B71: SELL | C71: 45953 | D71: 40000 | E71: 953.8 | F71: 953.8 | G71: -39.8 | I71: 1214.76 | J71: 302.5 | K71: =IF(AND(B71="SELL",E71>0,J71<>""),J71/E71,0) | L71: 0.301 | M71: =IF(AND(B71="SELL",L71>0),D71*L71,0) | O71: =IF(AND(B71="SELL",G71<>0),Q71/ABS(G71),0) | P71: =IF(AND(B71="SELL",D71>0),R71/D71,0) | Q71: =IF(AND(B71="SELL",D71>0,E71>0),(D71/E71)+G71,0) | R71: =IF(B71="SELL",Q71*F71,0) | S71: =S70+R71
A72: 71 | B72: SELL | C72: 45953 | D72: 10000 | E72: 953.8 | F72: 953.8 | G72: -10.01 | I72: 1204.75 | J72: 299.6 | K72: =IF(AND(B72="SELL",E72>0,J72<>""),J72/E72,0) | L72: 0.301 | M72: =IF(AND(B72="SELL",L72>0),D72*L72,0) | N72: cambio para el papa de paula | O72: =IF(AND(B72="SELL",G72<>0),Q72/ABS(G72),0) | P72: =IF(AND(B72="SELL",D72>0),R72/D72,0) | Q72: =IF(AND(B72="SELL",D72>0,E72>0),(D72/E72)+G72,0) | R72: =IF(B72="SELL",Q72*F72,0) | S72: =S71+R72
A73: 72 | B73: SELL | C73: 45953 | D73: 340000 | E73: 953.8 | F73: 953.8 | G73: -326.35 | I73: 878.4 | J73: 18.44 | K73: =IF(AND(B73="SELL",E73>0,J73<>""),J73/E73,0) | L73: 0.0177 | M73: =IF(AND(B73="SELL",L73>0),D73*L73,0) | N73: cambio a MXN | O73: =IF(AND(B73="SELL",G73<>0),Q73/ABS(G73),0) | P73: =IF(AND(B73="SELL",D73>0),R73/D73,0) | Q73: =IF(AND(B73="SELL",D73>0,E73>0),(D73/E73)+G73,0) | R73: =IF(B73="SELL",Q73*F73,0) | S73: =S72+R73
A74: 73 | B74: SELL | C74: 45954 | D74: 15000 | E74: 953.8 | F74: 953.8 | G74: -15.1 | I74: 863.3 | J74: 299 | K74: =IF(AND(B74="SELL",E74>0,J74<>""),J74/E74,0) | L74: 0.301 | M74: =IF(AND(B74="SELL",L74>0),D74*L74,0) | O74: =IF(AND(B74="SELL",G74<>0),Q74/ABS(G74),0) | P74: =IF(AND(B74="SELL",D74>0),R74/D74,0) | Q74: =IF(AND(B74="SELL",D74>0,E74>0),(D74/E74)+G74,0) | R74: =IF(B74="SELL",Q74*F74,0) | S74: =S73+R74
A75: 74 | B75: SELL | C75: 45954 | D75: 20000 | E75: 953.8 | F75: 953.8 | G75: -19.94 | I75: 843.36 | J75: 301.08 | K75: =IF(AND(B75="SELL",E75>0,J75<>""),J75/E75,0) | L75: 0.301 | M75: =IF(AND(B75="SELL",L75>0),D75*L75,0) | O75: =IF(AND(B75="SELL",G75<>0),Q75/ABS(G75),0) | P75: =IF(AND(B75="SELL",D75>0),R75/D75,0) | Q75: =IF(AND(B75="SELL",D75>0,E75>0),(D75/E75)+G75,0) | R75: =IF(B75="SELL",Q75*F75,0) | S75: =S74+R75
A76: 75 | B76: SELL | C76: 45954 | D76: 50000 | E76: 953.8 | F76: 953.8 | G76: -49.74 | I76: 793.62 | J76: 302.53 | K76: =IF(AND(B76="SELL",E76>0,J76<>""),J76/E76,0) | L76: 0.301 | M76: =IF(AND(B76="SELL",L76>0),D76*L76,0) | O76: =IF(AND(B76="SELL",G76<>0),Q76/ABS(G76),0) | P76: =IF(AND(B76="SELL",D76>0),R76/D76,0) | Q76: =IF(AND(B76="SELL",D76>0,E76>0),(D76/E76)+G76,0) | R76: =IF(B76="SELL",Q76*F76,0) | S76: =S75+R76
A77: 76 | B77: SELL | C77: 45955 | D77: 72000 | E77: 953.8 | F77: 953.8 | G77: -71.53 | I77: 722.09 | J77: 301.8 | K77: =IF(AND(B77="SELL",E77>0,J77<>""),J77/E77,0) | L77: 0.2998 | M77: =IF(AND(B77="SELL",L77>0),D77*L77,0) | O77: =IF(AND(B77="SELL",G77<>0),Q77/ABS(G77),0) | P77: =IF(AND(B77="SELL",D77>0),R77/D77,0) | Q77: =IF(AND(B77="SELL",D77>0,E77>0),(D77/E77)+G77,0) | R77: =IF(B77="SELL",Q77*F77,0) | S77: =S76+R77
A78: 77 | B78: SELL | C78: 45956 | D78: 20000 | E78: 953.8 | F78: 953.8 | G78: -20.4 | I78: 701.69 | J78: 297.905 | K78: =IF(AND(B78="SELL",E78>0,J78<>""),J78/E78,0) | L78: 0.304 | M78: =IF(AND(B78="SELL",L78>0),D78*L78,0) | O78: =IF(AND(B78="SELL",G78<>0),Q78/ABS(G78),0) | P78: =IF(AND(B78="SELL",D78>0),R78/D78,0) | Q78: =IF(AND(B78="SELL",D78>0,E78>0),(D78/E78)+G78,0) | R78: =IF(B78="SELL",Q78*F78,0) | S78: =S77+R78
A79: 78 | B79: SELL | C79: 45957 | D79: 14500 | E79: 953.8 | F79: 953.8 | G79: -14.79 | I79: 812.9 | J79: 297.001 | K79: =IF(AND(B79="SELL",E79>0,J79<>""),J79/E79,0) | L79: 0.303 | M79: =IF(AND(B79="SELL",L79>0),D79*L79,0) | O79: =IF(AND(B79="SELL",G79<>0),Q79/ABS(G79),0) | P79: =IF(AND(B79="SELL",D79>0),R79/D79,0) | Q79: =IF(AND(B79="SELL",D79>0,E79>0),(D79/E79)+G79,0) | R79: =IF(B79="SELL",Q79*F79,0) | S79: =S78+R79
A80: 79 | B80: SELL | C80: 45957 | D80: 25000 | E80: 953.8 | F80: 953.8 | G80: -25.3 | I80: 787.6 | J80: 299.36 | K80: =IF(AND(B80="SELL",E80>0,J80<>""),J80/E80,0) | L80: 0.303 | M80: =IF(AND(B80="SELL",L80>0),D80*L80,0) | O80: =IF(AND(B80="SELL",G80<>0),Q80/ABS(G80),0) | P80: =IF(AND(B80="SELL",D80>0),R80/D80,0) | Q80: =IF(AND(B80="SELL",D80>0,E80>0),(D80/E80)+G80,0) | R80: =IF(B80="SELL",Q80*F80,0) | S80: =S79+R80
A81: 80 | B81: SELL | C81: 45957 | D81: 151500 | E81: 953.8 | F81: 953.8 | G81: -149.85 | I81: 637.75 | J81: 1.001 | K81: =IF(AND(B81="SELL",E81>0,J81<>""),J81/E81,0) | L81: 0.000996 | M81: =IF(AND(B81="SELL",L81>0),D81*L81,0) | O81: =IF(AND(B81="SELL",G81<>0),Q81/ABS(G81),0) | P81: =IF(AND(B81="SELL",D81>0),R81/D81,0) | Q81: =IF(AND(B81="SELL",D81>0,E81>0),(D81/E81)+G81,0) | R81: =IF(B81="SELL",Q81*F81,0) | S81: =S80+R81
A82: 81 | B82: SELL | C82: 45958 | D82: 20000 | E82: 953.8 | F82: 953.8 | G82: -20.08 | I82: 617.67 | J82: 306.771 | K82: =IF(AND(B82="SELL",E82>0,J82<>""),J82/E82,0) | L82: 0.308 | M82: =IF(AND(B82="SELL",L82>0),D82*L82,0) | O82: =IF(AND(B82="SELL",G82<>0),Q82/ABS(G82),0) | P82: =IF(AND(B82="SELL",D82>0),R82/D82,0) | Q82: =IF(AND(B82="SELL",D82>0,E82>0),(D82/E82)+G82,0) | R82: =IF(B82="SELL",Q82*F82,0) | S82: =S81+R82
A83: 82 | B83: SELL | C83: 45958 | D83: 200000 | E83: 953.8 | F83: 953.8 | G83: -200.06 | I83: 417.61 | J83: 308.75 | K83: =IF(AND(B83="SELL",E83>0,J83<>""),J83/E83,0) | L83: 0.308 | M83: =IF(AND(B83="SELL",L83>0),D83*L83,0) | O83: =IF(AND(B83="SELL",G83<>0),Q83/ABS(G83),0) | P83: =IF(AND(B83="SELL",D83>0),R83/D83,0) | Q83: =IF(AND(B83="SELL",D83>0,E83>0),(D83/E83)+G83,0) | R83: =IF(B83="SELL",Q83*F83,0) | S83: =S82+R83
A84: 83 | B84: SELL | C84: 45958 | D84: 25000 | E84: 953.8 | F84: 953.8 | G84: -25.07 | I84: 392.54 | J84: 307.022 | K84: =IF(AND(B84="SELL",E84>0,J84<>""),J84/E84,0) | L84: 0.308 | M84: =IF(AND(B84="SELL",L84>0),D84*L84,0) | O84: =IF(AND(B84="SELL",G84<>0),Q84/ABS(G84),0) | P84: =IF(AND(B84="SELL",D84>0),R84/D84,0) | Q84: =IF(AND(B84="SELL",D84>0,E84>0),(D84/E84)+G84,0) | R84: =IF(B84="SELL",Q84*F84,0) | S84: =S83+R84
A85: 84 | B85: SELL | C85: 45958 | D85: 50000 | E85: 953.8 | F85: 953.8 | G85: -49.99 | I85: 342.55 | J85: 308.005 | K85: =IF(AND(B85="SELL",E85>0,J85<>""),J85/E85,0) | L85: 0.308 | M85: =IF(AND(B85="SELL",L85>0),D85*L85,0) | O85: =IF(AND(B85="SELL",G85<>0),Q85/ABS(G85),0) | P85: =IF(AND(B85="SELL",D85>0),R85/D85,0) | Q85: =IF(AND(B85="SELL",D85>0,E85>0),(D85/E85)+G85,0) | R85: =IF(B85="SELL",Q85*F85,0) | S85: =S84+R85
A86: 85 | B86: SELL | C86: 45958 | D86: 25000 | E86: 953.8 | F86: 953.8 | G86: -25.27 | I86: 317.28 | J86: 304.62 | K86: =IF(AND(B86="SELL",E86>0,J86<>""),J86/E86,0) | L86: 0.308 | M86: =IF(AND(B86="SELL",L86>0),D86*L86,0) | O86: =IF(AND(B86="SELL",G86<>0),Q86/ABS(G86),0) | P86: =IF(AND(B86="SELL",D86>0),R86/D86,0) | Q86: =IF(AND(B86="SELL",D86>0,E86>0),(D86/E86)+G86,0) | R86: =IF(B86="SELL",Q86*F86,0) | S86: =S85+R86
A87: 86 | B87: BUY | C87: 45958 | D87: 1340000 | E87: 953.8 | F87: 953.8 | G87: 1416.04 | I87: 1733.32 | K87: =IF(AND(B87="SELL",E87>0,J87<>""),J87/E87,0) | M87: =IF(AND(B87="SELL",L87>0),D87*L87,0) | O87: =IF(AND(B87="SELL",G87<>0),Q87/ABS(G87),0) | P87: =IF(AND(B87="SELL",D87>0),R87/D87,0) | Q87: =IF(AND(B87="SELL",D87>0,E87>0),(D87/E87)+G87,0) | R87: =IF(B87="SELL",Q87*F87,0) | S87: =S86+R87
A88: 87 | B88: SELL | C88: 45958 | D88: 1340000 | E88: 946.39 | F88: 953.8 | G88: -1345.71 | I88: 387.61 | J88: 946.39 | K88: =IF(AND(B88="SELL",E88>0,J88<>""),J88/E88,0) | L88: 1.0037 | M88: =IF(AND(B88="SELL",L88>0),D88*L88,0) | O88: =IF(AND(B88="SELL",G88<>0),Q88/ABS(G88),0) | P88: =IF(AND(B88="SELL",D88>0),R88/D88,0) | Q88: =IF(AND(B88="SELL",D88>0,E88>0),(D88/E88)+G88,0) | R88: =IF(B88="SELL",Q88*F88,0) | S88: =S87+R88
A89: 88 | B89: BUY | C89: 45958 | D89: 1212000 | E89: 946.22 | F89: 946.22 | G89: 1280.88 | I89: 1595.64 | K89: =IF(AND(B89="SELL",E89>0,J89<>""),J89/E89,0) | M89: =IF(AND(B89="SELL",L89>0),D89*L89,0) | N89: Compra de USDT | O89: =IF(AND(B89="SELL",G89<>0),Q89/ABS(G89),0) | P89: =IF(AND(B89="SELL",D89>0),R89/D89,0) | Q89: =IF(AND(B89="SELL",D89>0,E89>0),(D89/E89)+G89,0) | R89: =IF(B89="SELL",Q89*F89,0) | S89: =S88+R89
A90: 89 | B90: SELL | C90: 45958 | D90: 50000 | E90: 946.22 | F90: 946.22 | G90: -49.99 | I90: 1545.65 | J90: 308.305 | K90: =IF(AND(B90="SELL",E90>0,J90<>""),J90/E90,0) | L90: 0.308 | M90: =IF(AND(B90="SELL",L90>0),D90*L90,0) | O90: =IF(AND(B90="SELL",G90<>0),Q90/ABS(G90),0) | P90: =IF(AND(B90="SELL",D90>0),R90/D90,0) | Q90: =IF(AND(B90="SELL",D90>0,E90>0),(D90/E90)+G90,0) | R90: =IF(B90="SELL",Q90*F90,0) | S90: =S89+R90
A91: 90 | B91: SELL | C91: 45958 | D91: 25000 | E91: 946.22 | F91: 946.22 | G91: -25.27 | I91: 1520.38 | J91: 304.62 | K91: =IF(AND(B91="SELL",E91>0,J91<>""),J91/E91,0) | L91: 0.308 | M91: =IF(AND(B91="SELL",L91>0),D91*L91,0) | O91: =IF(AND(B91="SELL",G91<>0),Q91/ABS(G91),0) | P91: =IF(AND(B91="SELL",D91>0),R91/D91,0) | Q91: =IF(AND(B91="SELL",D91>0,E91>0),(D91/E91)+G91,0) | R91: =IF(B91="SELL",Q91*F91,0) | S91: =S90+R91
A92: 91 | B92: SELL | C92: 45959 | D92: 60000 | E92: 946.22 | F92: 946.22 | G92: -60.74 | I92: 1459.64 | J92: 304.2 | K92: =IF(AND(B92="SELL",E92>0,J92<>""),J92/E92,0) | L92: 0.308 | M92: =IF(AND(B92="SELL",L92>0),D92*L92,0) | O92: =IF(AND(B92="SELL",G92<>0),Q92/ABS(G92),0) | P92: =IF(AND(B92="SELL",D92>0),R92/D92,0) | Q92: =IF(AND(B92="SELL",D92>0,E92>0),(D92/E92)+G92,0) | R92: =IF(B92="SELL",Q92*F92,0) | S92: =S91+R92
A93: 92 | B93: SELL | C93: 45959 | D93: 50000 | E93: 946.22 | F93: 946.22 | G93: -50.5 | I93: 1409.14 | J93: 304.915 | K93: =IF(AND(B93="SELL",E93>0,J93<>""),J93/E93,0) | L93: 0.308 | M93: =IF(AND(B93="SELL",L93>0),D93*L93,0) | O93: =IF(AND(B93="SELL",G93<>0),Q93/ABS(G93),0) | P93: =IF(AND(B93="SELL",D93>0),R93/D93,0) | Q93: =IF(AND(B93="SELL",D93>0,E93>0),(D93/E93)+G93,0) | R93: =IF(B93="SELL",Q93*F93,0) | S93: =S92+R93
A94: 93 | B94: SELL | C94: 45960 | D94: 40000 | E94: 946.22 | F94: 946.22 | G94: -40 | I94: 1369.14 | J94: 304 | K94: =IF(AND(B94="SELL",E94>0,J94<>""),J94/E94,0) | L94: 0.304 | M94: =IF(AND(B94="SELL",L94>0),D94*L94,0) | O94: =IF(AND(B94="SELL",G94<>0),Q94/ABS(G94),0) | P94: =IF(AND(B94="SELL",D94>0),R94/D94,0) | Q94: =IF(AND(B94="SELL",D94>0,E94>0),(D94/E94)+G94,0) | R94: =IF(B94="SELL",Q94*F94,0) | S94: =S93+R94
A95: 94 | B95: SELL | C95: 45960 | D95: 20000 | E95: 946.22 | F95: 946.22 | G95: -20.05 | I95: 1349.09 | J95: 303.15 | K95: =IF(AND(B95="SELL",E95>0,J95<>""),J95/E95,0) | L95: 0.304 | M95: =IF(AND(B95="SELL",L95>0),D95*L95,0) | O95: =IF(AND(B95="SELL",G95<>0),Q95/ABS(G95),0) | P95: =IF(AND(B95="SELL",D95>0),R95/D95,0) | Q95: =IF(AND(B95="SELL",D95>0,E95>0),(D95/E95)+G95,0) | R95: =IF(B95="SELL",Q95*F95,0) | S95: =S94+R95
A96: 95 | B96: SELL | C96: 45960 | D96: 100000 | E96: 946.22 | F96: 946.22 | G96: -100.34 | I96: 1248.75 | J96: 302.955 | K96: =IF(AND(B96="SELL",E96>0,J96<>""),J96/E96,0) | L96: 0.304 | M96: =IF(AND(B96="SELL",L96>0),D96*L96,0) | O96: =IF(AND(B96="SELL",G96<>0),Q96/ABS(G96),0) | P96: =IF(AND(B96="SELL",D96>0),R96/D96,0) | Q96: =IF(AND(B96="SELL",D96>0,E96>0),(D96/E96)+G96,0) | R96: =IF(B96="SELL",Q96*F96,0) | S96: =S95+R96
A97: 96 | B97: SELL | C97: 45960 | D97: 100000 | E97: 946.22 | F97: 946.22 | G97: -100.34 | I97: 1148.41 | J97: 302.955 | K97: =IF(AND(B97="SELL",E97>0,J97<>""),J97/E97,0) | L97: 0.304 | M97: =IF(AND(B97="SELL",L97>0),D97*L97,0) | O97: =IF(AND(B97="SELL",G97<>0),Q97/ABS(G97),0) | P97: =IF(AND(B97="SELL",D97>0),R97/D97,0) | Q97: =IF(AND(B97="SELL",D97>0,E97>0),(D97/E97)+G97,0) | R97: =IF(B97="SELL",Q97*F97,0) | S97: =S96+R97
A98: 97 | B98: SELL | C98: 45960 | D98: 15000 | E98: 946.22 | F98: 946.22 | G98: -15.11 | I98: 1133.3 | J98: 301.7 | K98: =IF(AND(B98="SELL",E98>0,J98<>""),J98/E98,0) | L98: 0.304 | M98: =IF(AND(B98="SELL",L98>0),D98*L98,0) | O98: =IF(AND(B98="SELL",G98<>0),Q98/ABS(G98),0) | P98: =IF(AND(B98="SELL",D98>0),R98/D98,0) | Q98: =IF(AND(B98="SELL",D98>0,E98>0),(D98/E98)+G98,0) | R98: =IF(B98="SELL",Q98*F98,0) | S98: =S97+R98
A99: 98 | B99: SELL | C99: 45960 | D99: 40000 | E99: 946.22 | F99: 946.22 | G99: -40.2 | I99: 1093.1 | J99: 302.45 | K99: =IF(AND(B99="SELL",E99>0,J99<>""),J99/E99,0) | L99: 0.304 | M99: =IF(AND(B99="SELL",L99>0),D99*L99,0) | O99: =IF(AND(B99="SELL",G99<>0),Q99/ABS(G99),0) | P99: =IF(AND(B99="SELL",D99>0),R99/D99,0) | Q99: =IF(AND(B99="SELL",D99>0,E99>0),(D99/E99)+G99,0) | R99: =IF(B99="SELL",Q99*F99,0) | S99: =S98+R99
A100: 99 | B100: SELL | C100: 45960 | D100: 30000 | E100: 946.22 | F100: 946.22 | G100: -30.18 | I100: 1062.92 | J100: 302.1 | K100: =IF(AND(B100="SELL",E100>0,J100<>""),J100/E100,0) | L100: 0.304 | M100: =IF(AND(B100="SELL",L100>0),D100*L100,0) | O100: =IF(AND(B100="SELL",G100<>0),Q100/ABS(G100),0) | P100: =IF(AND(B100="SELL",D100>0),R100/D100,0) | Q100: =IF(AND(B100="SELL",D100>0,E100>0),(D100/E100)+G100,0) | R100: =IF(B100="SELL",Q100*F100,0) | S100: =S99+R100
A101: 100 | B101: SELL | C101: 45960 | D101: 24000 | E101: 946.22 | F101: 946.22 | G101: -24.26 | I101: 1038.66 | J101: 300.87 | K101: =IF(AND(B101="SELL",E101>0,J101<>""),J101/E101,0) | L101: 0.304 | M101: =IF(AND(B101="SELL",L101>0),D101*L101,0) | O101: =IF(AND(B101="SELL",G101<>0),Q101/ABS(G101),0) | P101: =IF(AND(B101="SELL",D101>0),R101/D101,0) | Q101: =IF(AND(B101="SELL",D101>0,E101>0),(D101/E101)+G101,0) | R101: =IF(B101="SELL",Q101*F101,0) | S101: =S100+R101
... A110: 109 | B110: SELL | C110: 45961 | D110: 50000 | E110: 946.22 | F110: 946.22 | G110: -50.66 | I110: 599.8 | J110: 298.01 | K110: =IF(AND(B110="SELL",E110>0,J110<>""),J110/E110,0) | L110: 0.302 | M110: =IF(AND(B110="SELL",L110>0),D110*L110,0) | O110: =IF(AND(B110="SELL",G110<>0),Q110/ABS(G110),0) | P110: =IF(AND(B110="SELL",D110>0),R110/D110,0) | Q110: =IF(AND(B110="SELL",D110>0,E110>0),(D110/E110)+G110,0) | R110: =IF(B110="SELL",Q110*F110,0) | S110: =S109+R110
A112: TOTALES — Octubre 2025 | D112: =SUMIF(B2:B110,"SELL",D2:D110) | G112: =COUNTIF(B2:B110,"SELL") | I112: =I110 | Q112: =SUM(Q2:Q110) | R112: =SUMIF(B2:B110,"SELL",R2:R110) | S112: =S110

Sheet Noviembre 2025
A1: N° | B1: Tipo | C1: Fecha | D1: Monto CLP | E1: USDT/CLP Compra | F1: USDT/CLP Venta | G1: USDT Mov | H1: Tax Binance | I1: Capital USDT | J1: Tasa Destino | K1: Tasa Real | L1: Tasa IREMI | M1: Valor Destino | N1: Comentario | O1: % G USDT | P1: % G CLP | Q1: Ganancia USDT | R1: Ganancia CLP | S1: Acumulado SELL
A2: 1 | B2: SELL | C2: 45961 | D2: 50000 | E2: 946.22 | F2: 946.22 | G2: -50.66 | I2: 599.8 | J2: 298.01 | K2: =IF(AND(B2="SELL",E2>0,J2<>""),J2/E2,0) | L2: 0.302 | M2: =IF(AND(B2="SELL",L2>0),D2*L2,0) | O2: =IF(AND(B2="SELL",G2<>0),Q2/ABS(G2),0) | P2: =IF(AND(B2="SELL",D2>0),R2/D2,0) | Q2: =IF(AND(B2="SELL",D2>0,E2>0),(D2/E2)+G2,0) | R2: =IF(B2="SELL",Q2*F2,0) | S2: ='Octubre 2025'!S110+R2
A3: 2 | B3: SELL | C3: 45962 | D3: 137000 | E3: 946.22 | F3: 946.22 | G3: -137.06 | I3: 462.74 | J3: 296.85 | K3: =IF(AND(B3="SELL",E3>0,J3<>""),J3/E3,0) | L3: 0.297 | M3: =IF(AND(B3="SELL",L3>0),D3*L3,0) | N3: Cambio uvida y francisco | O3: =IF(AND(B3="SELL",G3<>0),Q3/ABS(G3),0) | P3: =IF(AND(B3="SELL",D3>0),R3/D3,0) | Q3: =IF(AND(B3="SELL",D3>0,E3>0),(D3/E3)+G3,0) | R3: =IF(B3="SELL",Q3*F3,0) | S3: =S2+R3
A4: 3 | B4: SELL | C4: 45962 | D4: 40000 | E4: 946.22 | F4: 946.22 | G4: -39.77 | I4: 422.97 | J4: 298.66 | K4: =IF(AND(B4="SELL",E4>0,J4<>""),J4/E4,0) | L4: 0.297 | M4: =IF(AND(B4="SELL",L4>0),D4*L4,0) | N4: cambio angel | O4: =IF(AND(B4="SELL",G4<>0),Q4/ABS(G4),0) | P4: =IF(AND(B4="SELL",D4>0),R4/D4,0) | Q4: =IF(AND(B4="SELL",D4>0,E4>0),(D4/E4)+G4,0) | R4: =IF(B4="SELL",Q4*F4,0) | S4: =S3+R4
A5: 4 | B5: SELL | C5: 45962 | D5: 30000 | E5: 946.22 | F5: 946.22 | G5: -30.01 | I5: 392.96 | J5: 296.85 | K5: =IF(AND(B5="SELL",E5>0,J5<>""),J5/E5,0) | L5: 0.297 | M5: =IF(AND(B5="SELL",L5>0),D5*L5,0) | O5: =IF(AND(B5="SELL",G5<>0),Q5/ABS(G5),0) | P5: =IF(AND(B5="SELL",D5>0),R5/D5,0) | Q5: =IF(AND(B5="SELL",D5>0,E5>0),(D5/E5)+G5,0) | R5: =IF(B5="SELL",Q5*F5,0) | S5: =S4+R5
A6: 5 | B6: SELL | C6: 45962 | D6: 15000 | E6: 946.22 | F6: 946.22 | G6: -15.11 | I6: 377.85 | J6: 294.7 | K6: =IF(AND(B6="SELL",E6>0,J6<>""),J6/E6,0) | L6: 0.297 | M6: =IF(AND(B6="SELL",L6>0),D6*L6,0) | O6: =IF(AND(B6="SELL",G6<>0),Q6/ABS(G6),0) | P6: =IF(AND(B6="SELL",D6>0),R6/D6,0) | Q6: =IF(AND(B6="SELL",D6>0,E6>0),(D6/E6)+G6,0) | R6: =IF(B6="SELL",Q6*F6,0) | S6: =S5+R6
A7: 6 | B7: SELL | C7: 45963 | D7: 30000 | E7: 946.22 | F7: 946.22 | G7: -30.4 | I7: 347.45 | J7: 296.023 | K7: =IF(AND(B7="SELL",E7>0,J7<>""),J7/E7,0) | L7: 0.3 | M7: =IF(AND(B7="SELL",L7>0),D7*L7,0) | O7: =IF(AND(B7="SELL",G7<>0),Q7/ABS(G7),0) | P7: =IF(AND(B7="SELL",D7>0),R7/D7,0) | Q7: =IF(AND(B7="SELL",D7>0,E7>0),(D7/E7)+G7,0) | R7: =IF(B7="SELL",Q7*F7,0) | S7: =S6+R7
A8: 7 | B8: SELL | C8: 45964 | D8: 20000 | E8: 946.22 | F8: 946.22 | G8: -20.06 | I8: 327.39 | J8: 297.5 | K8: =IF(AND(B8="SELL",E8>0,J8<>""),J8/E8,0) | L8: 0.2985 | M8: =IF(AND(B8="SELL",L8>0),D8*L8,0) | O8: =IF(AND(B8="SELL",G8<>0),Q8/ABS(G8),0) | P8: =IF(AND(B8="SELL",D8>0),R8/D8,0) | Q8: =IF(AND(B8="SELL",D8>0,E8>0),(D8/E8)+G8,0) | R8: =IF(B8="SELL",Q8*F8,0) | S8: =S7+R8
A9: 8 | B9: SELL | C9: 45965 | D9: 140000 | E9: 946.22 | F9: 946.22 | G9: -139.33 | I9: 188.06 | J9: 307.46 | K9: =IF(AND(B9="SELL",E9>0,J9<>""),J9/E9,0) | L9: 0.306 | M9: =IF(AND(B9="SELL",L9>0),D9*L9,0) | O9: =IF(AND(B9="SELL",G9<>0),Q9/ABS(G9),0) | P9: =IF(AND(B9="SELL",D9>0),R9/D9,0) | Q9: =IF(AND(B9="SELL",D9>0,E9>0),(D9/E9)+G9,0) | R9: =IF(B9="SELL",Q9*F9,0) | S9: =S8+R9
A10: 9 | B10: SELL | C10: 45965 | D10: 50000 | E10: 946.22 | F10: 946.22 | G10: -51.03 | I10: 137.03 | J10: 299.5 | K10: =IF(AND(B10="SELL",E10>0,J10<>""),J10/E10,0) | L10: 0.306 | M10: =IF(AND(B10="SELL",L10>0),D10*L10,0) | O10: =IF(AND(B10="SELL",G10<>0),Q10/ABS(G10),0) | P10: =IF(AND(B10="SELL",D10>0),R10/D10,0) | Q10: =IF(AND(B10="SELL",D10>0,E10>0),(D10/E10)+G10,0) | R10: =IF(B10="SELL",Q10*F10,0) | S10: =S9+R10
A11: 10 | B11: SELL | C11: 45965 | D11: 15000 | E11: 946.22 | F11: 946.22 | G11: -15.14 | I11: 121.89 | J11: 303.011 | K11: =IF(AND(B11="SELL",E11>0,J11<>""),J11/E11,0) | L11: 0.306 | M11: =IF(AND(B11="SELL",L11>0),D11*L11,0) | O11: =IF(AND(B11="SELL",G11<>0),Q11/ABS(G11),0) | P11: =IF(AND(B11="SELL",D11>0),R11/D11,0) | Q11: =IF(AND(B11="SELL",D11>0,E11>0),(D11/E11)+G11,0) | R11: =IF(B11="SELL",Q11*F11,0) | S11: =S10+R11
A12: 11 | B12: SELL | C12: 45965 | D12: 40000 | E12: 946.22 | F12: 946.22 | G12: -40.15 | I12: 81.74 | J12: 304.81 | K12: =IF(AND(B12="SELL",E12>0,J12<>""),J12/E12,0) | L12: 0.306 | M12: =IF(AND(B12="SELL",L12>0),D12*L12,0) | O12: =IF(AND(B12="SELL",G12<>0),Q12/ABS(G12),0) | P12: =IF(AND(B12="SELL",D12>0),R12/D12,0) | Q12: =IF(AND(B12="SELL",D12>0,E12>0),(D12/E12)+G12,0) | R12: =IF(B12="SELL",Q12*F12,0) | S12: =S11+R12
A13: 12 | B13: SELL | C13: 45965 | D13: 50000 | E13: 946.22 | F13: 946.22 | G13: -49.62 | I13: 32.12 | J13: 3.375 | K13: =IF(AND(B13="SELL",E13>0,J13<>""),J13/E13,0) | L13: 0.00336 | M13: =IF(AND(B13="SELL",L13>0),D13*L13,0) | O13: =IF(AND(B13="SELL",G13<>0),Q13/ABS(G13),0) | P13: =IF(AND(B13="SELL",D13>0),R13/D13,0) | Q13: =IF(AND(B13="SELL",D13>0,E13>0),(D13/E13)+G13,0) | R13: =IF(B13="SELL",Q13*F13,0) | S13: =S12+R13
A14: 13 | B14: SELL | C14: 45965 | D14: 30000 | E14: 946.22 | F14: 946.22 | G14: -30 | I14: 2.12 | J14: 305.902 | K14: =IF(AND(B14="SELL",E14>0,J14<>""),J14/E14,0) | L14: 0.306 | M14: =IF(AND(B14="SELL",L14>0),D14*L14,0) | O14: =IF(AND(B14="SELL",G14<>0),Q14/ABS(G14),0) | P14: =IF(AND(B14="SELL",D14>0),R14/D14,0) | Q14: =IF(AND(B14="SELL",D14>0,E14>0),(D14/E14)+G14,0) | R14: =IF(B14="SELL",Q14*F14,0) | S14: =S13+R14
A15: 14 | B15: SELL | C15: 45965 | D15: 30000 | E15: 946.22 | F15: 946.22 | G15: -29.78 | I15: -27.66 | J15: 308.15 | K15: =IF(AND(B15="SELL",E15>0,J15<>""),J15/E15,0) | L15: 0.306 | M15: =IF(AND(B15="SELL",L15>0),D15*L15,0) | O15: =IF(AND(B15="SELL",G15<>0),Q15/ABS(G15),0) | P15: =IF(AND(B15="SELL",D15>0),R15/D15,0) | Q15: =IF(AND(B15="SELL",D15>0,E15>0),(D15/E15)+G15,0) | R15: =IF(B15="SELL",Q15*F15,0) | S15: =S14+R15
A16: 15 | B16: SELL | C16: 45965 | D16: 30000 | E16: 946.22 | F16: 946.22 | G16: -29.8 | I16: -57.46 | J16: 308.05 | K16: =IF(AND(B16="SELL",E16>0,J16<>""),J16/E16,0) | L16: 0.306 | M16: =IF(AND(B16="SELL",L16>0),D16*L16,0) | O16: =IF(AND(B16="SELL",G16<>0),Q16/ABS(G16),0) | P16: =IF(AND(B16="SELL",D16>0),R16/D16,0) | Q16: =IF(AND(B16="SELL",D16>0,E16>0),(D16/E16)+G16,0) | R16: =IF(B16="SELL",Q16*F16,0) | S16: =S15+R16
... A22: 21 | B22: SELL | C22: 45966 | D22: 60000 | E22: 950.43 | F22: 950.43 | G22: -58.87 | I22: -339.18 | J22: 313.9 | K22: =IF(AND(B22="SELL",E22>0,J22<>""),J22/E22,0) | L22: 0.308 | M22: =IF(AND(B22="SELL",L22>0),D22*L22,0) | O22: =IF(AND(B22="SELL",G22<>0),Q22/ABS(G22),0) | P22: =IF(AND(B22="SELL",D22>0),R22/D22,0) | Q22: =IF(AND(B22="SELL",D22>0,E22>0),(D22/E22)+G22,0) | R22: =IF(B22="SELL",Q22*F22,0) | S22: =S21+R22
A23: 22 | B23: BUY | C23: 45966 | D23: 1527300 | E23: 950.43 | F23: 950.43 | G23: 1606.95 | I23: 1267.77 | K23: =IF(AND(B23="SELL",E23>0,J23<>""),J23/E23,0) | M23: =IF(AND(B23="SELL",L23>0),D23*L23,0) | O23: =IF(AND(B23="SELL",G23<>0),Q23/ABS(G23),0) | P23: =IF(AND(B23="SELL",D23>0),R23/D23,0) | Q23: =IF(AND(B23="SELL",D23>0,E23>0),(D23/E23)+G23,0) | R23: =IF(B23="SELL",Q23*F23,0) | S23: =S22+R23
A24: 23 | B24: SELL | C24: 45967 | D24: 20000 | E24: 950.43 | F24: 950.43 | G24: -19.94 | I24: 1247.83 | J24: 312.851 | K24: =IF(AND(B24="SELL",E24>0,J24<>""),J24/E24,0) | L24: 0.312 | M24: =IF(AND(B24="SELL",L24>0),D24*L24,0) | O24: =IF(AND(B24="SELL",G24<>0),Q24/ABS(G24),0) | P24: =IF(AND(B24="SELL",D24>0),R24/D24,0) | Q24: =IF(AND(B24="SELL",D24>0,E24>0),(D24/E24)+G24,0) | R24: =IF(B24="SELL",Q24*F24,0) | S24: =S23+R24
A25: 24 | B25: SELL | C25: 45968 | D25: 15000 | E25: 950.43 | F25: 950.43 | G25: -15.07 | I25: 1232.76 | J25: 310.51 | K25: =IF(AND(B25="SELL",E25>0,J25<>""),J25/E25,0) | L25: 0.312 | M25: =IF(AND(B25="SELL",L25>0),D25*L25,0) | O25: =IF(AND(B25="SELL",G25<>0),Q25/ABS(G25),0) | P25: =IF(AND(B25="SELL",D25>0),R25/D25,0) | Q25: =IF(AND(B25="SELL",D25>0,E25>0),(D25/E25)+G25,0) | R25: =IF(B25="SELL",Q25*F25,0) | S25: =S24+R25
A26: 25 | B26: SELL | C26: 45968 | D26: 10000 | E26: 950.43 | F26: 950.43 | G26: -10.09 | I26: 1222.67 | J26: 309.001 | K26: =IF(AND(B26="SELL",E26>0,J26<>""),J26/E26,0) | L26: 0.312 | M26: =IF(AND(B26="SELL",L26>0),D26*L26,0) | O26: =IF(AND(B26="SELL",G26<>0),Q26/ABS(G26),0) | P26: =IF(AND(B26="SELL",D26>0),R26/D26,0) | Q26: =IF(AND(B26="SELL",D26>0,E26>0),(D26/E26)+G26,0) | R26: =IF(B26="SELL",Q26*F26,0) | S26: =S25+R26
A27: 26 | B27: SELL | C27: 45968 | D27: 50000 | E27: 950.43 | F27: 950.43 | G27: -49.84 | I27: 1172.83 | J27: 313 | K27: =IF(AND(B27="SELL",E27>0,J27<>""),J27/E27,0) | L27: 0.312 | M27: =IF(AND(B27="SELL",L27>0),D27*L27,0) | O27: =IF(AND(B27="SELL",G27<>0),Q27/ABS(G27),0) | P27: =IF(AND(B27="SELL",D27>0),R27/D27,0) | Q27: =IF(AND(B27="SELL",D27>0,E27>0),(D27/E27)+G27,0) | R27: =IF(B27="SELL",Q27*F27,0) | S27: =S26+R27
A28: 27 | B28: SELL | C28: 45968 | D28: 141800 | E28: 950.43 | F28: 950.43 | G28: -141.18 | I28: 1031.65 | J28: 313.51 | K28: =IF(AND(B28="SELL",E28>0,J28<>""),J28/E28,0) | L28: 0.312 | M28: =IF(AND(B28="SELL",L28>0),D28*L28,0) | O28: =IF(AND(B28="SELL",G28<>0),Q28/ABS(G28),0) | P28: =IF(AND(B28="SELL",D28>0),R28/D28,0) | Q28: =IF(AND(B28="SELL",D28>0,E28>0),(D28/E28)+G28,0) | R28: =IF(B28="SELL",Q28*F28,0) | S28: =S27+R28
A29: 28 | B29: SELL | C29: 45968 | D29: 50000 | E29: 950.43 | F29: 950.43 | G29: -49.79 | I29: 981.86 | J29: 313.3 | K29: =IF(AND(B29="SELL",E29>0,J29<>""),J29/E29,0) | L29: 0.312 | M29: =IF(AND(B29="SELL",L29>0),D29*L29,0) | O29: =IF(AND(B29="SELL",G29<>0),Q29/ABS(G29),0) | P29: =IF(AND(B29="SELL",D29>0),R29/D29,0) | Q29: =IF(AND(B29="SELL",D29>0,E29>0),(D29/E29)+G29,0) | R29: =IF(B29="SELL",Q29*F29,0) | S29: =S28+R29
A30: 29 | B30: SELL | C30: 45968 | D30: 40000 | E30: 950.43 | F30: 950.43 | G30: -39.73 | I30: 942.13 | J30: 314.1 | K30: =IF(AND(B30="SELL",E30>0,J30<>""),J30/E30,0) | L30: 0.312 | M30: =IF(AND(B30="SELL",L30>0),D30*L30,0) | O30: =IF(AND(B30="SELL",G30<>0),Q30/ABS(G30),0) | P30: =IF(AND(B30="SELL",D30>0),R30/D30,0) | Q30: =IF(AND(B30="SELL",D30>0,E30>0),(D30/E30)+G30,0) | R30: =IF(B30="SELL",Q30*F30,0) | S30: =S29+R30
A31: 30 | B31: SELL | C31: 45968 | D31: 15000 | E31: 950.43 | F31: 950.43 | G31: -15.04 | I31: 927.09 | J31: 311 | K31: =IF(AND(B31="SELL",E31>0,J31<>""),J31/E31,0) | L31: 0.312 | M31: =IF(AND(B31="SELL",L31>0),D31*L31,0) | O31: =IF(AND(B31="SELL",G31<>0),Q31/ABS(G31),0) | P31: =IF(AND(B31="SELL",D31>0),R31/D31,0) | Q31: =IF(AND(B31="SELL",D31>0,E31>0),(D31/E31)+G31,0) | R31: =IF(B31="SELL",Q31*F31,0) | S31: =S30+R31
A32: 31 | B32: SELL | C32: 45968 | D32: 20000 | E32: 950.43 | F32: 950.43 | G32: -19.97 | I32: 907.12 | J32: 312.325 | K32: =IF(AND(B32="SELL",E32>0,J32<>""),J32/E32,0) | L32: 0.312 | M32: =IF(AND(B32="SELL",L32>0),D32*L32,0) | O32: =IF(AND(B32="SELL",G32<>0),Q32/ABS(G32),0) | P32: =IF(AND(B32="SELL",D32>0),R32/D32,0) | Q32: =IF(AND(B32="SELL",D32>0,E32>0),(D32/E32)+G32,0) | R32: =IF(B32="SELL",Q32*F32,0) | S32: =S31+R32
A33: 32 | B33: SELL | C33: 45968 | D33: 10000 | E33: 950.43 | F33: 950.43 | G33: -9.99 | I33: 897.13 | J33: 312.002 | K33: =IF(AND(B33="SELL",E33>0,J33<>""),J33/E33,0) | L33: 0.312 | M33: =IF(AND(B33="SELL",L33>0),D33*L33,0) | O33: =IF(AND(B33="SELL",G33<>0),Q33/ABS(G33),0) | P33: =IF(AND(B33="SELL",D33>0),R33/D33,0) | Q33: =IF(AND(B33="SELL",D33>0,E33>0),(D33/E33)+G33,0) | R33: =IF(B33="SELL",Q33*F33,0) | S33: =S32+R33
A34: 33 | B34: SELL | C34: 45969 | D34: 10000 | E34: 950.43 | F34: 950.43 | G34: -10.18 | I34: 886.95 | J34: 307.301 | K34: =IF(AND(B34="SELL",E34>0,J34<>""),J34/E34,0) | L34: 0.313 | M34: =IF(AND(B34="SELL",L34>0),D34*L34,0) | O34: =IF(AND(B34="SELL",G34<>0),Q34/ABS(G34),0) | P34: =IF(AND(B34="SELL",D34>0),R34/D34,0) | Q34: =IF(AND(B34="SELL",D34>0,E34>0),(D34/E34)+G34,0) | R34: =IF(B34="SELL",Q34*F34,0) | S34: =S33+R34
A35: 34 | B35: SELL | C35: 45969 | D35: 43000 | E35: 950.43 | F35: 950.43 | G35: -43.26 | I35: 843.69 | J35: 311.102 | K35: =IF(AND(B35="SELL",E35>0,J35<>""),J35/E35,0) | L35: 0.313 | M35: =IF(AND(B35="SELL",L35>0),D35*L35,0) | O35: =IF(AND(B35="SELL",G35<>0),Q35/ABS(G35),0) | P35: =IF(AND(B35="SELL",D35>0),R35/D35,0) | Q35: =IF(AND(B35="SELL",D35>0,E35>0),(D35/E35)+G35,0) | R35: =IF(B35="SELL",Q35*F35,0) | S35: =S34+R35
... A68: 67 | B68: SELL | C68: 45976 | D68: 20000 | E68: 934.48 | F68: 934.48 | G68: -20.48 | I68: 39.94 | J68: 319.26 | K68: =IF(AND(B68="SELL",E68>0,J68<>""),J68/E68,0) | L68: 0.327 | M68: =IF(AND(B68="SELL",L68>0),D68*L68,0) | O68: =IF(AND(B68="SELL",G68<>0),Q68/ABS(G68),0) | P68: =IF(AND(B68="SELL",D68>0),R68/D68,0) | Q68: =IF(AND(B68="SELL",D68>0,E68>0),(D68/E68)+G68,0) | R68: =IF(B68="SELL",Q68*F68,0) | S68: =S67+R68
A69: 68 | B69: BUY | C69: 45976 | D69: 1500000 | E69: 934.48 | F69: 934.48 | G69: 1605.17 | I69: 1645.11 | K69: =IF(AND(B69="SELL",E69>0,J69<>""),J69/E69,0) | L69: 0 | M69: =IF(AND(B69="SELL",L69>0),D69*L69,0) | O69: =IF(AND(B69="SELL",G69<>0),Q69/ABS(G69),0) | P69: =IF(AND(B69="SELL",D69>0),R69/D69,0) | Q69: =IF(AND(B69="SELL",D69>0,E69>0),(D69/E69)+G69,0) | R69: =IF(B69="SELL",Q69*F69,0) | S69: =S68+R69
A70: 69 | B70: SELL | C70: 45977 | D70: 10000 | E70: 934.48 | F70: 934.48 | G70: -10.2 | I70: 1634.91 | J70: 322.521 | K70: =IF(AND(B70="SELL",E70>0,J70<>""),J70/E70,0) | L70: 0.329 | M70: =IF(AND(B70="SELL",L70>0),D70*L70,0) | O70: =IF(AND(B70="SELL",G70<>0),Q70/ABS(G70),0) | P70: =IF(AND(B70="SELL",D70>0),R70/D70,0) | Q70: =IF(AND(B70="SELL",D70>0,E70>0),(D70/E70)+G70,0) | R70: =IF(B70="SELL",Q70*F70,0) | S70: =S69+R70
A71: 70 | B71: SELL | C71: 45978 | D71: 45000 | E71: 934.48 | F71: 934.48 | G71: -45.27 | I71: 1589.64 | J71: 331.001 | K71: =IF(AND(B71="SELL",E71>0,J71<>""),J71/E71,0) | L71: 0.333 | M71: =IF(AND(B71="SELL",L71>0),D71*L71,0) | O71: =IF(AND(B71="SELL",G71<>0),Q71/ABS(G71),0) | P71: =IF(AND(B71="SELL",D71>0),R71/D71,0) | Q71: =IF(AND(B71="SELL",D71>0,E71>0),(D71/E71)+G71,0) | R71: =IF(B71="SELL",Q71*F71,0) | S71: =S70+R71
A72: 71 | B72: SELL | C72: 45978 | D72: 20000 | E72: 934.48 | F72: 934.48 | G72: -20.64 | I72: 1569 | J72: 322.53 | K72: =IF(AND(B72="SELL",E72>0,J72<>""),J72/E72,0) | L72: 0.333 | M72: =IF(AND(B72="SELL",L72>0),D72*L72,0) | O72: =IF(AND(B72="SELL",G72<>0),Q72/ABS(G72),0) | P72: =IF(AND(B72="SELL",D72>0),R72/D72,0) | Q72: =IF(AND(B72="SELL",D72>0,E72>0),(D72/E72)+G72,0) | R72: =IF(B72="SELL",Q72*F72,0) | S72: =S71+R72
A73: 72 | B73: SELL | C73: 45978 | D73: 10000 | E73: 934.48 | F73: 934.48 | G73: -10.3 | I73: 1558.7 | J73: 323.001 | K73: =IF(AND(B73="SELL",E73>0,J73<>""),J73/E73,0) | L73: 0.333 | M73: =IF(AND(B73="SELL",L73>0),D73*L73,0) | O73: =IF(AND(B73="SELL",G73<>0),Q73/ABS(G73),0) | P73: =IF(AND(B73="SELL",D73>0),R73/D73,0) | Q73: =IF(AND(B73="SELL",D73>0,E73>0),(D73/E73)+G73,0) | R73: =IF(B73="SELL",Q73*F73,0) | S73: =S72+R73
A74: 73 | B74: SELL | C74: 45978 | D74: 20000 | E74: 934.48 | F74: 934.48 | G74: -20.16 | I74: 1538.54 | J74: 330.2 | K74: =IF(AND(B74="SELL",E74>0,J74<>""),J74/E74,0) | L74: 0.333 | M74: =IF(AND(B74="SELL",L74>0),D74*L74,0) | O74: =IF(AND(B74="SELL",G74<>0),Q74/ABS(G74),0) | P74: =IF(AND(B74="SELL",D74>0),R74/D74,0) | Q74: =IF(AND(B74="SELL",D74>0,E74>0),(D74/E74)+G74,0) | R74: =IF(B74="SELL",Q74*F74,0) | S74: =S73+R74
A75: 74 | B75: SELL | C75: 45978 | D75: 20000 | E75: 934.48 | F75: 934.48 | G75: -20.12 | I75: 1518.42 | J75: 331 | K75: =IF(AND(B75="SELL",E75>0,J75<>""),J75/E75,0) | L75: 0.333 | M75: =IF(AND(B75="SELL",L75>0),D75*L75,0) | O75: =IF(AND(B75="SELL",G75<>0),Q75/ABS(G75),0) | P75: =IF(AND(B75="SELL",D75>0),R75/D75,0) | Q75: =IF(AND(B75="SELL",D75>0,E75>0),(D75/E75)+G75,0) | R75: =IF(B75="SELL",Q75*F75,0) | S75: =S74+R75
A76: 75 | B76: SELL | C76: 45980 | D76: 40000 | E76: 934.48 | F76: 934.48 | G76: -41.01 | I76: 1477.41 | J76: 336.45 | K76: =IF(AND(B76="SELL",E76>0,J76<>""),J76/E76,0) | L76: 0.345 | M76: =IF(AND(B76="SELL",L76>0),D76*L76,0) | O76: =IF(AND(B76="SELL",G76<>0),Q76/ABS(G76),0) | P76: =IF(AND(B76="SELL",D76>0),R76/D76,0) | Q76: =IF(AND(B76="SELL",D76>0,E76>0),(D76/E76)+G76,0) | R76: =IF(B76="SELL",Q76*F76,0) | S76: =S75+R76
A77: 76 | B77: SELL | C77: 45980 | D77: 60000 | E77: 934.48 | F77: 934.48 | G77: -61 | I77: 1416.41 | J77: 339.3 | K77: =IF(AND(B77="SELL",E77>0,J77<>""),J77/E77,0) | L77: 0.345 | M77: =IF(AND(B77="SELL",L77>0),D77*L77,0) | O77: =IF(AND(B77="SELL",G77<>0),Q77/ABS(G77),0) | P77: =IF(AND(B77="SELL",D77>0),R77/D77,0) | Q77: =IF(AND(B77="SELL",D77>0,E77>0),(D77/E77)+G77,0) | R77: =IF(B77="SELL",Q77*F77,0) | S77: =S76+R77
A78: 77 | B78: SELL | C78: 45980 | D78: 262000 | E78: 934.48 | F78: 934.48 | G78: -267.15 | I78: 1149.26 | J78: 339.28 | K78: =IF(AND(B78="SELL",E78>0,J78<>""),J78/E78,0) | L78: 0.3459545 | M78: =IF(AND(B78="SELL",L78>0),D78*L78,0) | O78: =IF(AND(B78="SELL",G78<>0),Q78/ABS(G78),0) | P78: =IF(AND(B78="SELL",D78>0),R78/D78,0) | Q78: =IF(AND(B78="SELL",D78>0,E78>0),(D78/E78)+G78,0) | R78: =IF(B78="SELL",Q78*F78,0) | S78: =S77+R78
A79: 78 | B79: SELL | C79: 45980 | D79: 55000 | E79: 934.48 | F79: 934.48 | G79: -56.05 | I79: 1093.21 | J79: 338.5 | K79: =IF(AND(B79="SELL",E79>0,J79<>""),J79/E79,0) | L79: 0.345 | M79: =IF(AND(B79="SELL",L79>0),D79*L79,0) | O79: =IF(AND(B79="SELL",G79<>0),Q79/ABS(G79),0) | P79: =IF(AND(B79="SELL",D79>0),R79/D79,0) | Q79: =IF(AND(B79="SELL",D79>0,E79>0),(D79/E79)+G79,0) | R79: =IF(B79="SELL",Q79*F79,0) | S79: =S78+R79
A80: 79 | B80: SELL | C80: 45981 | D80: 50000 | E80: 934.48 | F80: 934.48 | G80: -51.03 | I80: 1042.18 | J80: 341.9 | K80: =IF(AND(B80="SELL",E80>0,J80<>""),J80/E80,0) | L80: 0.349 | M80: =IF(AND(B80="SELL",L80>0),D80*L80,0) | O80: =IF(AND(B80="SELL",G80<>0),Q80/ABS(G80),0) | P80: =IF(AND(B80="SELL",D80>0),R80/D80,0) | Q80: =IF(AND(B80="SELL",D80>0,E80>0),(D80/E80)+G80,0) | R80: =IF(B80="SELL",Q80*F80,0) | S80: =S79+R80
A81: 80 | B81: SELL | C81: 45981 | D81: 100000 | E81: 934.48 | F81: 934.48 | G81: -107.07 | I81: 935.11 | K81: =IF(AND(B81="SELL",E81>0,J81<>""),J81/E81,0) | L81: 0 | M81: =IF(AND(B81="SELL",L81>0),D81*L81,0) | O81: =IF(AND(B81="SELL",G81<>0),Q81/ABS(G81),0) | P81: =IF(AND(B81="SELL",D81>0),R81/D81,0) | Q81: =IF(AND(B81="SELL",D81>0,E81>0),(D81/E81)+G81,0) | R81: =IF(B81="SELL",Q81*F81,0) | S81: =S80+R81
A82: 81 | B82: SELL | C82: 45982 | D82: 105000 | E82: 934.48 | F82: 934.48 | G82: -106.93 | I82: 828.18 | J82: 341.7 | K82: =IF(AND(B82="SELL",E82>0,J82<>""),J82/E82,0) | L82: 0.348 | M82: =IF(AND(B82="SELL",L82>0),D82*L82,0) | O82: =IF(AND(B82="SELL",G82<>0),Q82/ABS(G82),0) | P82: =IF(AND(B82="SELL",D82>0),R82/D82,0) | Q82: =IF(AND(B82="SELL",D82>0,E82>0),(D82/E82)+G82,0) | R82: =IF(B82="SELL",Q82*F82,0) | S82: =S81+R82
A83: 82 | B83: SELL | C83: 45982 | D83: 15000 | E83: 934.48 | F83: 934.48 | G83: -15.55 | I83: 812.63 | J83: 335.537 | K83: =IF(AND(B83="SELL",E83>0,J83<>""),J83/E83,0) | L83: 0.348 | M83: =IF(AND(B83="SELL",L83>0),D83*L83,0) | O83: =IF(AND(B83="SELL",G83<>0),Q83/ABS(G83),0) | P83: =IF(AND(B83="SELL",D83>0),R83/D83,0) | Q83: =IF(AND(B83="SELL",D83>0,E83>0),(D83/E83)+G83,0) | R83: =IF(B83="SELL",Q83*F83,0) | S83: =S82+R83
A84: 83 | B84: SELL | C84: 45983 | D84: 40000 | E84: 934.48 | F84: 934.48 | G84: -40.51 | I84: 772.12 | J84: 342.61 | K84: =IF(AND(B84="SELL",E84>0,J84<>""),J84/E84,0) | L84: 0.347 | M84: =IF(AND(B84="SELL",L84>0),D84*L84,0) | O84: =IF(AND(B84="SELL",G84<>0),Q84/ABS(G84),0) | P84: =IF(AND(B84="SELL",D84>0),R84/D84,0) | Q84: =IF(AND(B84="SELL",D84>0,E84>0),(D84/E84)+G84,0) | R84: =IF(B84="SELL",Q84*F84,0) | S84: =S83+R84
A85: 84 | B85: SELL | C85: 45983 | D85: 40000 | E85: 934.48 | F85: 934.48 | G85: -40.46 | I85: 731.66 | J85: 343 | K85: =IF(AND(B85="SELL",E85>0,J85<>""),J85/E85,0) | L85: 0.347 | M85: =IF(AND(B85="SELL",L85>0),D85*L85,0) | O85: =IF(AND(B85="SELL",G85<>0),Q85/ABS(G85),0) | P85: =IF(AND(B85="SELL",D85>0),R85/D85,0) | Q85: =IF(AND(B85="SELL",D85>0,E85>0),(D85/E85)+G85,0) | R85: =IF(B85="SELL",Q85*F85,0) | S85: =S84+R85
A86: 85 | B86: SELL | C86: 45983 | D86: 24000 | E86: 934.48 | F86: 934.48 | G86: -24.42 | I86: 707.24 | J86: 340.9 | K86: =IF(AND(B86="SELL",E86>0,J86<>""),J86/E86,0) | L86: 0.347 | M86: =IF(AND(B86="SELL",L86>0),D86*L86,0) | O86: =IF(AND(B86="SELL",G86<>0),Q86/ABS(G86),0) | P86: =IF(AND(B86="SELL",D86>0),R86/D86,0) | Q86: =IF(AND(B86="SELL",D86>0,E86>0),(D86/E86)+G86,0) | R86: =IF(B86="SELL",Q86*F86,0) | S86: =S85+R86
A87: 86 | B87: SELL | C87: 45984 | D87: 20000 | E87: 934.48 | F87: 934.48 | G87: -20.96 | I87: 686.28 | J87: 331.01 | K87: =IF(AND(B87="SELL",E87>0,J87<>""),J87/E87,0) | L87: 0.347 | M87: =IF(AND(B87="SELL",L87>0),D87*L87,0) | O87: =IF(AND(B87="SELL",G87<>0),Q87/ABS(G87),0) | P87: =IF(AND(B87="SELL",D87>0),R87/D87,0) | Q87: =IF(AND(B87="SELL",D87>0,E87>0),(D87/E87)+G87,0) | R87: =IF(B87="SELL",Q87*F87,0) | S87: =S86+R87
A88: 87 | B88: SELL | C88: 45984 | D88: 80000 | E88: 934.48 | F88: 934.48 | G88: -79.85 | I88: 606.43 | J88: 349.655 | K88: =IF(AND(B88="SELL",E88>0,J88<>""),J88/E88,0) | L88: 0.349 | M88: =IF(AND(B88="SELL",L88>0),D88*L88,0) | O88: =IF(AND(B88="SELL",G88<>0),Q88/ABS(G88),0) | P88: =IF(AND(B88="SELL",D88>0),R88/D88,0) | Q88: =IF(AND(B88="SELL",D88>0,E88>0),(D88/E88)+G88,0) | R88: =IF(B88="SELL",Q88*F88,0) | S88: =S87+R88
A89: 88 | B89: SELL | C89: 45984 | D89: 30000 | E89: 934.48 | F89: 934.48 | G89: -29.99 | I89: 576.44 | J89: 349.06 | K89: =IF(AND(B89="SELL",E89>0,J89<>""),J89/E89,0) | L89: 0.349 | M89: =IF(AND(B89="SELL",L89>0),D89*L89,0) | O89: =IF(AND(B89="SELL",G89<>0),Q89/ABS(G89),0) | P89: =IF(AND(B89="SELL",D89>0),R89/D89,0) | Q89: =IF(AND(B89="SELL",D89>0,E89>0),(D89/E89)+G89,0) | R89: =IF(B89="SELL",Q89*F89,0) | S89: =S88+R89
A90: 89 | B90: SELL | C90: 45986 | D90: 20000 | E90: 934.48 | F90: 934.48 | G90: -20.22 | I90: 556.22 | J90: 354 | K90: =IF(AND(B90="SELL",E90>0,J90<>""),J90/E90,0) | L90: 0.358 | M90: =IF(AND(B90="SELL",L90>0),D90*L90,0) | O90: =IF(AND(B90="SELL",G90<>0),Q90/ABS(G90),0) | P90: =IF(AND(B90="SELL",D90>0),R90/D90,0) | Q90: =IF(AND(B90="SELL",D90>0,E90>0),(D90/E90)+G90,0) | R90: =IF(B90="SELL",Q90*F90,0) | S90: =S89+R90
A91: 90 | B91: SELL | C91: 45986 | D91: 13580 | E91: 934.48 | F91: 934.48 | G91: -13.67 | I91: 542.55 | J91: 355.5 | K91: =IF(AND(B91="SELL",E91>0,J91<>""),J91/E91,0) | L91: 0.358 | M91: =IF(AND(B91="SELL",L91>0),D91*L91,0) | O91: =IF(AND(B91="SELL",G91<>0),Q91/ABS(G91),0) | P91: =IF(AND(B91="SELL",D91>0),R91/D91,0) | Q91: =IF(AND(B91="SELL",D91>0,E91>0),(D91/E91)+G91,0) | R91: =IF(B91="SELL",Q91*F91,0) | S91: =S90+R91
A92: 91 | B92: SELL | C92: 45986 | D92: 10000 | E92: 934.48 | F92: 934.48 | G92: -10.08 | I92: 532.47 | J92: 355.13 | K92: =IF(AND(B92="SELL",E92>0,J92<>""),J92/E92,0) | L92: 0.358 | M92: =IF(AND(B92="SELL",L92>0),D92*L92,0) | O92: =IF(AND(B92="SELL",G92<>0),Q92/ABS(G92),0) | P92: =IF(AND(B92="SELL",D92>0),R92/D92,0) | Q92: =IF(AND(B92="SELL",D92>0,E92>0),(D92/E92)+G92,0) | R92: =IF(B92="SELL",Q92*F92,0) | S92: =S91+R92
A93: 92 | B93: SELL | C93: 45986 | D93: 125000 | E93: 934.48 | F93: 934.48 | G93: -124.85 | I93: 407.62 | J93: 358.41 | K93: =IF(AND(B93="SELL",E93>0,J93<>""),J93/E93,0) | L93: 0.358 | M93: =IF(AND(B93="SELL",L93>0),D93*L93,0) | O93: =IF(AND(B93="SELL",G93<>0),Q93/ABS(G93),0) | P93: =IF(AND(B93="SELL",D93>0),R93/D93,0) | Q93: =IF(AND(B93="SELL",D93>0,E93>0),(D93/E93)+G93,0) | R93: =IF(B93="SELL",Q93*F93,0) | S93: =S92+R93
... A105: 104 | B105: SELL | C105: 45988 | D105: 20000 | E105: 934.48 | F105: 934.48 | G105: -20.45 | I105: -740.51 | J105: 365.601 | K105: =IF(AND(B105="SELL",E105>0,J105<>""),J105/E105,0) | L105: 0.374 | M105: =IF(AND(B105="SELL",L105>0),D105*L105,0) | O105: =IF(AND(B105="SELL",G105<>0),Q105/ABS(G105),0) | P105: =IF(AND(B105="SELL",D105>0),R105/D105,0) | Q105: =IF(AND(B105="SELL",D105>0,E105>0),(D105/E105)+G105,0) | R105: =IF(B105="SELL",Q105*F105,0) | S105: =S104+R105
A106: 105 | B106: BUY | C106: 45988 | D106: 1535800 | E106: 931.84 | F106: 931.84 | G106: 1648.08 | I106: 907.57 | K106: =IF(AND(B106="SELL",E106>0,J106<>""),J106/E106,0) | L106: 0 | M106: =IF(AND(B106="SELL",L106>0),D106*L106,0) | O106: =IF(AND(B106="SELL",G106<>0),Q106/ABS(G106),0) | P106: =IF(AND(B106="SELL",D106>0),R106/D106,0) | Q106: =IF(AND(B106="SELL",D106>0,E106>0),(D106/E106)+G106,0) | R106: =IF(B106="SELL",Q106*F106,0) | S106: =S105+R106
A107: 106 | B107: SELL | C107: 45989 | D107: 15000 | E107: 931.84 | F107: 931.84 | G107: -15.33 | I107: 892.24 | J107: 363.01 | K107: =IF(AND(B107="SELL",E107>0,J107<>""),J107/E107,0) | L107: 0.371 | M107: =IF(AND(B107="SELL",L107>0),D107*L107,0) | O107: =IF(AND(B107="SELL",G107<>0),Q107/ABS(G107),0) | P107: =IF(AND(B107="SELL",D107>0),R107/D107,0) | Q107: =IF(AND(B107="SELL",D107>0,E107>0),(D107/E107)+G107,0) | R107: =IF(B107="SELL",Q107*F107,0) | S107: =S106+R107
A108: 107 | B108: SELL | C108: 45989 | D108: 20000 | E108: 931.84 | F108: 931.84 | G108: -20.5 | I108: 871.74 | J108: 366.8 | K108: =IF(AND(B108="SELL",E108>0,J108<>""),J108/E108,0) | L108: 0.371 | M108: =IF(AND(B108="SELL",L108>0),D108*L108,0) | O108: =IF(AND(B108="SELL",G108<>0),Q108/ABS(G108),0) | P108: =IF(AND(B108="SELL",D108>0),R108/D108,0) | Q108: =IF(AND(B108="SELL",D108>0,E108>0),(D108/E108)+G108,0) | R108: =IF(B108="SELL",Q108*F108,0) | S108: =S107+R108
A109: 108 | B109: SELL | C109: 45989 | D109: 50000 | E109: 931.84 | F109: 931.84 | G109: -49.7 | I109: 822.04 | J109: 3.37 | K109: =IF(AND(B109="SELL",E109>0,J109<>""),J109/E109,0) | L109: 0.00335 | M109: =IF(AND(B109="SELL",L109>0),D109*L109,0) | O109: =IF(AND(B109="SELL",G109<>0),Q109/ABS(G109),0) | P109: =IF(AND(B109="SELL",D109>0),R109/D109,0) | Q109: =IF(AND(B109="SELL",D109>0,E109>0),(D109/E109)+G109,0) | R109: =IF(B109="SELL",Q109*F109,0) | S109: =S108+R109
A110: 109 | B110: SELL | C110: 45989 | D110: 70000 | E110: 931.84 | F110: 931.84 | G110: -71.54 | I110: 750.5 | J110: 363.001 | K110: =IF(AND(B110="SELL",E110>0,J110<>""),J110/E110,0) | L110: 0.371 | M110: =IF(AND(B110="SELL",L110>0),D110*L110,0) | O110: =IF(AND(B110="SELL",G110<>0),Q110/ABS(G110),0) | P110: =IF(AND(B110="SELL",D110>0),R110/D110,0) | Q110: =IF(AND(B110="SELL",D110>0,E110>0),(D110/E110)+G110,0) | R110: =IF(B110="SELL",Q110*F110,0) | S110: =S109+R110
A111: 110 | B111: SELL | C111: 45989 | D111: 40000 | E111: 931.84 | F111: 931.84 | G111: -41.02 | I111: 709.48 | J111: 361.725 | K111: =IF(AND(B111="SELL",E111>0,J111<>""),J111/E111,0) | L111: 0.371 | M111: =IF(AND(B111="SELL",L111>0),D111*L111,0) | O111: =IF(AND(B111="SELL",G111<>0),Q111/ABS(G111),0) | P111: =IF(AND(B111="SELL",D111>0),R111/D111,0) | Q111: =IF(AND(B111="SELL",D111>0,E111>0),(D111/E111)+G111,0) | R111: =IF(B111="SELL",Q111*F111,0) | S111: =S110+R111
A112: 111 | B112: SELL | C112: 45989 | D112: 30000 | E112: 931.84 | F112: 931.84 | G112: -30.69 | I112: 678.79 | J112: 363.601 | K112: =IF(AND(B112="SELL",E112>0,J112<>""),J112/E112,0) | L112: 0.372 | M112: =IF(AND(B112="SELL",L112>0),D112*L112,0) | O112: =IF(AND(B112="SELL",G112<>0),Q112/ABS(G112),0) | P112: =IF(AND(B112="SELL",D112>0),R112/D112,0) | Q112: =IF(AND(B112="SELL",D112>0,E112>0),(D112/E112)+G112,0) | R112: =IF(B112="SELL",Q112*F112,0) | S112: =S111+R112
A113: 112 | B113: SELL | C113: 45989 | D113: 400000 | E113: 931.84 | F113: 931.84 | G113: -407.18 | I113: 271.61 | J113: 365.351 | K113: =IF(AND(B113="SELL",E113>0,J113<>""),J113/E113,0) | L113: 0.372 | M113: =IF(AND(B113="SELL",L113>0),D113*L113,0) | O113: =IF(AND(B113="SELL",G113<>0),Q113/ABS(G113),0) | P113: =IF(AND(B113="SELL",D113>0),R113/D113,0) | Q113: =IF(AND(B113="SELL",D113>0,E113>0),(D113/E113)+G113,0) | R113: =IF(B113="SELL",Q113*F113,0) | S113: =S112+R113
A114: 113 | B114: SELL | C114: 45989 | D114: 13250 | E114: 931.84 | F114: 931.84 | G114: -13.68 | I114: 257.93 | J114: 359.115 | K114: =IF(AND(B114="SELL",E114>0,J114<>""),J114/E114,0) | L114: 0.371 | M114: =IF(AND(B114="SELL",L114>0),D114*L114,0) | O114: =IF(AND(B114="SELL",G114<>0),Q114/ABS(G114),0) | P114: =IF(AND(B114="SELL",D114>0),R114/D114,0) | Q114: =IF(AND(B114="SELL",D114>0,E114>0),(D114/E114)+G114,0) | R114: =IF(B114="SELL",Q114*F114,0) | S114: =S113+R114
A115: 114 | B115: SELL | C115: 45989 | D115: 50000 | E115: 931.84 | F115: 931.84 | G115: -50.82 | I115: 207.11 | J115: 365 | K115: =IF(AND(B115="SELL",E115>0,J115<>""),J115/E115,0) | L115: 0.371 | M115: =IF(AND(B115="SELL",L115>0),D115*L115,0) | O115: =IF(AND(B115="SELL",G115<>0),Q115/ABS(G115),0) | P115: =IF(AND(B115="SELL",D115>0),R115/D115,0) | Q115: =IF(AND(B115="SELL",D115>0,E115>0),(D115/E115)+G115,0) | R115: =IF(B115="SELL",Q115*F115,0) | S115: =S114+R115
A116: 115 | B116: SELL | C116: 45990 | D116: 18000 | E116: 934.11 | F116: 934.11 | G116: -18.34 | I116: 188.77 | J116: 364.011 | K116: =IF(AND(B116="SELL",E116>0,J116<>""),J116/E116,0) | L116: 0.371 | M116: =IF(AND(B116="SELL",L116>0),D116*L116,0) | O116: =IF(AND(B116="SELL",G116<>0),Q116/ABS(G116),0) | P116: =IF(AND(B116="SELL",D116>0),R116/D116,0) | Q116: =IF(AND(B116="SELL",D116>0,E116>0),(D116/E116)+G116,0) | R116: =IF(B116="SELL",Q116*F116,0) | S116: =S115+R116
A117: 116 | B117: SELL | C117: 45990 | D117: 70000 | E117: 934.11 | F117: 934.11 | G117: -71.35 | I117: 117.42 | J117: 363.968 | K117: =IF(AND(B117="SELL",E117>0,J117<>""),J117/E117,0) | L117: 0.371 | M117: =IF(AND(B117="SELL",L117>0),D117*L117,0) | O117: =IF(AND(B117="SELL",G117<>0),Q117/ABS(G117),0) | P117: =IF(AND(B117="SELL",D117>0),R117/D117,0) | Q117: =IF(AND(B117="SELL",D117>0,E117>0),(D117/E117)+G117,0) | R117: =IF(B117="SELL",Q117*F117,0) | S117: =S116+R117
A118: 117 | B118: SELL | C118: 45990 | D118: 100000 | E118: 934.11 | F118: 934.11 | G118: -101.11 | I118: 16.31 | J118: 366.91 | K118: =IF(AND(B118="SELL",E118>0,J118<>""),J118/E118,0) | L118: 0.371 | M118: =IF(AND(B118="SELL",L118>0),D118*L118,0) | O118: =IF(AND(B118="SELL",G118<>0),Q118/ABS(G118),0) | P118: =IF(AND(B118="SELL",D118>0),R118/D118,0) | Q118: =IF(AND(B118="SELL",D118>0,E118>0),(D118/E118)+G118,0) | R118: =IF(B118="SELL",Q118*F118,0) | S118: =S117+R118
... A122: 121 | B122: SELL | C122: 45990 | D122: 150000 | E122: 934.11 | F122: 934.11 | G122: -151.32 | I122: -194.25 | J122: 367.751 | K122: =IF(AND(B122="SELL",E122>0,J122<>""),J122/E122,0) | L122: 0.371 | M122: =IF(AND(B122="SELL",L122>0),D122*L122,0) | O122: =IF(AND(B122="SELL",G122<>0),Q122/ABS(G122),0) | P122: =IF(AND(B122="SELL",D122>0),R122/D122,0) | Q122: =IF(AND(B122="SELL",D122>0,E122>0),(D122/E122)+G122,0) | R122: =IF(B122="SELL",Q122*F122,0) | S122: =S121+R122
A123: 122 | B123: BUY | C123: 45990 | D123: 1500000 | E123: 934.11 | F123: 934.11 | G123: 1605.8 | I123: 1411.55 | K123: =IF(AND(B123="SELL",E123>0,J123<>""),J123/E123,0) | L123: 0 | M123: =IF(AND(B123="SELL",L123>0),D123*L123,0) | O123: =IF(AND(B123="SELL",G123<>0),Q123/ABS(G123),0) | P123: =IF(AND(B123="SELL",D123>0),R123/D123,0) | Q123: =IF(AND(B123="SELL",D123>0,E123>0),(D123/E123)+G123,0) | R123: =IF(B123="SELL",Q123*F123,0) | S123: =S122+R123
A124: 123 | B124: SELL | C124: 45991 | D124: 15000 | E124: 934.11 | F124: 934.11 | G124: -15.15 | I124: 1396.4 | J124: 367.308 | K124: =IF(AND(B124="SELL",E124>0,J124<>""),J124/E124,0) | L124: 0.371 | M124: =IF(AND(B124="SELL",L124>0),D124*L124,0) | O124: =IF(AND(B124="SELL",G124<>0),Q124/ABS(G124),0) | P124: =IF(AND(B124="SELL",D124>0),R124/D124,0) | Q124: =IF(AND(B124="SELL",D124>0,E124>0),(D124/E124)+G124,0) | R124: =IF(B124="SELL",Q124*F124,0) | S124: =S123+R124
A125: 124 | B125: SELL | C125: 45991 | D125: 13250 | E125: 934.11 | F125: 934.11 | G125: -13.46 | I125: 1382.94 | J125: 365 | K125: =IF(AND(B125="SELL",E125>0,J125<>""),J125/E125,0) | L125: 0.371 | M125: =IF(AND(B125="SELL",L125>0),D125*L125,0) | O125: =IF(AND(B125="SELL",G125<>0),Q125/ABS(G125),0) | P125: =IF(AND(B125="SELL",D125>0),R125/D125,0) | Q125: =IF(AND(B125="SELL",D125>0,E125>0),(D125/E125)+G125,0) | R125: =IF(B125="SELL",Q125*F125,0) | S125: =S124+R125
A126: 125 | B126: SELL | C126: 45991 | D126: 25000 | E126: 934.11 | F126: 934.11 | G126: -25.28 | I126: 1357.66 | J126: 366.801 | K126: =IF(AND(B126="SELL",E126>0,J126<>""),J126/E126,0) | L126: 0.371 | M126: =IF(AND(B126="SELL",L126>0),D126*L126,0) | O126: =IF(AND(B126="SELL",G126<>0),Q126/ABS(G126),0) | P126: =IF(AND(B126="SELL",D126>0),R126/D126,0) | Q126: =IF(AND(B126="SELL",D126>0,E126>0),(D126/E126)+G126,0) | R126: =IF(B126="SELL",Q126*F126,0) | S126: =S125+R126
A128: TOTALES — Noviembre 2025 | D128: =SUMIF(B2:B126,"SELL",D2:D126) | G128: =COUNTIF(B2:B126,"SELL") | I128: =I126 | Q128: =SUM(Q2:Q126) | R128: =SUMIF(B2:B126,"SELL",R2:R126) | S128: =S126

Sheet Diciembre 2025
A1: N° | B1: Tipo | C1: Fecha | D1: Monto CLP | E1: USDT/CLP Compra | F1: USDT/CLP Venta | G1: USDT Mov | H1: Tax Binance | I1: Capital USDT | J1: Tasa Destino | K1: Tasa Real | L1: Tasa IREMI | M1: Valor Destino | N1: Comentario | O1: % G USDT | P1: % G CLP | Q1: Ganancia USDT | R1: Ganancia CLP | S1: Acumulado SELL
A2: 1 | B2: SELL | C2: 45991 | D2: 25000 | E2: 934.11 | F2: 934.11 | G2: -25.28 | I2: 1357.66 | J2: 366.801 | K2: =IF(AND(B2="SELL",E2>0,J2<>""),J2/E2,0) | L2: 0.371 | M2: =IF(AND(B2="SELL",L2>0),D2*L2,0) | O2: =IF(AND(B2="SELL",G2<>0),Q2/ABS(G2),0) | P2: =IF(AND(B2="SELL",D2>0),R2/D2,0) | Q2: =IF(AND(B2="SELL",D2>0,E2>0),(D2/E2)+G2,0) | R2: =IF(B2="SELL",Q2*F2,0) | S2: ='Noviembre 2025'!S126+R2
A3: 2 | B3: SELL | C3: 45992 | D3: 50000 | E3: 934.11 | F3: 934.11 | G3: -50.88 | I3: 1306.78 | J3: 371.4 | K3: =IF(AND(B3="SELL",E3>0,J3<>""),J3/E3,0) | L3: 0.378 | M3: =IF(AND(B3="SELL",L3>0),D3*L3,0) | O3: =IF(AND(B3="SELL",G3<>0),Q3/ABS(G3),0) | P3: =IF(AND(B3="SELL",D3>0),R3/D3,0) | Q3: =IF(AND(B3="SELL",D3>0,E3>0),(D3/E3)+G3,0) | R3: =IF(B3="SELL",Q3*F3,0) | S3: =S2+R3
A4: 3 | B4: SELL | C4: 45992 | D4: 32000 | E4: 934.11 | F4: 934.11 | G4: -32.53 | I4: 1274.25 | J4: 368.851 | K4: =IF(AND(B4="SELL",E4>0,J4<>""),J4/E4,0) | L4: 0.375 | M4: =IF(AND(B4="SELL",L4>0),D4*L4,0) | O4: =IF(AND(B4="SELL",G4<>0),Q4/ABS(G4),0) | P4: =IF(AND(B4="SELL",D4>0),R4/D4,0) | Q4: =IF(AND(B4="SELL",D4>0,E4>0),(D4/E4)+G4,0) | R4: =IF(B4="SELL",Q4*F4,0) | S4: =S3+R4
A5: 4 | B5: SELL | C5: 45992 | D5: 60000 | E5: 934.11 | F5: 934.11 | G5: -60.15 | I5: 1214.1 | J5: 374.02 | K5: =IF(AND(B5="SELL",E5>0,J5<>""),J5/E5,0) | L5: 0.375 | M5: =IF(AND(B5="SELL",L5>0),D5*L5,0) | O5: =IF(AND(B5="SELL",G5<>0),Q5/ABS(G5),0) | P5: =IF(AND(B5="SELL",D5>0),R5/D5,0) | Q5: =IF(AND(B5="SELL",D5>0,E5>0),(D5/E5)+G5,0) | R5: =IF(B5="SELL",Q5*F5,0) | S5: =S4+R5
A6: 5 | B6: SELL | C6: 45992 | D6: 200000 | E6: 934.11 | F6: 934.11 | G6: -201.17 | I6: 1012.93 | J6: 373.85 | K6: =IF(AND(B6="SELL",E6>0,J6<>""),J6/E6,0) | L6: 0.376 | M6: =IF(AND(B6="SELL",L6>0),D6*L6,0) | O6: =IF(AND(B6="SELL",G6<>0),Q6/ABS(G6),0) | P6: =IF(AND(B6="SELL",D6>0),R6/D6,0) | Q6: =IF(AND(B6="SELL",D6>0,E6>0),(D6/E6)+G6,0) | R6: =IF(B6="SELL",Q6*F6,0) | S6: =S5+R6
A7: 6 | B7: SELL | C7: 45992 | D7: 130000 | E7: 934.11 | F7: 934.11 | G7: -130.69 | I7: 882.24 | J7: 373.001 | K7: =IF(AND(B7="SELL",E7>0,J7<>""),J7/E7,0) | L7: 0.375 | M7: =IF(AND(B7="SELL",L7>0),D7*L7,0) | O7: =IF(AND(B7="SELL",G7<>0),Q7/ABS(G7),0) | P7: =IF(AND(B7="SELL",D7>0),R7/D7,0) | Q7: =IF(AND(B7="SELL",D7>0,E7>0),(D7/E7)+G7,0) | R7: =IF(B7="SELL",Q7*F7,0) | S7: =S6+R7
A8: 7 | B8: SELL | C8: 45992 | D8: 65500 | E8: 934.11 | F8: 934.11 | G8: -64.89 | I8: 811.35 | J8: 378.801 | K8: =IF(AND(B8="SELL",E8>0,J8<>""),J8/E8,0) | L8: 0.375 | M8: =IF(AND(B8="SELL",L8>0),D8*L8,0) | O8: =IF(AND(B8="SELL",G8<>0),Q8/ABS(G8),0) | P8: =IF(AND(B8="SELL",D8>0),R8/D8,0) | Q8: =IF(AND(B8="SELL",D8>0,E8>0),(D8/E8)+G8,0) | R8: =IF(B8="SELL",Q8*F8,0) | S8: =S7+R8
A9: 8 | B9: SELL | C9: 45993 | D9: 33000 | E9: 934.11 | F9: 934.11 | G9: -33.12 | I9: 778.23 | J9: 384.27 | K9: =IF(AND(B9="SELL",E9>0,J9<>""),J9/E9,0) | L9: 0.385 | M9: =IF(AND(B9="SELL",L9>0),D9*L9,0) | O9: =IF(AND(B9="SELL",G9<>0),Q9/ABS(G9),0) | P9: =IF(AND(B9="SELL",D9>0),R9/D9,0) | Q9: =IF(AND(B9="SELL",D9>0,E9>0),(D9/E9)+G9,0) | R9: =IF(B9="SELL",Q9*F9,0) | S9: =S8+R9
A10: 9 | B10: SELL | C10: 45993 | D10: 60000 | E10: 934.11 | F10: 934.11 | G10: -58.94 | I10: 719.29 | J10: 3750.05 | K10: =IF(AND(B10="SELL",E10>0,J10<>""),J10/E10,0) | L10: 3.68 | M10: =IF(AND(B10="SELL",L10>0),D10*L10,0) | O10: =IF(AND(B10="SELL",G10<>0),Q10/ABS(G10),0) | P10: =IF(AND(B10="SELL",D10>0),R10/D10,0) | Q10: =IF(AND(B10="SELL",D10>0,E10>0),(D10/E10)+G10,0) | R10: =IF(B10="SELL",Q10*F10,0) | S10: =S9+R10
A11: 10 | B11: SELL | C11: 45993 | D11: 40000 | E11: 934.11 | F11: 934.11 | G11: -40.21 | I11: 679.08 | J11: 383.54 | K11: =IF(AND(B11="SELL",E11>0,J11<>""),J11/E11,0) | L11: 0.385 | M11: =IF(AND(B11="SELL",L11>0),D11*L11,0) | O11: =IF(AND(B11="SELL",G11<>0),Q11/ABS(G11),0) | P11: =IF(AND(B11="SELL",D11>0),R11/D11,0) | Q11: =IF(AND(B11="SELL",D11>0,E11>0),(D11/E11)+G11,0) | R11: =IF(B11="SELL",Q11*F11,0) | S11: =S10+R11
A12: 11 | B12: SELL | C12: 45993 | D12: 50000 | E12: 934.11 | F12: 934.11 | G12: -51.6 | I12: 627.48 | J12: 373.001 | K12: =IF(AND(B12="SELL",E12>0,J12<>""),J12/E12,0) | L12: 0.385 | M12: =IF(AND(B12="SELL",L12>0),D12*L12,0) | O12: =IF(AND(B12="SELL",G12<>0),Q12/ABS(G12),0) | P12: =IF(AND(B12="SELL",D12>0),R12/D12,0) | Q12: =IF(AND(B12="SELL",D12>0,E12>0),(D12/E12)+G12,0) | R12: =IF(B12="SELL",Q12*F12,0) | S12: =S11+R12
A13: 12 | B13: SELL | C13: 45994 | D13: 50000 | E13: 934.11 | F13: 934.11 | G13: -50.53 | I13: 576.95 | J13: 396.22 | K13: =IF(AND(B13="SELL",E13>0,J13<>""),J13/E13,0) | L13: 0.4 | M13: =IF(AND(B13="SELL",L13>0),D13*L13,0) | O13: =IF(AND(B13="SELL",G13<>0),Q13/ABS(G13),0) | P13: =IF(AND(B13="SELL",D13>0),R13/D13,0) | Q13: =IF(AND(B13="SELL",D13>0,E13>0),(D13/E13)+G13,0) | R13: =IF(B13="SELL",Q13*F13,0) | S13: =S12+R13
A14: 13 | B14: SELL | C14: 45994 | D14: 49000 | E14: 934.11 | F14: 934.11 | G14: -48.69 | I14: 528.26 | J14: 403 | K14: =IF(AND(B14="SELL",E14>0,J14<>""),J14/E14,0) | L14: 0.4 | M14: =IF(AND(B14="SELL",L14>0),D14*L14,0) | O14: =IF(AND(B14="SELL",G14<>0),Q14/ABS(G14),0) | P14: =IF(AND(B14="SELL",D14>0),R14/D14,0) | Q14: =IF(AND(B14="SELL",D14>0,E14>0),(D14/E14)+G14,0) | R14: =IF(B14="SELL",Q14*F14,0) | S14: =S13+R14
... A17: 16 | B17: SELL | C17: 45995 | D17: 40000 | E17: 934.11 | F17: 934.11 | G17: -39.2 | I17: 368.41 | J17: 423 | K17: =IF(AND(B17="SELL",E17>0,J17<>""),J17/E17,0) | L17: 0.414 | M17: =IF(AND(B17="SELL",L17>0),D17*L17,0) | O17: =IF(AND(B17="SELL",G17<>0),Q17/ABS(G17),0) | P17: =IF(AND(B17="SELL",D17>0),R17/D17,0) | Q17: =IF(AND(B17="SELL",D17>0,E17>0),(D17/E17)+G17,0) | R17: =IF(B17="SELL",Q17*F17,0) | S17: =S16+R17
A18: 17 | B18: BUY | C18: 45995 | D18: 1435000 | E18: 924.5 | F18: 924.5 | G18: 1552.12 | I18: 1920.53 | K18: =IF(AND(B18="SELL",E18>0,J18<>""),J18/E18,0) | M18: =IF(AND(B18="SELL",L18>0),D18*L18,0) | O18: =IF(AND(B18="SELL",G18<>0),Q18/ABS(G18),0) | P18: =IF(AND(B18="SELL",D18>0),R18/D18,0) | Q18: =IF(AND(B18="SELL",D18>0,E18>0),(D18/E18)+G18,0) | R18: =IF(B18="SELL",Q18*F18,0) | S18: =S17+R18
A19: 18 | B19: SELL | C19: 45996 | D19: 95000 | E19: 924.5 | F19: 924.5 | G19: -97.34 | I19: 1823.19 | J19: 416.01 | K19: =IF(AND(B19="SELL",E19>0,J19<>""),J19/E19,0) | L19: 0.426 | M19: =IF(AND(B19="SELL",L19>0),D19*L19,0) | O19: =IF(AND(B19="SELL",G19<>0),Q19/ABS(G19),0) | P19: =IF(AND(B19="SELL",D19>0),R19/D19,0) | Q19: =IF(AND(B19="SELL",D19>0,E19>0),(D19/E19)+G19,0) | R19: =IF(B19="SELL",Q19*F19,0) | S19: =S18+R19
A20: 19 | B20: SELL | C20: 45996 | D20: 100000 | E20: 924.5 | F20: 924.5 | G20: -102.16 | I20: 1721.03 | J20: 417.2 | K20: =IF(AND(B20="SELL",E20>0,J20<>""),J20/E20,0) | L20: 0.426 | M20: =IF(AND(B20="SELL",L20>0),D20*L20,0) | O20: =IF(AND(B20="SELL",G20<>0),Q20/ABS(G20),0) | P20: =IF(AND(B20="SELL",D20>0),R20/D20,0) | Q20: =IF(AND(B20="SELL",D20>0,E20>0),(D20/E20)+G20,0) | R20: =IF(B20="SELL",Q20*F20,0) | S20: =S19+R20
A21: 20 | B21: SELL | C21: 45996 | D21: 15000 | E21: 924.5 | F21: 924.5 | G21: -15.46 | I21: 1705.57 | J21: 414.1 | K21: =IF(AND(B21="SELL",E21>0,J21<>""),J21/E21,0) | L21: 0.426 | M21: =IF(AND(B21="SELL",L21>0),D21*L21,0) | O21: =IF(AND(B21="SELL",G21<>0),Q21/ABS(G21),0) | P21: =IF(AND(B21="SELL",D21>0),R21/D21,0) | Q21: =IF(AND(B21="SELL",D21>0,E21>0),(D21/E21)+G21,0) | R21: =IF(B21="SELL",Q21*F21,0) | S21: =S20+R21
A22: 21 | B22: SELL | C22: 45996 | D22: 158000 | E22: 924.5 | F22: 924.5 | G22: -161.39 | I22: 1544.18 | J22: 417.2 | K22: =IF(AND(B22="SELL",E22>0,J22<>""),J22/E22,0) | L22: 0.426 | M22: =IF(AND(B22="SELL",L22>0),D22*L22,0) | O22: =IF(AND(B22="SELL",G22<>0),Q22/ABS(G22),0) | P22: =IF(AND(B22="SELL",D22>0),R22/D22,0) | Q22: =IF(AND(B22="SELL",D22>0,E22>0),(D22/E22)+G22,0) | R22: =IF(B22="SELL",Q22*F22,0) | S22: =S21+R22
A23: 22 | B23: SELL | C23: 45997 | D23: 70000 | E23: 924.5 | F23: 924.5 | G23: -71.56 | I23: 1472.62 | J23: 419.02 | K23: =IF(AND(B23="SELL",E23>0,J23<>""),J23/E23,0) | L23: 0.428 | M23: =IF(AND(B23="SELL",L23>0),D23*L23,0) | O23: =IF(AND(B23="SELL",G23<>0),Q23/ABS(G23),0) | P23: =IF(AND(B23="SELL",D23>0),R23/D23,0) | Q23: =IF(AND(B23="SELL",D23>0,E23>0),(D23/E23)+G23,0) | R23: =IF(B23="SELL",Q23*F23,0) | S23: =S22+R23
A24: 23 | B24: SELL | C24: 45997 | D24: 500000 | E24: 924.5 | F24: 924.5 | G24: -511.78 | I24: 960.84 | J24: 422.1 | K24: =IF(AND(B24="SELL",E24>0,J24<>""),J24/E24,0) | L24: 0.432 | M24: =IF(AND(B24="SELL",L24>0),D24*L24,0) | O24: =IF(AND(B24="SELL",G24<>0),Q24/ABS(G24),0) | P24: =IF(AND(B24="SELL",D24>0),R24/D24,0) | Q24: =IF(AND(B24="SELL",D24>0,E24>0),(D24/E24)+G24,0) | R24: =IF(B24="SELL",Q24*F24,0) | S24: =S23+R24
A25: 24 | B25: SELL | C25: 45997 | D25: 250000 | E25: 924.5 | F25: 924.5 | G25: -254.95 | I25: 705.89 | J25: 423.701 | K25: =IF(AND(B25="SELL",E25>0,J25<>""),J25/E25,0) | L25: 0.432 | M25: =IF(AND(B25="SELL",L25>0),D25*L25,0) | O25: =IF(AND(B25="SELL",G25<>0),Q25/ABS(G25),0) | P25: =IF(AND(B25="SELL",D25>0),R25/D25,0) | Q25: =IF(AND(B25="SELL",D25>0,E25>0),(D25/E25)+G25,0) | R25: =IF(B25="SELL",Q25*F25,0) | S25: =S24+R25
A26: 25 | B26: SELL | C26: 45997 | D26: 60000 | E26: 924.5 | F26: 924.5 | G26: -61.66 | I26: 644.23 | J26: 416.82 | K26: =IF(AND(B26="SELL",E26>0,J26<>""),J26/E26,0) | L26: 0.428 | M26: =IF(AND(B26="SELL",L26>0),D26*L26,0) | O26: =IF(AND(B26="SELL",G26<>0),Q26/ABS(G26),0) | P26: =IF(AND(B26="SELL",D26>0),R26/D26,0) | Q26: =IF(AND(B26="SELL",D26>0,E26>0),(D26/E26)+G26,0) | R26: =IF(B26="SELL",Q26*F26,0) | S26: =S25+R26
A27: 26 | B27: SELL | C27: 45997 | D27: 20000 | E27: 924.5 | F27: 924.5 | G27: -20.68 | I27: 623.55 | J27: 415 | K27: =IF(AND(B27="SELL",E27>0,J27<>""),J27/E27,0) | L27: 0.428 | M27: =IF(AND(B27="SELL",L27>0),D27*L27,0) | O27: =IF(AND(B27="SELL",G27<>0),Q27/ABS(G27),0) | P27: =IF(AND(B27="SELL",D27>0),R27/D27,0) | Q27: =IF(AND(B27="SELL",D27>0,E27>0),(D27/E27)+G27,0) | R27: =IF(B27="SELL",Q27*F27,0) | S27: =S26+R27
A28: 27 | B28: SELL | C28: 45997 | D28: 50000 | E28: 924.5 | F28: 924.5 | G28: -51.24 | I28: 572.31 | J28: 418.1 | K28: =IF(AND(B28="SELL",E28>0,J28<>""),J28/E28,0) | L28: 0.428 | M28: =IF(AND(B28="SELL",L28>0),D28*L28,0) | O28: =IF(AND(B28="SELL",G28<>0),Q28/ABS(G28),0) | P28: =IF(AND(B28="SELL",D28>0),R28/D28,0) | Q28: =IF(AND(B28="SELL",D28>0,E28>0),(D28/E28)+G28,0) | R28: =IF(B28="SELL",Q28*F28,0) | S28: =S27+R28
A29: 28 | B29: SELL | C29: 45997 | D29: 100000 | E29: 924.5 | F29: 924.5 | G29: -101.99 | I29: 470.32 | J29: 419.88 | K29: =IF(AND(B29="SELL",E29>0,J29<>""),J29/E29,0) | L29: 0.428 | M29: =IF(AND(B29="SELL",L29>0),D29*L29,0) | O29: =IF(AND(B29="SELL",G29<>0),Q29/ABS(G29),0) | P29: =IF(AND(B29="SELL",D29>0),R29/D29,0) | Q29: =IF(AND(B29="SELL",D29>0,E29>0),(D29/E29)+G29,0) | R29: =IF(B29="SELL",Q29*F29,0) | S29: =S28+R29
A30: 29 | B30: SELL | C30: 45997 | D30: 20000 | E30: 924.5 | F30: 924.5 | G30: -20.73 | I30: 449.59 | J30: 414.7 | K30: =IF(AND(B30="SELL",E30>0,J30<>""),J30/E30,0) | L30: 0.428 | M30: =IF(AND(B30="SELL",L30>0),D30*L30,0) | O30: =IF(AND(B30="SELL",G30<>0),Q30/ABS(G30),0) | P30: =IF(AND(B30="SELL",D30>0),R30/D30,0) | Q30: =IF(AND(B30="SELL",D30>0,E30>0),(D30/E30)+G30,0) | R30: =IF(B30="SELL",Q30*F30,0) | S30: =S29+R30
... A35: 34 | B35: SELL | C35: 45999 | D35: 20000 | E35: 924.5 | F35: 924.5 | G35: -20.41 | I35: 198.86 | J35: 412.575 | K35: =IF(AND(B35="SELL",E35>0,J35<>""),J35/E35,0) | L35: 0.42 | M35: =IF(AND(B35="SELL",L35>0),D35*L35,0) | O35: =IF(AND(B35="SELL",G35<>0),Q35/ABS(G35),0) | P35: =IF(AND(B35="SELL",D35>0),R35/D35,0) | Q35: =IF(AND(B35="SELL",D35>0,E35>0),(D35/E35)+G35,0) | R35: =IF(B35="SELL",Q35*F35,0) | S35: =S34+R35
A36: 35 | B36: BUY | C36: 45999 | D36: 200000 | E36: 940.97 | F36: 940.97 | G36: 212.47 | I36: 411.33 | K36: =IF(AND(B36="SELL",E36>0,J36<>""),J36/E36,0) | L36: 0 | M36: =IF(AND(B36="SELL",L36>0),D36*L36,0) | O36: =IF(AND(B36="SELL",G36<>0),Q36/ABS(G36),0) | P36: =IF(AND(B36="SELL",D36>0),R36/D36,0) | Q36: =IF(AND(B36="SELL",D36>0,E36>0),(D36/E36)+G36,0) | R36: =IF(B36="SELL",Q36*F36,0) | S36: =S35+R36
A37: 36 | B37: SELL | C37: 45999 | D37: 250000 | E37: 940.97 | F37: 940.97 | G37: -250.92 | I37: 160.41 | J37: 419.702 | K37: =IF(AND(B37="SELL",E37>0,J37<>""),J37/E37,0) | L37: 0.421 | M37: =IF(AND(B37="SELL",L37>0),D37*L37,0) | O37: =IF(AND(B37="SELL",G37<>0),Q37/ABS(G37),0) | P37: =IF(AND(B37="SELL",D37>0),R37/D37,0) | Q37: =IF(AND(B37="SELL",D37>0,E37>0),(D37/E37)+G37,0) | R37: =IF(B37="SELL",Q37*F37,0) | S37: =S36+R37
A38: 37 | B38: SELL | C38: 46000 | D38: 10000 | E38: 940.97 | F38: 940.97 | G38: -10.32 | I38: 150.09 | J38: 410 | K38: =IF(AND(B38="SELL",E38>0,J38<>""),J38/E38,0) | L38: 0.421 | M38: =IF(AND(B38="SELL",L38>0),D38*L38,0) | O38: =IF(AND(B38="SELL",G38<>0),Q38/ABS(G38),0) | P38: =IF(AND(B38="SELL",D38>0),R38/D38,0) | Q38: =IF(AND(B38="SELL",D38>0,E38>0),(D38/E38)+G38,0) | R38: =IF(B38="SELL",Q38*F38,0) | S38: =S37+R38
A39: 38 | B39: SELL | C39: 46000 | D39: 37000 | E39: 940.97 | F39: 940.97 | G39: -37.66 | I39: 112.43 | J39: 414.2 | K39: =IF(AND(B39="SELL",E39>0,J39<>""),J39/E39,0) | L39: 0.421 | M39: =IF(AND(B39="SELL",L39>0),D39*L39,0) | O39: =IF(AND(B39="SELL",G39<>0),Q39/ABS(G39),0) | P39: =IF(AND(B39="SELL",D39>0),R39/D39,0) | Q39: =IF(AND(B39="SELL",D39>0,E39>0),(D39/E39)+G39,0) | R39: =IF(B39="SELL",Q39*F39,0) | S39: =S38+R39
A40: 39 | B40: SELL | C40: 46000 | D40: 25000 | E40: 940.97 | F40: 940.97 | G40: -25.22 | I40: 87.21 | J40: 418.322 | K40: =IF(AND(B40="SELL",E40>0,J40<>""),J40/E40,0) | L40: 0.421 | M40: =IF(AND(B40="SELL",L40>0),D40*L40,0) | O40: =IF(AND(B40="SELL",G40<>0),Q40/ABS(G40),0) | P40: =IF(AND(B40="SELL",D40>0),R40/D40,0) | Q40: =IF(AND(B40="SELL",D40>0,E40>0),(D40/E40)+G40,0) | R40: =IF(B40="SELL",Q40*F40,0) | S40: =S39+R40
A41: 40 | B41: SELL | C41: 46000 | D41: 55000 | E41: 940.97 | F41: 940.97 | G41: -56.56 | I41: 30.65 | J41: 416.7 | K41: =IF(AND(B41="SELL",E41>0,J41<>""),J41/E41,0) | L41: 0.421 | M41: =IF(AND(B41="SELL",L41>0),D41*L41,0) | O41: =IF(AND(B41="SELL",G41<>0),Q41/ABS(G41),0) | P41: =IF(AND(B41="SELL",D41>0),R41/D41,0) | Q41: =IF(AND(B41="SELL",D41>0,E41>0),(D41/E41)+G41,0) | R41: =IF(B41="SELL",Q41*F41,0) | S41: =S40+R41
A42: 41 | B42: BUY | C42: 46000 | D42: 1969000 | E42: 931.89 | F42: 931.89 | G42: 2112.84 | I42: 2143.49 | K42: =IF(AND(B42="SELL",E42>0,J42<>""),J42/E42,0) | M42: =IF(AND(B42="SELL",L42>0),D42*L42,0) | O42: =IF(AND(B42="SELL",G42<>0),Q42/ABS(G42),0) | P42: =IF(AND(B42="SELL",D42>0),R42/D42,0) | Q42: =IF(AND(B42="SELL",D42>0,E42>0),(D42/E42)+G42,0) | R42: =IF(B42="SELL",Q42*F42,0) | S42: =S41+R42
A43: 42 | B43: SELL | C43: 46001 | D43: 15000 | E43: 931.89 | F43: 931.89 | G43: -15.23 | I43: 2128.26 | J43: 418.1 | K43: =IF(AND(B43="SELL",E43>0,J43<>""),J43/E43,0) | L43: 0.423 | M43: =IF(AND(B43="SELL",L43>0),D43*L43,0) | O43: =IF(AND(B43="SELL",G43<>0),Q43/ABS(G43),0) | P43: =IF(AND(B43="SELL",D43>0),R43/D43,0) | Q43: =IF(AND(B43="SELL",D43>0,E43>0),(D43/E43)+G43,0) | R43: =IF(B43="SELL",Q43*F43,0) | S43: =S42+R43
A44: 43 | B44: SELL | C44: 46001 | D44: 20000 | E44: 931.89 | F44: 931.89 | G44: -20.08 | I44: 2108.18 | J44: 422.505 | K44: =IF(AND(B44="SELL",E44>0,J44<>""),J44/E44,0) | L44: 0.423 | M44: =IF(AND(B44="SELL",L44>0),D44*L44,0) | O44: =IF(AND(B44="SELL",G44<>0),Q44/ABS(G44),0) | P44: =IF(AND(B44="SELL",D44>0),R44/D44,0) | Q44: =IF(AND(B44="SELL",D44>0,E44>0),(D44/E44)+G44,0) | R44: =IF(B44="SELL",Q44*F44,0) | S44: =S43+R44
A45: 44 | B45: SELL | C45: 46001 | D45: 50000 | E45: 931.89 | F45: 931.89 | G45: -49.58 | I45: 2058.6 | J45: 427.09 | K45: =IF(AND(B45="SELL",E45>0,J45<>""),J45/E45,0) | L45: 0.423 | M45: =IF(AND(B45="SELL",L45>0),D45*L45,0) | O45: =IF(AND(B45="SELL",G45<>0),Q45/ABS(G45),0) | P45: =IF(AND(B45="SELL",D45>0),R45/D45,0) | Q45: =IF(AND(B45="SELL",D45>0,E45>0),(D45/E45)+G45,0) | R45: =IF(B45="SELL",Q45*F45,0) | S45: =S44+R45
A46: 45 | B46: SELL | C46: 46001 | D46: 12500 | E46: 931.89 | F46: 931.89 | G46: -12.58 | I46: 2046.02 | J46: 422.15 | K46: =IF(AND(B46="SELL",E46>0,J46<>""),J46/E46,0) | L46: 0.423 | M46: =IF(AND(B46="SELL",L46>0),D46*L46,0) | O46: =IF(AND(B46="SELL",G46<>0),Q46/ABS(G46),0) | P46: =IF(AND(B46="SELL",D46>0),R46/D46,0) | Q46: =IF(AND(B46="SELL",D46>0,E46>0),(D46/E46)+G46,0) | R46: =IF(B46="SELL",Q46*F46,0) | S46: =S45+R46
A47: 46 | B47: SELL | C47: 46002 | D47: 25000 | E47: 931.89 | F47: 931.89 | G47: -25.17 | I47: 2020.85 | J47: 420.971 | K47: =IF(AND(B47="SELL",E47>0,J47<>""),J47/E47,0) | L47: 0.424 | M47: =IF(AND(B47="SELL",L47>0),D47*L47,0) | O47: =IF(AND(B47="SELL",G47<>0),Q47/ABS(G47),0) | P47: =IF(AND(B47="SELL",D47>0),R47/D47,0) | Q47: =IF(AND(B47="SELL",D47>0,E47>0),(D47/E47)+G47,0) | R47: =IF(B47="SELL",Q47*F47,0) | S47: =S46+R47
A48: 47 | B48: SELL | C48: 46002 | D48: 40000 | E48: 931.89 | F48: 931.89 | G48: -38.99 | I48: 1981.86 | J48: 3.334 | K48: =IF(AND(B48="SELL",E48>0,J48<>""),J48/E48,0) | L48: 0.00326 | M48: =IF(AND(B48="SELL",L48>0),D48*L48,0) | O48: =IF(AND(B48="SELL",G48<>0),Q48/ABS(G48),0) | P48: =IF(AND(B48="SELL",D48>0),R48/D48,0) | Q48: =IF(AND(B48="SELL",D48>0,E48>0),(D48/E48)+G48,0) | R48: =IF(B48="SELL",Q48*F48,0) | S48: =S47+R48
A49: 48 | B49: SELL | C49: 46002 | D49: 10000 | E49: 931.89 | F49: 931.89 | G49: -10.1 | I49: 1971.76 | J49: 419.5 | K49: =IF(AND(B49="SELL",E49>0,J49<>""),J49/E49,0) | L49: 0.424 | M49: =IF(AND(B49="SELL",L49>0),D49*L49,0) | O49: =IF(AND(B49="SELL",G49<>0),Q49/ABS(G49),0) | P49: =IF(AND(B49="SELL",D49>0),R49/D49,0) | Q49: =IF(AND(B49="SELL",D49>0,E49>0),(D49/E49)+G49,0) | R49: =IF(B49="SELL",Q49*F49,0) | S49: =S48+R49
A50: 49 | B50: SELL | C50: 46002 | D50: 67800 | E50: 931.89 | F50: 931.89 | G50: -68.03 | I50: 1903.73 | J50: 422.506 | K50: =IF(AND(B50="SELL",E50>0,J50<>""),J50/E50,0) | L50: 0.424 | M50: =IF(AND(B50="SELL",L50>0),D50*L50,0) | O50: =IF(AND(B50="SELL",G50<>0),Q50/ABS(G50),0) | P50: =IF(AND(B50="SELL",D50>0),R50/D50,0) | Q50: =IF(AND(B50="SELL",D50>0,E50>0),(D50/E50)+G50,0) | R50: =IF(B50="SELL",Q50*F50,0) | S50: =S49+R50
A51: 50 | B51: SELL | C51: 46003 | D51: 20000 | E51: 931.89 | F51: 931.89 | G51: -20.58 | I51: 1883.15 | J51: 417.709 | K51: =IF(AND(B51="SELL",E51>0,J51<>""),J51/E51,0) | L51: 0.43 | M51: =IF(AND(B51="SELL",L51>0),D51*L51,0) | O51: =IF(AND(B51="SELL",G51<>0),Q51/ABS(G51),0) | P51: =IF(AND(B51="SELL",D51>0),R51/D51,0) | Q51: =IF(AND(B51="SELL",D51>0,E51>0),(D51/E51)+G51,0) | R51: =IF(B51="SELL",Q51*F51,0) | S51: =S50+R51
A52: 51 | B52: SELL | C52: 46003 | D52: 50000 | E52: 931.89 | F52: 931.89 | G52: -50.78 | I52: 1832.37 | J52: 423.325 | K52: =IF(AND(B52="SELL",E52>0,J52<>""),J52/E52,0) | L52: 0.43 | M52: =IF(AND(B52="SELL",L52>0),D52*L52,0) | O52: =IF(AND(B52="SELL",G52<>0),Q52/ABS(G52),0) | P52: =IF(AND(B52="SELL",D52>0),R52/D52,0) | Q52: =IF(AND(B52="SELL",D52>0,E52>0),(D52/E52)+G52,0) | R52: =IF(B52="SELL",Q52*F52,0) | S52: =S51+R52
A53: 52 | B53: SELL | C53: 46003 | D53: 50000 | E53: 931.89 | F53: 931.89 | G53: -50.91 | I53: 1781.46 | J53: 422.225 | K53: =IF(AND(B53="SELL",E53>0,J53<>""),J53/E53,0) | L53: 0.43 | M53: =IF(AND(B53="SELL",L53>0),D53*L53,0) | O53: =IF(AND(B53="SELL",G53<>0),Q53/ABS(G53),0) | P53: =IF(AND(B53="SELL",D53>0),R53/D53,0) | Q53: =IF(AND(B53="SELL",D53>0,E53>0),(D53/E53)+G53,0) | R53: =IF(B53="SELL",Q53*F53,0) | S53: =S52+R53
A54: 53 | B54: SELL | C54: 46003 | D54: 19000 | E54: 931.89 | F54: 931.89 | G54: -19.38 | I54: 1762.08 | J54: 421.5 | K54: =IF(AND(B54="SELL",E54>0,J54<>""),J54/E54,0) | L54: 0.43 | M54: =IF(AND(B54="SELL",L54>0),D54*L54,0) | O54: =IF(AND(B54="SELL",G54<>0),Q54/ABS(G54),0) | P54: =IF(AND(B54="SELL",D54>0),R54/D54,0) | Q54: =IF(AND(B54="SELL",D54>0,E54>0),(D54/E54)+G54,0) | R54: =IF(B54="SELL",Q54*F54,0) | S54: =S53+R54
... A80: 79 | B80: SELL | C80: 46007 | D80: 222988.5 | E80: 931.89 | F80: 931.89 | G80: -222.79 | I80: -13.98 | J80: 435.5 | K80: =IF(AND(B80="SELL",E80>0,J80<>""),J80/E80,0) | L80: 0.435 | M80: =IF(AND(B80="SELL",L80>0),D80*L80,0) | O80: =IF(AND(B80="SELL",G80<>0),Q80/ABS(G80),0) | P80: =IF(AND(B80="SELL",D80>0),R80/D80,0) | Q80: =IF(AND(B80="SELL",D80>0,E80>0),(D80/E80)+G80,0) | R80: =IF(B80="SELL",Q80*F80,0) | S80: =S79+R80
A81: 80 | B81: BUY | C81: 46007 | D81: 2128700 | E81: 918.69 | F81: 918.69 | G81: 2317.03 | I81: 2303.05 | K81: =IF(AND(B81="SELL",E81>0,J81<>""),J81/E81,0) | L81: 0 | M81: =IF(AND(B81="SELL",L81>0),D81*L81,0) | O81: =IF(AND(B81="SELL",G81<>0),Q81/ABS(G81),0) | P81: =IF(AND(B81="SELL",D81>0),R81/D81,0) | Q81: =IF(AND(B81="SELL",D81>0,E81>0),(D81/E81)+G81,0) | R81: =IF(B81="SELL",Q81*F81,0) | S81: =S80+R81
A82: 81 | B82: SELL | C82: 46007 | D82: 27586.2 | E82: 918.69 | F82: 918.69 | G82: -27.76 | I82: 2275.29 | J82: 433.111 | K82: =IF(AND(B82="SELL",E82>0,J82<>""),J82/E82,0) | L82: 0.435 | M82: =IF(AND(B82="SELL",L82>0),D82*L82,0) | O82: =IF(AND(B82="SELL",G82<>0),Q82/ABS(G82),0) | P82: =IF(AND(B82="SELL",D82>0),R82/D82,0) | Q82: =IF(AND(B82="SELL",D82>0,E82>0),(D82/E82)+G82,0) | R82: =IF(B82="SELL",Q82*F82,0) | S82: =S81+R82
A83: 82 | B83: SELL | C83: 46008 | D83: 86000 | E83: 918.69 | F83: 918.69 | G83: -88.16 | I83: 2187.13 | J83: 436 | K83: =IF(AND(B83="SELL",E83>0,J83<>""),J83/E83,0) | L83: 0.447 | M83: =IF(AND(B83="SELL",L83>0),D83*L83,0) | O83: =IF(AND(B83="SELL",G83<>0),Q83/ABS(G83),0) | P83: =IF(AND(B83="SELL",D83>0),R83/D83,0) | Q83: =IF(AND(B83="SELL",D83>0,E83>0),(D83/E83)+G83,0) | R83: =IF(B83="SELL",Q83*F83,0) | S83: =S82+R83
A84: 83 | B84: SELL | C84: 46008 | D84: 60000 | E84: 918.69 | F84: 918.69 | G84: -60.98 | I84: 2126.15 | J84: 439.752 | K84: =IF(AND(B84="SELL",E84>0,J84<>""),J84/E84,0) | L84: 0.447 | M84: =IF(AND(B84="SELL",L84>0),D84*L84,0) | O84: =IF(AND(B84="SELL",G84<>0),Q84/ABS(G84),0) | P84: =IF(AND(B84="SELL",D84>0),R84/D84,0) | Q84: =IF(AND(B84="SELL",D84>0,E84>0),(D84/E84)+G84,0) | R84: =IF(B84="SELL",Q84*F84,0) | S84: =S83+R84
A85: 84 | B85: SELL | C85: 46008 | D85: 10000 | E85: 918.69 | F85: 918.69 | G85: -10.23 | I85: 2115.92 | J85: 436.525 | K85: =IF(AND(B85="SELL",E85>0,J85<>""),J85/E85,0) | L85: 0.447 | M85: =IF(AND(B85="SELL",L85>0),D85*L85,0) | O85: =IF(AND(B85="SELL",G85<>0),Q85/ABS(G85),0) | P85: =IF(AND(B85="SELL",D85>0),R85/D85,0) | Q85: =IF(AND(B85="SELL",D85>0,E85>0),(D85/E85)+G85,0) | R85: =IF(B85="SELL",Q85*F85,0) | S85: =S84+R85
A86: 85 | B86: SELL | C86: 46009 | D86: 250000 | E86: 918.69 | F86: 918.69 | G86: -252.6 | I86: 1863.32 | J86: 3.365 | K86: =IF(AND(B86="SELL",E86>0,J86<>""),J86/E86,0) | L86: 0.0034 | M86: =IF(AND(B86="SELL",L86>0),D86*L86,0) | O86: =IF(AND(B86="SELL",G86<>0),Q86/ABS(G86),0) | P86: =IF(AND(B86="SELL",D86>0),R86/D86,0) | Q86: =IF(AND(B86="SELL",D86>0,E86>0),(D86/E86)+G86,0) | R86: =IF(B86="SELL",Q86*F86,0) | S86: =S85+R86
A87: 86 | B87: SELL | C87: 46009 | D87: 230000 | E87: 918.69 | F87: 918.69 | G87: -233.43 | I87: 1629.89 | J87: 3.35 | K87: =IF(AND(B87="SELL",E87>0,J87<>""),J87/E87,0) | L87: 0.0034 | M87: =IF(AND(B87="SELL",L87>0),D87*L87,0) | O87: =IF(AND(B87="SELL",G87<>0),Q87/ABS(G87),0) | P87: =IF(AND(B87="SELL",D87>0),R87/D87,0) | Q87: =IF(AND(B87="SELL",D87>0,E87>0),(D87/E87)+G87,0) | R87: =IF(B87="SELL",Q87*F87,0) | S87: =S86+R87
A88: 87 | B88: SELL | C88: 46009 | D88: 50000 | E88: 918.69 | F88: 918.69 | G88: -49.01 | I88: 1580.88 | J88: 473.3 | K88: =IF(AND(B88="SELL",E88>0,J88<>""),J88/E88,0) | L88: 0.464 | M88: =IF(AND(B88="SELL",L88>0),D88*L88,0) | O88: =IF(AND(B88="SELL",G88<>0),Q88/ABS(G88),0) | P88: =IF(AND(B88="SELL",D88>0),R88/D88,0) | Q88: =IF(AND(B88="SELL",D88>0,E88>0),(D88/E88)+G88,0) | R88: =IF(B88="SELL",Q88*F88,0) | S88: =S87+R88
A89: 88 | B89: SELL | C89: 46009 | D89: 150000 | E89: 918.69 | F89: 918.69 | G89: -145 | I89: 1435.88 | J89: 480 | K89: =IF(AND(B89="SELL",E89>0,J89<>""),J89/E89,0) | L89: 0.464 | M89: =IF(AND(B89="SELL",L89>0),D89*L89,0) | O89: =IF(AND(B89="SELL",G89<>0),Q89/ABS(G89),0) | P89: =IF(AND(B89="SELL",D89>0),R89/D89,0) | Q89: =IF(AND(B89="SELL",D89>0,E89>0),(D89/E89)+G89,0) | R89: =IF(B89="SELL",Q89*F89,0) | S89: =S88+R89
A90: 89 | B90: SELL | C90: 46009 | D90: 20000 | E90: 918.69 | F90: 918.69 | G90: -19.45 | I90: 1416.43 | J90: 477 | K90: =IF(AND(B90="SELL",E90>0,J90<>""),J90/E90,0) | L90: 0.464 | M90: =IF(AND(B90="SELL",L90>0),D90*L90,0) | O90: =IF(AND(B90="SELL",G90<>0),Q90/ABS(G90),0) | P90: =IF(AND(B90="SELL",D90>0),R90/D90,0) | Q90: =IF(AND(B90="SELL",D90>0,E90>0),(D90/E90)+G90,0) | R90: =IF(B90="SELL",Q90*F90,0) | S90: =S89+R90
A91: 90 | B91: SELL | C91: 46009 | D91: 10000 | E91: 918.69 | F91: 918.69 | G91: -9.76 | I91: 1406.67 | J91: 475 | K91: =IF(AND(B91="SELL",E91>0,J91<>""),J91/E91,0) | L91: 0.464 | M91: =IF(AND(B91="SELL",L91>0),D91*L91,0) | O91: =IF(AND(B91="SELL",G91<>0),Q91/ABS(G91),0) | P91: =IF(AND(B91="SELL",D91>0),R91/D91,0) | Q91: =IF(AND(B91="SELL",D91>0,E91>0),(D91/E91)+G91,0) | R91: =IF(B91="SELL",Q91*F91,0) | S91: =S90+R91
A92: 91 | B92: SELL | C92: 46010 | D92: 240000 | E92: 918.69 | F92: 918.69 | G92: -277 | I92: 1129.67 | J92: 914.2 | K92: =IF(AND(B92="SELL",E92>0,J92<>""),J92/E92,0) | L92: 0.0011544545 | M92: =IF(AND(B92="SELL",L92>0),D92*L92,0) | N92: cambio usdt | O92: =IF(AND(B92="SELL",G92<>0),Q92/ABS(G92),0) | P92: =IF(AND(B92="SELL",D92>0),R92/D92,0) | Q92: =IF(AND(B92="SELL",D92>0,E92>0),(D92/E92)+G92,0) | R92: =IF(B92="SELL",Q92*F92,0) | S92: =S91+R92
A93: 92 | B93: SELL | C93: 46010 | D93: 34000 | E93: 918.69 | F93: 918.69 | G93: -35.81 | I93: 1093.86 | J93: 469.87 | K93: =IF(AND(B93="SELL",E93>0,J93<>""),J93/E93,0) | L93: 0.495 | M93: =IF(AND(B93="SELL",L93>0),D93*L93,0) | O93: =IF(AND(B93="SELL",G93<>0),Q93/ABS(G93),0) | P93: =IF(AND(B93="SELL",D93>0),R93/D93,0) | Q93: =IF(AND(B93="SELL",D93>0,E93>0),(D93/E93)+G93,0) | R93: =IF(B93="SELL",Q93*F93,0) | S93: =S92+R93
A94: 93 | B94: SELL | C94: 46010 | D94: 70000 | E94: 918.69 | F94: 918.69 | G94: -73.13 | I94: 1020.73 | J94: 473.801 | K94: =IF(AND(B94="SELL",E94>0,J94<>""),J94/E94,0) | L94: 0.495 | M94: =IF(AND(B94="SELL",L94>0),D94*L94,0) | O94: =IF(AND(B94="SELL",G94<>0),Q94/ABS(G94),0) | P94: =IF(AND(B94="SELL",D94>0),R94/D94,0) | Q94: =IF(AND(B94="SELL",D94>0,E94>0),(D94/E94)+G94,0) | R94: =IF(B94="SELL",Q94*F94,0) | S94: =S93+R94
A95: 94 | B95: SELL | C95: 46010 | D95: 30000 | E95: 918.69 | F95: 918.69 | G95: -31.73 | I95: 989 | J95: 468 | K95: =IF(AND(B95="SELL",E95>0,J95<>""),J95/E95,0) | L95: 0.495 | M95: =IF(AND(B95="SELL",L95>0),D95*L95,0) | O95: =IF(AND(B95="SELL",G95<>0),Q95/ABS(G95),0) | P95: =IF(AND(B95="SELL",D95>0),R95/D95,0) | Q95: =IF(AND(B95="SELL",D95>0,E95>0),(D95/E95)+G95,0) | R95: =IF(B95="SELL",Q95*F95,0) | S95: =S94+R95
A96: 95 | B96: SELL | C96: 46010 | D96: 121000 | E96: 918.69 | F96: 918.69 | G96: -123.75 | I96: 865.25 | J96: 472.25 | K96: =IF(AND(B96="SELL",E96>0,J96<>""),J96/E96,0) | L96: 0.483 | M96: =IF(AND(B96="SELL",L96>0),D96*L96,0) | O96: =IF(AND(B96="SELL",G96<>0),Q96/ABS(G96),0) | P96: =IF(AND(B96="SELL",D96>0),R96/D96,0) | Q96: =IF(AND(B96="SELL",D96>0,E96>0),(D96/E96)+G96,0) | R96: =IF(B96="SELL",Q96*F96,0) | S96: =S95+R96
A97: 96 | B97: SELL | C97: 46010 | D97: 89030 | E97: 918.69 | F97: 918.69 | G97: -91.1 | I97: 774.15 | J97: 472 | K97: =IF(AND(B97="SELL",E97>0,J97<>""),J97/E97,0) | L97: 0.483 | M97: =IF(AND(B97="SELL",L97>0),D97*L97,0) | O97: =IF(AND(B97="SELL",G97<>0),Q97/ABS(G97),0) | P97: =IF(AND(B97="SELL",D97>0),R97/D97,0) | Q97: =IF(AND(B97="SELL",D97>0,E97>0),(D97/E97)+G97,0) | R97: =IF(B97="SELL",Q97*F97,0) | S97: =S96+R97
A98: 97 | B98: SELL | C98: 46011 | D98: 180000 | E98: 918.69 | F98: 918.69 | G98: -180.99 | I98: 593.16 | J98: 471.4 | K98: =IF(AND(B98="SELL",E98>0,J98<>""),J98/E98,0) | L98: 0.474 | M98: =IF(AND(B98="SELL",L98>0),D98*L98,0) | O98: =IF(AND(B98="SELL",G98<>0),Q98/ABS(G98),0) | P98: =IF(AND(B98="SELL",D98>0),R98/D98,0) | Q98: =IF(AND(B98="SELL",D98>0,E98>0),(D98/E98)+G98,0) | R98: =IF(B98="SELL",Q98*F98,0) | S98: =S97+R98
A99: 98 | B99: SELL | C99: 46011 | D99: 10000 | E99: 918.69 | F99: 918.69 | G99: -10.23 | I99: 582.93 | J99: 463 | K99: =IF(AND(B99="SELL",E99>0,J99<>""),J99/E99,0) | L99: 0.474 | M99: =IF(AND(B99="SELL",L99>0),D99*L99,0) | O99: =IF(AND(B99="SELL",G99<>0),Q99/ABS(G99),0) | P99: =IF(AND(B99="SELL",D99>0),R99/D99,0) | Q99: =IF(AND(B99="SELL",D99>0,E99>0),(D99/E99)+G99,0) | R99: =IF(B99="SELL",Q99*F99,0) | S99: =S98+R99
A100: 99 | B100: SELL | C100: 46011 | D100: 20000 | E100: 918.69 | F100: 918.69 | G100: -20.61 | I100: 562.32 | J100: 459.877 | K100: =IF(AND(B100="SELL",E100>0,J100<>""),J100/E100,0) | L100: 0.474 | M100: =IF(AND(B100="SELL",L100>0),D100*L100,0) | O100: =IF(AND(B100="SELL",G100<>0),Q100/ABS(G100),0) | P100: =IF(AND(B100="SELL",D100>0),R100/D100,0) | Q100: =IF(AND(B100="SELL",D100>0,E100>0),(D100/E100)+G100,0) | R100: =IF(B100="SELL",Q100*F100,0) | S100: =S99+R100
A101: 100 | B101: SELL | C101: 46011 | D101: 20000 | E101: 918.69 | F101: 918.69 | G101: -20.29 | I101: 542.03 | J101: 467 | K101: =IF(AND(B101="SELL",E101>0,J101<>""),J101/E101,0) | L101: 0.474 | M101: =IF(AND(B101="SELL",L101>0),D101*L101,0) | O101: =IF(AND(B101="SELL",G101<>0),Q101/ABS(G101),0) | P101: =IF(AND(B101="SELL",D101>0),R101/D101,0) | Q101: =IF(AND(B101="SELL",D101>0,E101>0),(D101/E101)+G101,0) | R101: =IF(B101="SELL",Q101*F101,0) | S101: =S100+R101
A102: 101 | B102: SELL | C102: 46012 | D102: 15000 | E102: 918.69 | F102: 918.69 | G102: -15.6 | I102: 526.43 | J102: 461.52 | K102: =IF(AND(B102="SELL",E102>0,J102<>""),J102/E102,0) | L102: 0.48 | M102: =IF(AND(B102="SELL",L102>0),D102*L102,0) | O102: =IF(AND(B102="SELL",G102<>0),Q102/ABS(G102),0) | P102: =IF(AND(B102="SELL",D102>0),R102/D102,0) | Q102: =IF(AND(B102="SELL",D102>0,E102>0),(D102/E102)+G102,0) | R102: =IF(B102="SELL",Q102*F102,0) | S102: =S101+R102
A103: 102 | B103: SELL | C103: 46012 | D103: 14700 | E103: 918.69 | F103: 918.69 | G103: -15.17 | I103: 511.26 | J103: 465 | K103: =IF(AND(B103="SELL",E103>0,J103<>""),J103/E103,0) | L103: 0.48 | M103: =IF(AND(B103="SELL",L103>0),D103*L103,0) | O103: =IF(AND(B103="SELL",G103<>0),Q103/ABS(G103),0) | P103: =IF(AND(B103="SELL",D103>0),R103/D103,0) | Q103: =IF(AND(B103="SELL",D103>0,E103>0),(D103/E103)+G103,0) | R103: =IF(B103="SELL",Q103*F103,0) | S103: =S102+R103
A104: 103 | B104: SELL | C104: 46012 | D104: 15300 | E104: 918.69 | F104: 918.69 | G104: -15.83 | I104: 495.43 | J104: 464.81 | K104: =IF(AND(B104="SELL",E104>0,J104<>""),J104/E104,0) | L104: 0.48 | M104: =IF(AND(B104="SELL",L104>0),D104*L104,0) | O104: =IF(AND(B104="SELL",G104<>0),Q104/ABS(G104),0) | P104: =IF(AND(B104="SELL",D104>0),R104/D104,0) | Q104: =IF(AND(B104="SELL",D104>0,E104>0),(D104/E104)+G104,0) | R104: =IF(B104="SELL",Q104*F104,0) | S104: =S103+R104
... A111: 110 | B111: SELL | C111: 46013 | D111: 20000 | E111: 918.69 | F111: 918.69 | G111: -20.27 | I111: 170.21 | J111: 475.42 | K111: =IF(AND(B111="SELL",E111>0,J111<>""),J111/E111,0) | L111: 0.482 | M111: =IF(AND(B111="SELL",L111>0),D111*L111,0) | O111: =IF(AND(B111="SELL",G111<>0),Q111/ABS(G111),0) | P111: =IF(AND(B111="SELL",D111>0),R111/D111,0) | Q111: =IF(AND(B111="SELL",D111>0,E111>0),(D111/E111)+G111,0) | R111: =IF(B111="SELL",Q111*F111,0) | S111: =S110+R111
A112: 111 | B112: BUY | C112: 46014 | D112: 1880000 | E112: 910.65 | F112: 910.65 | G112: 2064.45 | I112: 2234.66 | K112: =IF(AND(B112="SELL",E112>0,J112<>""),J112/E112,0) | L112: 0 | M112: =IF(AND(B112="SELL",L112>0),D112*L112,0) | O112: =IF(AND(B112="SELL",G112<>0),Q112/ABS(G112),0) | P112: =IF(AND(B112="SELL",D112>0),R112/D112,0) | Q112: =IF(AND(B112="SELL",D112>0,E112>0),(D112/E112)+G112,0) | R112: =IF(B112="SELL",Q112*F112,0) | S112: =S111+R112
A113: 112 | B113: SELL | C113: 46014 | D113: 130000 | E113: 910.65 | F113: 910.65 | G113: -133.41 | I113: 2101.25 | J113: 475.501 | K113: =IF(AND(B113="SELL",E113>0,J113<>""),J113/E113,0) | L113: 0.488 | M113: =IF(AND(B113="SELL",L113>0),D113*L113,0) | O113: =IF(AND(B113="SELL",G113<>0),Q113/ABS(G113),0) | P113: =IF(AND(B113="SELL",D113>0),R113/D113,0) | Q113: =IF(AND(B113="SELL",D113>0,E113>0),(D113/E113)+G113,0) | R113: =IF(B113="SELL",Q113*F113,0) | S113: =S112+R113
A114: 113 | B114: SELL | C114: 46014 | D114: 20000 | E114: 910.65 | F114: 910.65 | G114: -20.93 | I114: 2080.32 | J114: 466.25 | K114: =IF(AND(B114="SELL",E114>0,J114<>""),J114/E114,0) | L114: 0.488 | M114: =IF(AND(B114="SELL",L114>0),D114*L114,0) | O114: =IF(AND(B114="SELL",G114<>0),Q114/ABS(G114),0) | P114: =IF(AND(B114="SELL",D114>0),R114/D114,0) | Q114: =IF(AND(B114="SELL",D114>0,E114>0),(D114/E114)+G114,0) | R114: =IF(B114="SELL",Q114*F114,0) | S114: =S113+R114
A115: 114 | B115: SELL | C115: 46014 | D115: 40000 | E115: 910.65 | F115: 910.65 | G115: -41.97 | I115: 2038.35 | J115: 465 | K115: =IF(AND(B115="SELL",E115>0,J115<>""),J115/E115,0) | L115: 0.488 | M115: =IF(AND(B115="SELL",L115>0),D115*L115,0) | O115: =IF(AND(B115="SELL",G115<>0),Q115/ABS(G115),0) | P115: =IF(AND(B115="SELL",D115>0),R115/D115,0) | Q115: =IF(AND(B115="SELL",D115>0,E115>0),(D115/E115)+G115,0) | R115: =IF(B115="SELL",Q115*F115,0) | S115: =S114+R115
A116: 115 | B116: SELL | C116: 46014 | D116: 15000 | E116: 910.65 | F116: 910.65 | G116: -15.74 | I116: 2022.61 | J116: 465 | K116: =IF(AND(B116="SELL",E116>0,J116<>""),J116/E116,0) | L116: 0.488 | M116: =IF(AND(B116="SELL",L116>0),D116*L116,0) | O116: =IF(AND(B116="SELL",G116<>0),Q116/ABS(G116),0) | P116: =IF(AND(B116="SELL",D116>0),R116/D116,0) | Q116: =IF(AND(B116="SELL",D116>0,E116>0),(D116/E116)+G116,0) | R116: =IF(B116="SELL",Q116*F116,0) | S116: =S115+R116
A117: 116 | B117: SELL | C117: 46014 | D117: 128000 | E117: 910.65 | F117: 910.65 | G117: -131.91 | I117: 1890.7 | J117: 473.52 | K117: =IF(AND(B117="SELL",E117>0,J117<>""),J117/E117,0) | L117: 0.488 | M117: =IF(AND(B117="SELL",L117>0),D117*L117,0) | O117: =IF(AND(B117="SELL",G117<>0),Q117/ABS(G117),0) | P117: =IF(AND(B117="SELL",D117>0),R117/D117,0) | Q117: =IF(AND(B117="SELL",D117>0,E117>0),(D117/E117)+G117,0) | R117: =IF(B117="SELL",Q117*F117,0) | S117: =S116+R117
A118: 117 | B118: SELL | C118: 46014 | D118: 39000 | E118: 910.65 | F118: 910.65 | G118: -41.32 | I118: 1849.38 | J118: 460.55 | K118: =IF(AND(B118="SELL",E118>0,J118<>""),J118/E118,0) | L118: 0.488 | M118: =IF(AND(B118="SELL",L118>0),D118*L118,0) | O118: =IF(AND(B118="SELL",G118<>0),Q118/ABS(G118),0) | P118: =IF(AND(B118="SELL",D118>0),R118/D118,0) | Q118: =IF(AND(B118="SELL",D118>0,E118>0),(D118/E118)+G118,0) | R118: =IF(B118="SELL",Q118*F118,0) | S118: =S117+R118
A119: 118 | B119: SELL | C119: 46014 | D119: 80000 | E119: 910.65 | F119: 910.65 | G119: -86.93 | I119: 1762.45 | K119: =IF(AND(B119="SELL",E119>0,J119<>""),J119/E119,0) | L119: 0 | M119: =IF(AND(B119="SELL",L119>0),D119*L119,0) | N119: en USDT para cuchi cuchi | O119: =IF(AND(B119="SELL",G119<>0),Q119/ABS(G119),0) | P119: =IF(AND(B119="SELL",D119>0),R119/D119,0) | Q119: =IF(AND(B119="SELL",D119>0,E119>0),(D119/E119)+G119,0) | R119: =IF(B119="SELL",Q119*F119,0) | S119: =S118+R119
A120: 119 | B120: SELL | C120: 46014 | D120: 70000 | E120: 910.65 | F120: 910.65 | G120: -72.35 | I120: 1707.9 | J120: 472.1 | K120: =IF(AND(B120="SELL",E120>0,J120<>""),J120/E120,0) | L120: 0.488 | M120: =IF(AND(B120="SELL",L120>0),D120*L120,0) | O120: =IF(AND(B120="SELL",G120<>0),Q120/ABS(G120),0) | P120: =IF(AND(B120="SELL",D120>0),R120/D120,0) | Q120: =IF(AND(B120="SELL",D120>0,E120>0),(D120/E120)+G120,0) | R120: =IF(B120="SELL",Q120*F120,0) | S120: =S119+R120
A121: 120 | B121: SELL | C121: 46014 | D121: 80000 | E121: 910.65 | F121: 910.65 | G121: -82.44 | I121: 1625.46 | J121: 473.501 | K121: =IF(AND(B121="SELL",E121>0,J121<>""),J121/E121,0) | L121: 0.488 | M121: =IF(AND(B121="SELL",L121>0),D121*L121,0) | O121: =IF(AND(B121="SELL",G121<>0),Q121/ABS(G121),0) | P121: =IF(AND(B121="SELL",D121>0),R121/D121,0) | Q121: =IF(AND(B121="SELL",D121>0,E121>0),(D121/E121)+G121,0) | R121: =IF(B121="SELL",Q121*F121,0) | S121: =S120+R121
A122: 121 | B122: SELL | C122: 46014 | D122: 300000 | E122: 910.65 | F122: 910.65 | G122: -304.61 | I122: 1320.85 | J122: 480.6 | K122: =IF(AND(B122="SELL",E122>0,J122<>""),J122/E122,0) | L122: 0.488 | M122: =IF(AND(B122="SELL",L122>0),D122*L122,0) | O122: =IF(AND(B122="SELL",G122<>0),Q122/ABS(G122),0) | P122: =IF(AND(B122="SELL",D122>0),R122/D122,0) | Q122: =IF(AND(B122="SELL",D122>0,E122>0),(D122/E122)+G122,0) | R122: =IF(B122="SELL",Q122*F122,0) | S122: =S121+R122
A123: 122 | B123: SELL | C123: 46014 | D123: 10000 | E123: 910.65 | F123: 910.65 | G123: -10.7 | I123: 1310.15 | J123: 456.019 | K123: =IF(AND(B123="SELL",E123>0,J123<>""),J123/E123,0) | L123: 0.488 | M123: =IF(AND(B123="SELL",L123>0),D123*L123,0) | O123: =IF(AND(B123="SELL",G123<>0),Q123/ABS(G123),0) | P123: =IF(AND(B123="SELL",D123>0),R123/D123,0) | Q123: =IF(AND(B123="SELL",D123>0,E123>0),(D123/E123)+G123,0) | R123: =IF(B123="SELL",Q123*F123,0) | S123: =S122+R123
A124: 123 | B124: SELL | C124: 46015 | D124: 150000 | E124: 910.65 | F124: 910.65 | G124: -156.24 | I124: 1153.91 | J124: 480.21 | K124: =IF(AND(B124="SELL",E124>0,J124<>""),J124/E124,0) | L124: 0.5 | M124: =IF(AND(B124="SELL",L124>0),D124*L124,0) | O124: =IF(AND(B124="SELL",G124<>0),Q124/ABS(G124),0) | P124: =IF(AND(B124="SELL",D124>0),R124/D124,0) | Q124: =IF(AND(B124="SELL",D124>0,E124>0),(D124/E124)+G124,0) | R124: =IF(B124="SELL",Q124*F124,0) | S124: =S123+R124
A125: 124 | B125: SELL | C125: 46015 | D125: 10000 | E125: 910.65 | F125: 910.65 | G125: -10.42 | I125: 1143.49 | J125: 479.61 | K125: =IF(AND(B125="SELL",E125>0,J125<>""),J125/E125,0) | L125: 0.5 | M125: =IF(AND(B125="SELL",L125>0),D125*L125,0) | O125: =IF(AND(B125="SELL",G125<>0),Q125/ABS(G125),0) | P125: =IF(AND(B125="SELL",D125>0),R125/D125,0) | Q125: =IF(AND(B125="SELL",D125>0,E125>0),(D125/E125)+G125,0) | R125: =IF(B125="SELL",Q125*F125,0) | S125: =S124+R125
A126: 125 | B126: SELL | C126: 46015 | D126: 80000 | E126: 910.65 | F126: 910.65 | G126: -84.03 | I126: 1059.46 | J126: 476.001 | K126: =IF(AND(B126="SELL",E126>0,J126<>""),J126/E126,0) | L126: 0.5 | M126: =IF(AND(B126="SELL",L126>0),D126*L126,0) | O126: =IF(AND(B126="SELL",G126<>0),Q126/ABS(G126),0) | P126: =IF(AND(B126="SELL",D126>0),R126/D126,0) | Q126: =IF(AND(B126="SELL",D126>0,E126>0),(D126/E126)+G126,0) | R126: =IF(B126="SELL",Q126*F126,0) | S126: =S125+R126
A127: 126 | B127: SELL | C127: 46015 | D127: 20000 | E127: 910.65 | F127: 910.65 | G127: -20.97 | I127: 1038.49 | J127: 476.75 | K127: =IF(AND(B127="SELL",E127>0,J127<>""),J127/E127,0) | L127: 0.5 | M127: =IF(AND(B127="SELL",L127>0),D127*L127,0) | O127: =IF(AND(B127="SELL",G127<>0),Q127/ABS(G127),0) | P127: =IF(AND(B127="SELL",D127>0),R127/D127,0) | Q127: =IF(AND(B127="SELL",D127>0,E127>0),(D127/E127)+G127,0) | R127: =IF(B127="SELL",Q127*F127,0) | S127: =S126+R127
A128: 127 | B128: SELL | C128: 46015 | D128: 90000 | E128: 910.65 | F128: 910.65 | G128: -94.13 | I128: 944.36 | J128: 478.06 | K128: =IF(AND(B128="SELL",E128>0,J128<>""),J128/E128,0) | L128: 0.5 | M128: =IF(AND(B128="SELL",L128>0),D128*L128,0) | O128: =IF(AND(B128="SELL",G128<>0),Q128/ABS(G128),0) | P128: =IF(AND(B128="SELL",D128>0),R128/D128,0) | Q128: =IF(AND(B128="SELL",D128>0,E128>0),(D128/E128)+G128,0) | R128: =IF(B128="SELL",Q128*F128,0) | S128: =S127+R128
A129: 128 | B129: SELL | C129: 46015 | D129: 20000 | E129: 910.65 | F129: 910.65 | G129: -21.04 | I129: 923.32 | J129: 475.2 | K129: =IF(AND(B129="SELL",E129>0,J129<>""),J129/E129,0) | L129: 0.5 | M129: =IF(AND(B129="SELL",L129>0),D129*L129,0) | O129: =IF(AND(B129="SELL",G129<>0),Q129/ABS(G129),0) | P129: =IF(AND(B129="SELL",D129>0),R129/D129,0) | Q129: =IF(AND(B129="SELL",D129>0,E129>0),(D129/E129)+G129,0) | R129: =IF(B129="SELL",Q129*F129,0) | S129: =S128+R129
A130: 129 | B130: SELL | C130: 46017 | D130: 30000 | E130: 910.65 | F130: 910.65 | G130: -31.27 | I130: 892.05 | J130: 490.2 | K130: =IF(AND(B130="SELL",E130>0,J130<>""),J130/E130,0) | L130: 0.511 | M130: =IF(AND(B130="SELL",L130>0),D130*L130,0) | O130: =IF(AND(B130="SELL",G130<>0),Q130/ABS(G130),0) | P130: =IF(AND(B130="SELL",D130>0),R130/D130,0) | Q130: =IF(AND(B130="SELL",D130>0,E130>0),(D130/E130)+G130,0) | R130: =IF(B130="SELL",Q130*F130,0) | S130: =S129+R130
A131: 130 | B131: SELL | C131: 46017 | D131: 68000 | E131: 910.65 | F131: 910.65 | G131: -69.61 | I131: 822.44 | J131: 499.122 | K131: =IF(AND(B131="SELL",E131>0,J131<>""),J131/E131,0) | L131: 0.511 | M131: =IF(AND(B131="SELL",L131>0),D131*L131,0) | O131: =IF(AND(B131="SELL",G131<>0),Q131/ABS(G131),0) | P131: =IF(AND(B131="SELL",D131>0),R131/D131,0) | Q131: =IF(AND(B131="SELL",D131>0,E131>0),(D131/E131)+G131,0) | R131: =IF(B131="SELL",Q131*F131,0) | S131: =S130+R131
... A138: 137 | B138: SELL | C138: 46020 | D138: 214000 | E138: 910.65 | F138: 910.65 | G138: -222.35 | I138: 347.47 | J138: 538 | K138: =IF(AND(B138="SELL",E138>0,J138<>""),J138/E138,0) | L138: 0.558 | M138: =IF(AND(B138="SELL",L138>0),D138*L138,0) | O138: =IF(AND(B138="SELL",G138<>0),Q138/ABS(G138),0) | P138: =IF(AND(B138="SELL",D138>0),R138/D138,0) | Q138: =IF(AND(B138="SELL",D138>0,E138>0),(D138/E138)+G138,0) | R138: =IF(B138="SELL",Q138*F138,0) | S138: =S137+R138
A139: 138 | B139: BUY | C139: 46020 | D139: 2853300 | E139: 912 | F139: 912 | G139: 3128.61 | I139: 3476.08 | K139: =IF(AND(B139="SELL",E139>0,J139<>""),J139/E139,0) | L139: 0 | M139: =IF(AND(B139="SELL",L139>0),D139*L139,0) | O139: =IF(AND(B139="SELL",G139<>0),Q139/ABS(G139),0) | P139: =IF(AND(B139="SELL",D139>0),R139/D139,0) | Q139: =IF(AND(B139="SELL",D139>0,E139>0),(D139/E139)+G139,0) | R139: =IF(B139="SELL",Q139*F139,0) | S139: =S138+R139
A140: 139 | B140: SELL | C140: 46020 | D140: 980000 | E140: 912 | F140: 910.65 | G140: -1015 | I140: 2461.08 | J140: 912 | K140: =IF(AND(B140="SELL",E140>0,J140<>""),J140/E140,0) | L140: 0.0010358 | M140: =IF(AND(B140="SELL",L140>0),D140*L140,0) | O140: =IF(AND(B140="SELL",G140<>0),Q140/ABS(G140),0) | P140: =IF(AND(B140="SELL",D140>0),R140/D140,0) | Q140: =IF(AND(B140="SELL",D140>0,E140>0),(D140/E140)+G140,0) | R140: =IF(B140="SELL",Q140*F140,0) | S140: =S139+R140
A141: 140 | B141: SELL | C141: 46020 | D141: 20000 | E141: 912 | F141: 910.65 | G141: -20.43 | I141: 2440.65 | J141: 546 | K141: =IF(AND(B141="SELL",E141>0,J141<>""),J141/E141,0) | L141: 0.558 | M141: =IF(AND(B141="SELL",L141>0),D141*L141,0) | O141: =IF(AND(B141="SELL",G141<>0),Q141/ABS(G141),0) | P141: =IF(AND(B141="SELL",D141>0),R141/D141,0) | Q141: =IF(AND(B141="SELL",D141>0,E141>0),(D141/E141)+G141,0) | R141: =IF(B141="SELL",Q141*F141,0) | S141: =S140+R141
A142: 141 | B142: SELL | C142: 46020 | D142: 205000 | E142: 912 | F142: 910.65 | G142: -206.77 | I142: 2233.88 | J142: 554.2 | K142: =IF(AND(B142="SELL",E142>0,J142<>""),J142/E142,0) | L142: 0.559 | M142: =IF(AND(B142="SELL",L142>0),D142*L142,0) | O142: =IF(AND(B142="SELL",G142<>0),Q142/ABS(G142),0) | P142: =IF(AND(B142="SELL",D142>0),R142/D142,0) | Q142: =IF(AND(B142="SELL",D142>0,E142>0),(D142/E142)+G142,0) | R142: =IF(B142="SELL",Q142*F142,0) | S142: =S141+R142
A143: 142 | B143: SELL | C143: 46021 | D143: 50000 | E143: 912 | F143: 910.65 | G143: -52.5 | I143: 2181.38 | J143: 539.001 | K143: =IF(AND(B143="SELL",E143>0,J143<>""),J143/E143,0) | L143: 0.566 | M143: =IF(AND(B143="SELL",L143>0),D143*L143,0) | O143: =IF(AND(B143="SELL",G143<>0),Q143/ABS(G143),0) | P143: =IF(AND(B143="SELL",D143>0),R143/D143,0) | Q143: =IF(AND(B143="SELL",D143>0,E143>0),(D143/E143)+G143,0) | R143: =IF(B143="SELL",Q143*F143,0) | S143: =S142+R143
...

Sheet Enero 2026
A1: N° | B1: Tipo | C1: Fecha | D1: Monto CLP | E1: USDT/CLP Compra | F1: USDT/CLP Venta | G1: USDT Mov | H1: Tax Binance | I1: Capital USDT | J1: Tasa Destino | K1: Tasa Real | L1: Tasa IREMI | M1: Valor Destino | N1: Comentario | O1: % G USDT | P1: % G CLP | Q1: Ganancia USDT | R1: Ganancia CLP | S1: Acumulado SELL
A2: 1 | B2: SELL | C2: 46022 | D2: 35000 | E2: 912 | F2: 912 | G2: -36.98 | I2: 1163.63 | J2: 546 | K2: =IF(AND(B2="SELL",E2>0,J2<>""),J2/E2,0) | L2: 0.577 | M2: =IF(AND(B2="SELL",L2>0),D2*L2,0) | O2: =IF(AND(B2="SELL",G2<>0),Q2/ABS(G2),0) | P2: =IF(AND(B2="SELL",D2>0),R2/D2,0) | Q2: =IF(AND(B2="SELL",D2>0,E2>0),(D2/E2)+G2,0) | R2: =IF(B2="SELL",Q2*F2,0) | S2: ='Diciembre 2025'!S161+R2
A3: 2 | B3: SELL | C3: 46022 | D3: 110000 | E3: 912 | F3: 912 | G3: -112.06 | I3: 1051.57 | J3: 566.35 | K3: =IF(AND(B3="SELL",E3>0,J3<>""),J3/E3,0) | L3: 0.577 | M3: =IF(AND(B3="SELL",L3>0),D3*L3,0) | O3: =IF(AND(B3="SELL",G3<>0),Q3/ABS(G3),0) | P3: =IF(AND(B3="SELL",D3>0),R3/D3,0) | Q3: =IF(AND(B3="SELL",D3>0,E3>0),(D3/E3)+G3,0) | R3: =IF(B3="SELL",Q3*F3,0) | S3: =S2+R3
A4: 3 | B4: SELL | C4: 46022 | D4: 20000 | E4: 912 | F4: 912 | G4: -20.75 | I4: 1030.82 | J4: 556.075 | K4: =IF(AND(B4="SELL",E4>0,J4<>""),J4/E4,0) | L4: 0.577 | M4: =IF(AND(B4="SELL",L4>0),D4*L4,0) | O4: =IF(AND(B4="SELL",G4<>0),Q4/ABS(G4),0) | P4: =IF(AND(B4="SELL",D4>0),R4/D4,0) | Q4: =IF(AND(B4="SELL",D4>0,E4>0),(D4/E4)+G4,0) | R4: =IF(B4="SELL",Q4*F4,0) | S4: =S3+R4
A5: 4 | B5: SELL | C5: 46022 | D5: 60000 | E5: 912 | F5: 912 | G5: -61.11 | I5: 969.71 | J5: 567.2 | K5: =IF(AND(B5="SELL",E5>0,J5<>""),J5/E5,0) | L5: 0.577 | M5: =IF(AND(B5="SELL",L5>0),D5*L5,0) | O5: =IF(AND(B5="SELL",G5<>0),Q5/ABS(G5),0) | P5: =IF(AND(B5="SELL",D5>0),R5/D5,0) | Q5: =IF(AND(B5="SELL",D5>0,E5>0),(D5/E5)+G5,0) | R5: =IF(B5="SELL",Q5*F5,0) | S5: =S4+R5
A6: 5 | B6: SELL | C6: 46024 | D6: 50000 | E6: 912 | F6: 912 | G6: -52.12 | I6: 917.59 | J6: 558.3 | K6: =IF(AND(B6="SELL",E6>0,J6<>""),J6/E6,0) | L6: 0.582 | M6: =IF(AND(B6="SELL",L6>0),D6*L6,0) | O6: =IF(AND(B6="SELL",G6<>0),Q6/ABS(G6),0) | P6: =IF(AND(B6="SELL",D6>0),R6/D6,0) | Q6: =IF(AND(B6="SELL",D6>0,E6>0),(D6/E6)+G6,0) | R6: =IF(B6="SELL",Q6*F6,0) | S6: =S5+R6
A7: 6 | B7: SELL | C7: 46024 | D7: 100000 | E7: 912 | F7: 912 | G7: -102.94 | I7: 814.65 | J7: 565.365 | K7: =IF(AND(B7="SELL",E7>0,J7<>""),J7/E7,0) | L7: 0.582 | M7: =IF(AND(B7="SELL",L7>0),D7*L7,0) | O7: =IF(AND(B7="SELL",G7<>0),Q7/ABS(G7),0) | P7: =IF(AND(B7="SELL",D7>0),R7/D7,0) | Q7: =IF(AND(B7="SELL",D7>0,E7>0),(D7/E7)+G7,0) | R7: =IF(B7="SELL",Q7*F7,0) | S7: =S6+R7
A8: 7 | B8: SELL | C8: 46024 | D8: 20000 | E8: 912 | F8: 912 | G8: -20.96 | I8: 793.69 | J8: 555.25 | K8: =IF(AND(B8="SELL",E8>0,J8<>""),J8/E8,0) | L8: 0.582 | M8: =IF(AND(B8="SELL",L8>0),D8*L8,0) | O8: =IF(AND(B8="SELL",G8<>0),Q8/ABS(G8),0) | P8: =IF(AND(B8="SELL",D8>0),R8/D8,0) | Q8: =IF(AND(B8="SELL",D8>0,E8>0),(D8/E8)+G8,0) | R8: =IF(B8="SELL",Q8*F8,0) | S8: =S7+R8
A9: 8 | B9: SELL | C9: 46024 | D9: 65000 | E9: 912 | F9: 912 | G9: -64.77 | I9: 728.92 | J9: 584.05 | K9: =IF(AND(B9="SELL",E9>0,J9<>""),J9/E9,0) | L9: 0.582 | M9: =IF(AND(B9="SELL",L9>0),D9*L9,0) | O9: =IF(AND(B9="SELL",G9<>0),Q9/ABS(G9),0) | P9: =IF(AND(B9="SELL",D9>0),R9/D9,0) | Q9: =IF(AND(B9="SELL",D9>0,E9>0),(D9/E9)+G9,0) | R9: =IF(B9="SELL",Q9*F9,0) | S9: =S8+R9
A10: 9 | B10: SELL | C10: 46024 | D10: 20000 | E10: 912 | F10: 912 | G10: -19.62 | I10: 709.3 | J10: 593.001 | K10: =IF(AND(B10="SELL",E10>0,J10<>""),J10/E10,0) | L10: 0.582 | M10: =IF(AND(B10="SELL",L10>0),D10*L10,0) | O10: =IF(AND(B10="SELL",G10<>0),Q10/ABS(G10),0) | P10: =IF(AND(B10="SELL",D10>0),R10/D10,0) | Q10: =IF(AND(B10="SELL",D10>0,E10>0),(D10/E10)+G10,0) | R10: =IF(B10="SELL",Q10*F10,0) | S10: =S9+R10
A11: 10 | B11: SELL | C11: 46025 | D11: 250000 | E11: 912 | F11: 912 | G11: -224.27 | I11: 485.03 | J11: 598.6 | K11: =IF(AND(B11="SELL",E11>0,J11<>""),J11/E11,0) | L11: 0.537 | M11: =IF(AND(B11="SELL",L11>0),D11*L11,0) | O11: =IF(AND(B11="SELL",G11<>0),Q11/ABS(G11),0) | P11: =IF(AND(B11="SELL",D11>0),R11/D11,0) | Q11: =IF(AND(B11="SELL",D11>0,E11>0),(D11/E11)+G11,0) | R11: =IF(B11="SELL",Q11*F11,0) | S11: =S10+R11
A12: 11 | B12: SELL | C12: 46025 | D12: 60000 | E12: 912 | F12: 912 | G12: -56.42 | I12: 428.61 | J12: 570 | K12: =IF(AND(B12="SELL",E12>0,J12<>""),J12/E12,0) | L12: 0.536 | M12: =IF(AND(B12="SELL",L12>0),D12*L12,0) | O12: =IF(AND(B12="SELL",G12<>0),Q12/ABS(G12),0) | P12: =IF(AND(B12="SELL",D12>0),R12/D12,0) | Q12: =IF(AND(B12="SELL",D12>0,E12>0),(D12/E12)+G12,0) | R12: =IF(B12="SELL",Q12*F12,0) | S12: =S11+R12
A13: 12 | B13: SELL | C13: 46025 | D13: 50000 | E13: 912 | F13: 912 | G13: -48.68 | I13: 379.93 | J13: 550.5 | K13: =IF(AND(B13="SELL",E13>0,J13<>""),J13/E13,0) | L13: 0.536 | M13: =IF(AND(B13="SELL",L13>0),D13*L13,0) | O13: =IF(AND(B13="SELL",G13<>0),Q13/ABS(G13),0) | P13: =IF(AND(B13="SELL",D13>0),R13/D13,0) | Q13: =IF(AND(B13="SELL",D13>0,E13>0),(D13/E13)+G13,0) | R13: =IF(B13="SELL",Q13*F13,0) | S13: =S12+R13
A14: 13 | B14: SELL | C14: 46025 | D14: 120000 | E14: 912 | F14: 912 | G14: -116.03 | I14: 263.9 | J14: 554.3 | K14: =IF(AND(B14="SELL",E14>0,J14<>""),J14/E14,0) | L14: 0.536 | M14: =IF(AND(B14="SELL",L14>0),D14*L14,0) | O14: =IF(AND(B14="SELL",G14<>0),Q14/ABS(G14),0) | P14: =IF(AND(B14="SELL",D14>0),R14/D14,0) | Q14: =IF(AND(B14="SELL",D14>0,E14>0),(D14/E14)+G14,0) | R14: =IF(B14="SELL",Q14*F14,0) | S14: =S13+R14
... A16: 15 | B16: SELL | C16: 46025 | D16: 100000 | E16: 912 | F16: 912 | G16: -99.81 | I16: 130.21 | J16: 541 | K16: =IF(AND(B16="SELL",E16>0,J16<>""),J16/E16,0) | L16: 0.54 | M16: =IF(AND(B16="SELL",L16>0),D16*L16,0) | O16: =IF(AND(B16="SELL",G16<>0),Q16/ABS(G16),0) | P16: =IF(AND(B16="SELL",D16>0),R16/D16,0) | Q16: =IF(AND(B16="SELL",D16>0,E16>0),(D16/E16)+G16,0) | R16: =IF(B16="SELL",Q16*F16,0) | S16: =S15+R16
A17: 16 | B17: BUY | C17: 46025 | D17: 2559600 | E17: 912.94 | F17: 912.94 | G17: 2803.68 | I17: 2933.89 | K17: =IF(AND(B17="SELL",E17>0,J17<>""),J17/E17,0) | L17: 0 | M17: =IF(AND(B17="SELL",L17>0),D17*L17,0) | O17: =IF(AND(B17="SELL",G17<>0),Q17/ABS(G17),0) | P17: =IF(AND(B17="SELL",D17>0),R17/D17,0) | Q17: =IF(AND(B17="SELL",D17>0,E17>0),(D17/E17)+G17,0) | R17: =IF(B17="SELL",Q17*F17,0) | S17: =S16+R17
A18: 17 | B18: SELL | C18: 46025 | D18: 30000 | E18: 912.94 | F18: 912.94 | G18: -30.09 | I18: 2903.8 | J18: 535 | K18: =IF(AND(B18="SELL",E18>0,J18<>""),J18/E18,0) | L18: 0.536 | M18: =IF(AND(B18="SELL",L18>0),D18*L18,0) | O18: =IF(AND(B18="SELL",G18<>0),Q18/ABS(G18),0) | P18: =IF(AND(B18="SELL",D18>0),R18/D18,0) | Q18: =IF(AND(B18="SELL",D18>0,E18>0),(D18/E18)+G18,0) | R18: =IF(B18="SELL",Q18*F18,0) | S18: =S17+R18
A19: 18 | B19: SELL | C19: 46025 | D19: 200000 | E19: 912.94 | F19: 912.94 | G19: -189.9 | I19: 2713.9 | J19: 568.702 | K19: =IF(AND(B19="SELL",E19>0,J19<>""),J19/E19,0) | L19: 0.54 | M19: =IF(AND(B19="SELL",L19>0),D19*L19,0) | O19: =IF(AND(B19="SELL",G19<>0),Q19/ABS(G19),0) | P19: =IF(AND(B19="SELL",D19>0),R19/D19,0) | Q19: =IF(AND(B19="SELL",D19>0,E19>0),(D19/E19)+G19,0) | R19: =IF(B19="SELL",Q19*F19,0) | S19: =S18+R19
A20: 19 | B20: SELL | C20: 46025 | D20: 30000 | E20: 912.94 | F20: 912.94 | G20: -29.17 | I20: 2684.73 | J20: 551.088 | K20: =IF(AND(B20="SELL",E20>0,J20<>""),J20/E20,0) | L20: 0.536 | M20: =IF(AND(B20="SELL",L20>0),D20*L20,0) | O20: =IF(AND(B20="SELL",G20<>0),Q20/ABS(G20),0) | P20: =IF(AND(B20="SELL",D20>0),R20/D20,0) | Q20: =IF(AND(B20="SELL",D20>0,E20>0),(D20/E20)+G20,0) | R20: =IF(B20="SELL",Q20*F20,0) | S20: =S19+R20
A21: 20 | B21: SELL | C21: 46025 | D21: 222000 | E21: 912.94 | F21: 912.94 | G21: -205.37 | I21: 2479.36 | J21: 583.7 | K21: =IF(AND(B21="SELL",E21>0,J21<>""),J21/E21,0) | L21: 0.54 | M21: =IF(AND(B21="SELL",L21>0),D21*L21,0) | O21: =IF(AND(B21="SELL",G21<>0),Q21/ABS(G21),0) | P21: =IF(AND(B21="SELL",D21>0),R21/D21,0) | Q21: =IF(AND(B21="SELL",D21>0,E21>0),(D21/E21)+G21,0) | R21: =IF(B21="SELL",Q21*F21,0) | S21: =S20+R21
A22: 21 | B22: SELL | C22: 46025 | D22: 30000 | E22: 912.94 | F22: 912.94 | G22: -29.22 | I22: 2450.14 | J22: 550.155 | K22: =IF(AND(B22="SELL",E22>0,J22<>""),J22/E22,0) | L22: 0.536 | M22: =IF(AND(B22="SELL",L22>0),D22*L22,0) | O22: =IF(AND(B22="SELL",G22<>0),Q22/ABS(G22),0) | P22: =IF(AND(B22="SELL",D22>0),R22/D22,0) | Q22: =IF(AND(B22="SELL",D22>0,E22>0),(D22/E22)+G22,0) | R22: =IF(B22="SELL",Q22*F22,0) | S22: =S21+R22
A23: 22 | B23: SELL | C23: 46025 | D23: 45000 | E23: 912.94 | F23: 912.94 | G23: -42.69 | I23: 2407.45 | J23: 565 | K23: =IF(AND(B23="SELL",E23>0,J23<>""),J23/E23,0) | L23: 0.536 | M23: =IF(AND(B23="SELL",L23>0),D23*L23,0) | O23: =IF(AND(B23="SELL",G23<>0),Q23/ABS(G23),0) | P23: =IF(AND(B23="SELL",D23>0),R23/D23,0) | Q23: =IF(AND(B23="SELL",D23>0,E23>0),(D23/E23)+G23,0) | R23: =IF(B23="SELL",Q23*F23,0) | S23: =S22+R23
A24: 23 | B24: SELL | C24: 46025 | D24: 30000 | E24: 912.94 | F24: 912.94 | G24: -29.09 | I24: 2378.36 | J24: 591.1 | K24: =IF(AND(B24="SELL",E24>0,J24<>""),J24/E24,0) | L24: 0.573 | M24: =IF(AND(B24="SELL",L24>0),D24*L24,0) | O24: =IF(AND(B24="SELL",G24<>0),Q24/ABS(G24),0) | P24: =IF(AND(B24="SELL",D24>0),R24/D24,0) | Q24: =IF(AND(B24="SELL",D24>0,E24>0),(D24/E24)+G24,0) | R24: =IF(B24="SELL",Q24*F24,0) | S24: =S23+R24
A25: 24 | B25: SELL | C25: 46025 | D25: 20000 | E25: 912.94 | F25: 912.94 | G25: -19.26 | I25: 2359.1 | J25: 595 | K25: =IF(AND(B25="SELL",E25>0,J25<>""),J25/E25,0) | L25: 0.573 | M25: =IF(AND(B25="SELL",L25>0),D25*L25,0) | O25: =IF(AND(B25="SELL",G25<>0),Q25/ABS(G25),0) | P25: =IF(AND(B25="SELL",D25>0),R25/D25,0) | Q25: =IF(AND(B25="SELL",D25>0,E25>0),(D25/E25)+G25,0) | R25: =IF(B25="SELL",Q25*F25,0) | S25: =S24+R25
A26: 25 | B26: SELL | C26: 46026 | D26: 30000 | E26: 912.94 | F26: 912.94 | G26: -30.69 | I26: 2328.41 | J26: 592.3 | K26: =IF(AND(B26="SELL",E26>0,J26<>""),J26/E26,0) | L26: 0.606 | M26: =IF(AND(B26="SELL",L26>0),D26*L26,0) | O26: =IF(AND(B26="SELL",G26<>0),Q26/ABS(G26),0) | P26: =IF(AND(B26="SELL",D26>0),R26/D26,0) | Q26: =IF(AND(B26="SELL",D26>0,E26>0),(D26/E26)+G26,0) | R26: =IF(B26="SELL",Q26*F26,0) | S26: =S25+R26
A27: 26 | B27: SELL | C27: 46027 | D27: 50000 | E27: 912.94 | F27: 912.94 | G27: -50.24 | I27: 2278.17 | J27: 595.077 | K27: =IF(AND(B27="SELL",E27>0,J27<>""),J27/E27,0) | L27: 0.598 | M27: =IF(AND(B27="SELL",L27>0),D27*L27,0) | O27: =IF(AND(B27="SELL",G27<>0),Q27/ABS(G27),0) | P27: =IF(AND(B27="SELL",D27>0),R27/D27,0) | Q27: =IF(AND(B27="SELL",D27>0,E27>0),(D27/E27)+G27,0) | R27: =IF(B27="SELL",Q27*F27,0) | S27: =S26+R27
A28: 27 | B28: SELL | C28: 46027 | D28: 50000 | E28: 912.94 | F28: 912.94 | G28: -50.59 | I28: 2227.58 | J28: 591 | K28: =IF(AND(B28="SELL",E28>0,J28<>""),J28/E28,0) | L28: 0.598 | M28: =IF(AND(B28="SELL",L28>0),D28*L28,0) | O28: =IF(AND(B28="SELL",G28<>0),Q28/ABS(G28),0) | P28: =IF(AND(B28="SELL",D28>0),R28/D28,0) | Q28: =IF(AND(B28="SELL",D28>0,E28>0),(D28/E28)+G28,0) | R28: =IF(B28="SELL",Q28*F28,0) | S28: =S27+R28
A29: 28 | B29: SELL | C29: 46027 | D29: 10000 | E29: 912.94 | F29: 912.94 | G29: -9.97 | I29: 2217.61 | J29: 599.511 | K29: =IF(AND(B29="SELL",E29>0,J29<>""),J29/E29,0) | L29: 0.598 | M29: =IF(AND(B29="SELL",L29>0),D29*L29,0) | O29: =IF(AND(B29="SELL",G29<>0),Q29/ABS(G29),0) | P29: =IF(AND(B29="SELL",D29>0),R29/D29,0) | Q29: =IF(AND(B29="SELL",D29>0,E29>0),(D29/E29)+G29,0) | R29: =IF(B29="SELL",Q29*F29,0) | S29: =S28+R29
... A42: 41 | B42: SELL | C42: 46028 | D42: 20000 | E42: 912.94 | F42: 912.94 | G42: -17.8 | I42: 1311.53 | J42: 707.5 | K42: =IF(AND(B42="SELL",E42>0,J42<>""),J42/E42,0) | L42: 0.63 | M42: =IF(AND(B42="SELL",L42>0),D42*L42,0) | O42: =IF(AND(B42="SELL",G42<>0),Q42/ABS(G42),0) | P42: =IF(AND(B42="SELL",D42>0),R42/D42,0) | Q42: =IF(AND(B42="SELL",D42>0,E42>0),(D42/E42)+G42,0) | R42: =IF(B42="SELL",Q42*F42,0) | S42: =S41+R42
A43: 42 | B43: SELL | C43: 46028 | D43: 30000 | E43: 912.94 | F43: 912.94 | G43: -31.05 | I43: 1270.48 | J43: 539 | K43: =IF(AND(B43="SELL",E43>0,J43<>""),J43/E43,0) | L43: 0.558 | M43: =IF(AND(B43="SELL",L43>0),D43*L43,0) | N43: de diciembre | O43: =IF(AND(B43="SELL",G43<>0),Q43/ABS(G43),0) | P43: =IF(AND(B43="SELL",D43>0),R43/D43,0) | Q43: =IF(AND(B43="SELL",D43>0,E43>0),(D43/E43)+G43,0) | R43: =IF(B43="SELL",Q43*F43,0) | S43: =S42+R43
A44: 43 | B44: SELL | C44: 46029 | D44: 20000 | E44: 912.94 | F44: 912.94 | G44: -19.08 | I44: 1247.2 | J44: 811.1 | K44: =IF(AND(B44="SELL",E44>0,J44<>""),J44/E44,0) | L44: 0.774 | M44: =IF(AND(B44="SELL",L44>0),D44*L44,0) | O44: =IF(AND(B44="SELL",G44<>0),Q44/ABS(G44),0) | P44: =IF(AND(B44="SELL",D44>0),R44/D44,0) | Q44: =IF(AND(B44="SELL",D44>0,E44>0),(D44/E44)+G44,0) | R44: =IF(B44="SELL",Q44*F44,0) | S44: =S43+R44
A45: 44 | B45: SELL | C45: 46029 | D45: 40000 | E45: 912.94 | F45: 912.94 | G45: -37.77 | I45: 1209.43 | J45: 819.6 | K45: =IF(AND(B45="SELL",E45>0,J45<>""),J45/E45,0) | L45: 0.774 | M45: =IF(AND(B45="SELL",L45>0),D45*L45,0) | O45: =IF(AND(B45="SELL",G45<>0),Q45/ABS(G45),0) | P45: =IF(AND(B45="SELL",D45>0),R45/D45,0) | Q45: =IF(AND(B45="SELL",D45>0,E45>0),(D45/E45)+G45,0) | R45: =IF(B45="SELL",Q45*F45,0) | S45: =S44+R45
A46: 45 | B46: SELL | C46: 46029 | D46: 20000 | E46: 912.94 | F46: 912.94 | G46: -18.78 | I46: 1190.65 | J46: 824 | K46: =IF(AND(B46="SELL",E46>0,J46<>""),J46/E46,0) | L46: 0.774 | M46: =IF(AND(B46="SELL",L46>0),D46*L46,0) | O46: =IF(AND(B46="SELL",G46<>0),Q46/ABS(G46),0) | P46: =IF(AND(B46="SELL",D46>0),R46/D46,0) | Q46: =IF(AND(B46="SELL",D46>0,E46>0),(D46/E46)+G46,0) | R46: =IF(B46="SELL",Q46*F46,0) | S46: =S45+R46
A47: 46 | B47: SELL | C47: 46029 | D47: 10000 | E47: 912.94 | F47: 912.94 | G47: -10.85 | I47: 1179.8 | J47: 713.2 | K47: =IF(AND(B47="SELL",E47>0,J47<>""),J47/E47,0) | L47: 0.774 | M47: =IF(AND(B47="SELL",L47>0),D47*L47,0) | O47: =IF(AND(B47="SELL",G47<>0),Q47/ABS(G47),0) | P47: =IF(AND(B47="SELL",D47>0),R47/D47,0) | Q47: =IF(AND(B47="SELL",D47>0,E47>0),(D47/E47)+G47,0) | R47: =IF(B47="SELL",Q47*F47,0) | S47: =S46+R47
